Workbook

Sheet Week of 46-410
B1: CW | C1: Fortune | D1: Viola | E1: A1 Firewood | F1: Wabash | G1: Superior | H1: Aya | I1: Closed Loop | J1: Testa | K1: Cornille | L1: Rare Tea Cellar | M1: Steve's | N1: Turano | O1: Daily Spend | P1: Daily Revenue | Q1: Daily Cost %
A2: Wednesday | B2: 5570.11 | C2: 1407.23 | D2: 446.88 | E2: 390 | I2: 242 | M2: 100 | O2: =SUM(B2:N2) -> 8156.22 | P2: 7462 | Q2: =O2/P2 -> 1.093034
A3: Thursday | B3: 2108.57 | C3: 261.09 | K3: 800 | O3: =SUM(B3:N3) -> 3169.66 | P3: 6777.8 | Q3: =O3/P3 -> 0.46765322
A4: Friday | B4: 1452.79 | C4: 266.5 | G4: 355 | H4: 127.3 | J4: 370.5 | L4: 52 | M4: 100 | N4: 277.41 | O4: =SUM(B4:N4) -> 3001.5 | P4: 9749 | Q4: =O4/P4 -> 0.30787773
A5: Saturday | B5: 1533.03 | C5: 928.1 | O5: =SUM(B5:N5) -> 2461.13 | P5: =3555+10500.8 -> 14055.8 | Q5: =O5/P5 -> 0.17509711
A6: Sunday | B6: N/A | C6: N/A | D6: N/A | E6: N/A | G6: N/A | H6: 45.6 | I6: N/A | J6: N/A | K6: N/A | L6: N/A | M6: N/A | N6: N/A | O6: 0 | P6: 9949 | Q6: =O6/P6 -> 0
A9: Budget | B9: 14000
A10: Total Weekly Spend | B10: =SUM(B2:N6) -> 16834.11
A11: Remaing Spend | B11: =SUM(B9-B10) -> -2834.11
A13: Weekly Food Revenue | B13: =SUM(P2:P6) -> 47993.6
A14: Weekly Cost % | B14: =B10/B13 -> 0.35075739
A17: End of week status
A18: list items over $100
A19: Items carrying over | B19: Amount | C19: Items discarded | D19: Amount
A23: Duck week 1
A25: Duck Week 2
A27: Duck Week 3
A32: Total | B32: =sum(B20:B31) -> 0 | D32: =sum(D20:D31) -> 0

Sheet Week of 413-417
B1: CW | C1: Fortune | D1: Viola | E1: A1 Firewood | F1: Superior | G1: Aya | H1: Closed Loop | I1: Truffles/ carryover | J1: Cornille | K1: Rare Tea Cellar | L1: Steve's | M1: Turano | N1: Daily Spend | O1: Daily Revenue | P1: Daily Cost %
A2: Wednesday | B2: 5315.67 | C2: 754.4 | E2: 390 | F2: 177.5 | H2: 242 | I2: 500 | K2: 46.5 | L2: 100 | N2: =SUM(B2:M2) -> 7526.07 | O2: 7831.47 | P2: =N2/O2 -> 0.96100349
A3: Thursday | B3: 1600.5 | C3: 90.4 | D3: 446.88 | J3: 450 | N3: =SUM(B3:M3) -> 2587.78 | O3: 8512.1 | P3: =N3/O3 -> 0.30401194
A4: Friday | B4: 1278.77 | C4: 473.8 | G4: 127.3 | I4: 370.5 | L4: 100 | M4: 277.41 | N4: =SUM(B4:M4) -> 2627.78 | O4: 10478 | P4: =N4/O4 -> 0.25079023
A5: Saturday | B5: 1675.34 | C5: 310.4 | K5: 19 | N5: =SUM(B5:M5) -> 2004.74 | O5: 13260 | P5: =N5/O5 -> 0.15118703
A6: Sunday | B6: N/A | C6: N/A | D6: N/A | E6: N/A | F6: N/A | G6: N/A | H6: N/A | I6: N/A | J6: N/A | K6: N/A | L6: N/A | M6: N/A | N6: 0 | O6: 10550 | P6: =N6/O6 -> 0
A9: Budget | B9: 14000
A10: Total Weekly Spend | B10: =SUM(B2:M6) -> 14746.37
A11: Remaing Spend | B11: =SUM(B9-B10) -> -746.37
A13: Weekly Food Revenue | B13: =SUM(O2:O6) -> 50631.57
A14: Weekly Cost % | B14: =B10/B13 -> 0.29124852
A17: End of week status
A18: list items over $100
A19: Items carrying over | B19: Amount | C19: Items discarded | D19: Amount
A32: Total | B32: =sum(B20:B31) -> 0 | D32: =sum(D20:D31) -> 0

Sheet (Roister)Week of 420- 424
B1: CW | C1: Fortune | D1: Viola | E1: A1 Firewood | F1: Superior | G1: Aya | H1: Closed Loop | I1: Truffles/ carryover | J1: Cornille | K1: Rare Tea Cellar | L1: Steve's | M1: Turano | N1: Daily Spend | O1: Daily Revenue | P1: Daily Cost %
A2: Wednesday | B2: 4808.69 | C2: 1633.2 | E2: 390 | H2: 242 | I2: 370.5 | K2: 52 | L2: 100 | N2: =SUM(B2:M2) -> 7596.39 | O2: 7097 | P2: =N2/O2 -> 1.0703664
A3: Thursday | B3: 1152.18 | C3: 138.7 | D3: 446.88 | J3: 400 | N3: =SUM(B3:M3) -> 2137.76 | O3: 6330 | P3: =N3/O3 -> 0.3377188
A4: Friday | B4: 2399.9 | C4: 491.48 | G4: 127.3 | L4: 100 | M4: 277.41 | N4: =SUM(B4:M4) -> 3396.09 | P4: =N4/O4 -> #DIV/0!
A5: Saturday | B5: 1551.56 | C5: 402.25 | I5: 370.5 | N5: =SUM(B5:M5) -> 2324.31 | O5: 16070.01 | P5: =N5/O5 -> 0.1446365
A6: Sunday | B6: N/A | C6: N/A | D6: N/A | E6: N/A | F6: N/A | G6: N/A | H6: N/A | I6: N/A | J6: N/A | K6: N/A | L6: N/A | M6: N/A | N6: 0 | O6: 13009.5 | P6: =N6/O6 -> 0
A9: Budget | B9: 14000
A10: Total Weekly Spend | B10: =SUM(B2:M6) -> 15454.55
A11: Remaing Spend | B11: =SUM(B9-B10) -> -1454.55
A13: Weekly Food Revenue | B13: =SUM(O2:O6) -> 42506.51
A14: Weekly Cost % | B14: =B10/B13 -> 0.36358078
A17: End of week status
A18: list items over $100
A19: Items carrying over | B19: Amount | C19: Items discarded | D19: Amount
A32: Total | B32: =sum(B20:B31) -> 0 | D32: =sum(D20:D31) -> 0

Sheet (Roister) Week of 54- 58
B1: CW | C1: Fortune | D1: Viola | E1: A1 Firewood | F1: Superior | G1: Aya | H1: Closed Loop | I1: Truffles/ carryover | J1: Cornille | K1: Rare Tea Cellar | L1: Steve's | M1: Turano | N1: Daily Spend | O1: Daily Revenue | P1: Daily Cost %
A2: Wednesday | B2: 4940.53 | C2: 1684.15 | E2: 390 | F2: 355 | H2: 242 | K2: 39 | L2: 100 | N2: =SUM(B2:M2) -> 7750.68 | O2: 7362 | P2: =N2/O2 -> 1.0527954
A3: Thursday | B3: 1751.9 | C3: 269 | D3: 446.88 | J3: 350 | N3: =SUM(B3:M3) -> 2817.78 | O3: 10200.96 | P3: =N3/O3 -> 0.27622694
A4: Friday | B4: 1650.04 | C4: 593.85 | G4: 127.3 | L4: 100 | M4: 277.41 | N4: =SUM(B4:M4) -> 2748.6 | O4: 11475.8 | P4: =N4/O4 -> 0.23951271
A5: Saturday | B5: 2131.75 | C5: 200.3 | F5: 245.64 | G5: 76 | N5: =SUM(B5:M5) -> 2653.69 | O5: 17111.5 | P5: =N5/O5 -> 0.15508225
A6: Sunday | B6: N/A | C6: N/A | D6: N/A | E6: N/A | F6: N/A | G6: N/A | H6: N/A | I6: N/A | J6: N/A | K6: N/A | L6: N/A | M6: N/A | N6: 0 | O6: 12811 | P6: =N6/O6 -> 0
A9: Budget | B9: 14000
A10: Total Weekly Spend | B10: =SUM(B2:M6) -> 15970.75
A11: Remaing Spend | B11: =SUM(B9-B10) -> -1970.75
A13: Weekly Food Revenue | B13: =SUM(O2:O6) -> 58961.26
A14: Weekly Cost % | B14: =B10/B13 -> 0.27086853
A17: End of week status
A18: list items over $100
A19: Items carrying over | B19: Amount | C19: Items discarded | D19: Amount
A32: Total | B32: =sum(B20:B31) -> 0 | D32: =sum(D20:D31) -> 0

Sheet (Roister) Week of 427-51
B1: CW | C1: Fortune | D1: Viola | E1: A1 Firewood | F1: Superior | G1: Aya | H1: Closed Loop | I1: Truffles/ carryover | J1: Cornille | K1: Rare Tea Cellar | L1: Steve's | M1: Turano | N1: Daily Spend | O1: Daily Revenue | P1: Daily Cost %
A2: Wednesday | B2: 5588.35 | C2: 1525 | E2: 390 | F2: 248.95 | H2: 242 | K2: 15.95 | L2: 100 | N2: =SUM(B2:M2) -> 8110.25 | O2: 7023.01 | P2: =N2/O2 -> 1.1548111
A3: Thursday | B3: 2447.87 | C3: 243.93 | D3: 446.88 | I3: 370.15 | N3: =SUM(B3:M3) -> 3508.83 | O3: 8057 | P3: =N3/O3 -> 0.43550081
A4: Friday | B4: 2193.28 | C4: 234.15 | G4: 127.3 | L4: 100 | M4: 277.41 | N4: =SUM(B4:M4) -> 2932.14 | O4: 10393.4 | P4: =N4/O4 -> 0.28211557
A5: Saturday | B5: 2361.93 | C5: 146.8 | I5: 370.15 | K5: 25 | N5: =SUM(B5:M5) -> 2903.88 | O5: 14361 | P5: =N5/O5 -> 0.20220597
A6: Sunday | B6: N/A | C6: N/A | D6: N/A | E6: N/A | F6: N/A | G6: N/A | H6: N/A | I6: N/A | J6: N/A | K6: N/A | L6: N/A | M6: N/A | N6: 0 | O6: 11288.6 | P6: =N6/O6 -> 0
A9: Budget | B9: 14000
A10: Total Weekly Spend | B10: =SUM(B2:M6) -> 17455.1
A11: Remaing Spend | B11: =SUM(B9-B10) -> -3455.1
A13: Weekly Food Revenue | B13: =SUM(O2:O6) -> 51123.01
A14: Weekly Cost % | B14: =B10/B13 -> 0.34143334
A17: End of week status
A18: list items over $100
A19: Items carrying over | B19: Amount | C19: Items discarded | D19: Amount
A32: Total | B32: =sum(B20:B31) -> 0 | D32: =sum(D20:D31) -> 0

Sheet Roister Week of 519- 523
B1: CW | C1: Fortune | D1: Viola | E1: A1 Firewood | F1: Superior | G1: Aya | H1: Closed Loop | I1: Truffles/ carryover | J1: Cornille | K1: Rare Tea Cellar | L1: Steve's | M1: Turano | N1: Daily Spend | O1: Daily Revenue | P1: Daily Cost %
A2: Wednesday | B2: 3552.49 | C2: 309.3 | E2: 390 | F2: 355 | H2: 242 | I2: 440 | L2: 100 | N2: =SUM(B2:M2) -> 5388.79 | O2: 0 | P2: =N2/O2 -> #DIV/0!
A3: Thursday | B3: 871.14 | C3: 532.96 | D3: 446.88 | N3: =SUM(B3:M3) -> 1850.98 | O3: 17208.75 | P3: =N3/O3 -> 0.1075604
A4: Friday | B4: 2065.2 | C4: 466.8 | G4: 127.3 | J4: 800 | K4: 44.5 | L4: 100 | M4: 277.41 | N4: =SUM(B4:M4) -> 3881.21 | O4: 13514 | P4: =N4/O4 -> 0.2871992
A5: Saturday | B5: 2482.46 | C5: 1042.79 | N5: =SUM(B5:M5) -> 3525.25 | O5: 20288.1 | P5: =N5/O5 -> 0.17375949
A6: Sunday | B6: N/A | C6: N/A | D6: N/A | E6: N/A | F6: N/A | G6: N/A | H6: N/A | I6: N/A | J6: N/A | K6: N/A | L6: N/A | M6: N/A | N6: 0 | O6: 20679 | P6: =N6/O6 -> 0
A9: Budget | B9: 14000
A10: Total Weekly Spend | B10: =SUM(B2:M6) -> 14646.23
A11: Remaing Spend | B11: =SUM(B9-B10) -> -646.23
A13: Weekly Food Revenue | B13: =SUM(O2:O6) -> 71689.85
A14: Weekly Cost % | B14: =B10/B13 -> 0.20429991

Sheet Roister (511-515)
B1: CW | C1: Fortune | D1: Viola | E1: A1 Firewood | F1: Superior | G1: Aya | H1: Closed Loop | I1: Truffles/ carryover | J1: Cornille | K1: Rare Tea Cellar | L1: Steve's | M1: Turano | N1: Daily Spend | O1: Daily Revenue | P1: Daily Cost %
A2: Wednesday | B2: 3196.04 | C2: 284.63 | E2: 390 | H2: 242 | K2: 183.45 | L2: 100 | N2: =SUM(B2:M2) -> 4396.12 | O2: 8400.5 | P2: =N2/O2 -> 0.52331647
A3: Thursday | B3: 1692.44 | C3: 550.86 | D3: 446.88 | J3: 350 | N3: =SUM(B3:M3) -> 3040.18 | O3: 10570.5 | P3: =N3/O3 -> 0.28760986
A4: Friday | B4: 1448.71 | C4: 185 | I4: 1000 | N4: =SUM(B4:M4) -> 2633.71 | O4: 15153 | P4: =N4/O4 -> 0.17380783
A5: Saturday | N5: =SUM(B5:M5) -> 0 | P5: =N5/O5 -> #DIV/0!
A6: Sunday | B6: N/A | C6: N/A | D6: N/A | E6: N/A | F6: N/A | G6: N/A | H6: N/A | I6: N/A | J6: N/A | K6: N/A | L6: N/A | M6: N/A | N6: 0 | P6: =N6/O6 -> #DIV/0!
A9: Budget | B9: 14000
A10: Total Weekly Spend | B10: =SUM(B2:M6) -> 10070.01
A11: Remaing Spend | B11: =SUM(B9-B10) -> 3929.99
A13: Weekly Food Revenue | B13: =SUM(O2:O6) -> 34124
A14: Weekly Cost % | B14: =B10/B13 -> 0.29510052
A17: End of week status
A18: list items over $100
A19: Items carrying over | B19: Amount | C19: Items discarded | D19: Amount
A32: Total | B32: =sum(B20:B31) -> 0 | D32: =sum(D20:D31) -> 0

Sheet Week of 525-529
B1: CW | C1: Fortune | D1: Viola | E1: A1 Firewood | F1: Superior | G1: Aya | H1: Closed Loop | I1: Truffles | J1: Cornille | K1: Rare Tea Cellar | L1: Steve's | M1: Turano | N1: Daily Spend | O1: Daily Revenue | P1: Daily Cost %
A2: Monday | B2: 2653.7 | C2: 1042.79 | I2: 440 | K2: 49.5 | N2: =SUM(B2:M2) -> 4185.99 | O2: 13711 | P2: =N2/O2 -> 0.30530158
A3: Wednesday | B3: 5982.13 | C3: 1314.46 | D3: 446.88 | E3: 390 | H3: 242 | K3: 168 | L3: 100 | N3: =SUM(B3:M3) -> 8643.47 | O3: 8168.6 | P3: =N3/O3 -> 1.0581336
A4: Thursday | B4: 3616.3 | C4: 1053.03 | N4: =SUM(B4:M4) -> 4669.33 | O4: 9119.2 | P4: =N4/O4 -> 0.51203285
A5: Friday | B5: 1049.5 | C5: 722.07 | F5: 248.5 | G5: 127.3 | L5: 100 | M5: 277.41 | N5: =SUM(B5:M5) -> 2524.78 | O5: 13446 | P5: =N5/O5 -> 0.18777183
A6: Saturday | B6: 2983.87 | C6: 722.07 | G6: 45.6 | K6: 44.5 | N6: =SUM(C6:M6) -> 812.17 | O6: 20810 | P6: =N6/O6 -> 0.039027871
A7: Sunday | B7: N/A | C7: N/A | D7: N/A | E7: N/A | F7: N/A | G7: N/A | H7: N/A | I7: N/A | J7: N/A | K7: N/A | L7: N/A | M7: N/A | N7: 0 | O7: 19021.53 | P7: =N7/O7 -> 0
A9: Budget | B9: 14000
A10: Total Weekly Spend | B10: =SUM(B3:M7) -> 19633.62
A11: Remaing Spend | B11: =SUM(B9-B10) -> -5633.62 | I11: 6 ribeyes
A13: Weekly Food Revenue | B13: =SUM(O2:O7) -> 84276.33
A14: Weekly Cost % | B14: =B10/B13 -> 0.23296719

Sheet Roister week of (61-65)
B1: CW | C1: Fortune | D1: Viola | E1: A1 Firewood | F1: Superior | G1: Aya | H1: Closed Loop | I1: Truffles/ carryover | J1: Cornille | K1: Rare Tea Cellar | L1: Steve's | M1: Turano | N1: Daily Spend | O1: Daily Revenue | P1: Daily Cost %
A2: Wednesday | B2: 4777.09 | C2: 725.25 | E2: 390 | F2: 355 | H2: 242 | K2: 67.5 | L2: 100 | N2: =SUM(B2:M2) -> 6656.84 | O2: 8581 | P2: =N2/O2 -> 0.77576506
A3: Thursday | B3: 2135.6 | C3: 368.04 | D3: 510.72 | I3: 440 | J3: 750 | N3: =SUM(B3:M3) -> 4204.36 | O3: 0 | P3: =N3/O3 -> #DIV/0!
A4: Friday | B4: 1113.2 | C4: 444.81 | G4: 127.3 | L4: 100 | M4: 277.41 | N4: =SUM(B4:M4) -> 2062.72 | O4: 15905.6 | P4: =N4/O4 -> 0.12968514
A5: Saturday | B5: 1834.33 | C5: 485.4 | N5: =SUM(B5:M5) -> 2319.73 | O5: =3947+16083 -> 20030 | P5: =N5/O5 -> 0.11581278
A6: Sunday | B6: N/A | C6: N/A | D6: N/A | E6: N/A | F6: N/A | G6: N/A | H6: N/A | I6: N/A | J6: N/A | K6: N/A | L6: N/A | M6: N/A | N6: 0 | O6: 13700.2 | P6: =N6/O6 -> 0
A9: Budget | B9: 14000
A10: Total Weekly Spend | B10: =SUM(B2:M6) -> 15243.65
A11: Remaing Spend | B11: =SUM(B9-B10) -> -1243.65
A13: Weekly Food Revenue | B13: =SUM(O2:O6) -> 58216.8
A14: Weekly Cost % | B14: =B10/B13 -> 0.2618428

Sheet Roister week of (68-612)
B1: CW | C1: Fortune | D1: Viola | E1: A1 Firewood | F1: Superior | G1: Aya | H1: Closed Loop | I1: D'artagnan | J1: Cornille | K1: Rare Tea Cellar | L1: Steve's | M1: Turano | N1: Daily Spend | O1: Daily Revenue | P1: Daily Cost %
A2: Wednesday | B2: 5671.82 | C2: 698.37 | D2: 510.72 | E2: 390 | F2: 783.75 | H2: 242 | I2: 3662.58 | K2: 68 | L2: 100 | N2: =SUM(B2:M2) -> 12127.24 | O2: 13068 | P2: =N2/O2 -> 0.92801041
A3: Thursday | B3: 1982.7 | C3: 723.65 | N3: =SUM(B3:M3) -> 2706.35 | O3: 12027 | P3: =N3/O3 -> 0.22502287
A4: Friday | B4: 2547.85 | C4: 996.64 | G4: 127.3 | I4: 1836.89 | L4: 100 | M4: 277.41 | N4: =SUM(B4:M4) -> 5886.09 | O4: 13246.6 | P4: =N4/O4 -> 0.44434723
A5: Saturday | B5: 2786.88 | C5: 928.1 | N5: =SUM(B5:M5) -> 3714.98 | O5: 17921.8 | P5: =N5/O5 -> 0.20728833
A6: Sunday | B6: N/A | C6: N/A | D6: N/A | E6: N/A | F6: N/A | G6: 45.6 | H6: N/A | I6: N/A | J6: N/A | K6: N/A | L6: N/A | M6: N/A | N6: 0 | O6: 19133.9 | P6: =N6/O6 -> 0
A9: Budget | B9: 14000
A10: Total Weekly Spend | B10: =SUM(B2:M6) -> 24480.26
A11: Remaing Spend | B11: =SUM(B9-B10) -> -10480.26
A13: Weekly Food Revenue | B13: =SUM(O2:O6) -> 75397.3
A14: Weekly Cost % | B14: =B10/B13 -> 0.32468351
A17: End of week status
A18: list items over $100
A19: Items carrying over | B19: Amount | C19: Items discarded | D19: Amount
A20: Short Ribs | B20: 3662.58
A32: Total | B32: =sum(B20:B31) -> 3662.58 | D32: =sum(D20:D31) -> 0

Sheet Roister week of (615-619)
B1: CW | C1: Fortune | D1: Viola | E1: A1 Firewood | F1: Superior | G1: Regalis | H1: Aya | I1: Closed Loop | J1: Rocker Bros | K1: Cornille | L1: Rare Tea Cellar | M1: D'artagnan | N1: Steve's | O1: Turano | P1: Daily Spend | Q1: Food Revenue | R1: Daily Cost %
A2: Wednesday | B2: 4244.06 | C2: 1381.57 | E2: 390 | F2: 909.5 | G2: 293.95 | H2: 19.8 | N2: 100 | P2: =SUM(B2:O2) -> 7338.88 | Q2: 12424.7 | R2: =P2/Q2 -> 0.59066859
A3: Thursday | B3: 2959.02 | C3: 483.5 | F3: 290 | L3: 55 | P3: =SUM(B3:O3) -> 3787.52 | Q3: 13022.4 | R3: =P3/Q3 -> 0.29084654
A4: Friday | B4: 3798.23 | C4: 1120.17 | F4: 1346.43 | H4: 181.31 | J4: 1035.49 | L4: 55.95 | M4: 2742.04 | N4: 100 | O4: 277.41 | P4: =SUM(B4:O4) -> 10657.03 | Q4: 17201 | R4: =P4/Q4 -> 0.61955875
A5: Saturday | B5: 2588.44 | C5: 1948.4 | F5: 293 | P5: =SUM(B5:O5) -> 4829.84 | Q5: 23303.25 | R5: =P5/Q5 -> 0.20726036
A6: Sunday | B6: N/A | C6: N/A | D6: N/A | E6: N/A | F6: N/A | H6: 45.6 | I6: N/A | J6: N/A | K6: N/A | L6: N/A | N6: N/A | O6: N/A | P6: 0 | Q6: 18482.2 | R6: =P6/Q6 -> 0
A9: Budget | B9: 14000
A10: Total Weekly Spend | B10: =SUM(B2:O6) -> 26658.87
A11: Remaing Spend | B11: =SUM(B9-B10) -> -12658.87
A13: Weekly Food Revenue | B13: =SUM(Q2:Q6) -> 84433.55
A14: Weekly Cost % | B14: =B10/B13 -> 0.31573788
A17: End of week status
A18: list items over $100
A19: Items carrying over | B19: Amount | C19: Items discarded | D19: Amount
A32: Total | B32: =sum(B20:B31) -> 0 | D32: =sum(D20:D31) -> 0

Sheet Roister week of (621-26)
B1: CW | C1: Fortune | D1: Viola | E1: A1 Firewood | F1: Superior | G1: Aya | H1: Closed Loop | I1: Rocker Bros | J1: Testa | K1: Regalis | L1: Cornille | M1: Rare Tea Cellar | N1: Steve's | O1: Turano | P1: Daily Spend | Q1: Daily Revenue | R1: Daily Cost %
A2: Tuesday (buyout) | B2: 4468.31 | D2: 270.08 | E2: 390 | G2: 49.5 | H2: 242 | N2: 100 | P2: =SUM(B2:O2) -> 5519.89 | Q2: 15600 | R2: =P2/Q2 -> 0.3538391
A3: Thursday | B3: 2556.14 | C3: 801.43 | F3: 2128.55 | I3: 3046.55 | K3: 339.54 | M3: 188.85 | P3: =SUM(B3:O3) -> 9061.06 | Q3: 14013.6 | R3: =P3/Q3 -> 0.64659046
A4: Friday | B4: 2139.68 | C4: 1796.3 | F4: $966,80 | G4: 166.9 | M4: 60 | N4: 100 | O4: 277.41 | P4: =SUM(B4:O4) -> 4540.29 | Q4: 18065 | R4: =P4/Q4 -> 0.25133075
A5: Saturday | B5: 2173.74 | C5: 1169.94 | G5: 82.5 | P5: =SUM(B5:O5) -> 3426.18 | Q5: 19569.6 | R5: =P5/Q5 -> 0.17507665
A6: Sunday | B6: N/A | C6: N/A | D6: N/A | E6: N/A | F6: N/A | H6: N/A | J6: N/A | L6: N/A | M6: N/A | N6: N/A | O6: N/A | P6: 0 | Q6: =4337.15+10901 -> 15238.15 | R6: =P6/Q6 -> 0
A9: Budget | B9: 14000
A10: Total Weekly Spend | B10: =SUM(B2:O6) -> 22547.42
A11: Remaing Spend | B11: =SUM(B9-B10) -> -8547.42
A13: Weekly Food Revenue | B13: =SUM(Q2:Q6) -> 82486.35
A14: Weekly Cost % | B14: =B10/B13 -> 0.27334729
A17: End of week status
A18: list items over $100
A19: Items carrying over | B19: Amount | C19: Items discarded | D19: Amount
A32: Total | B32: =sum(B20:B31) -> 0 | D32: =sum(D20:D31) -> 0

Sheet Roister week of (629-73)
B1: CW | C1: Fortune | D1: Closed Loop | E1: A1 Firewood | F1: Superior | G1: Aya | H1: Rocker Bros | I1: Regalis | J1: Cornille | K1: Rare Tea Cellar | L1: Steve's | M1: Turano | N1: Daily Spend | O1: Daily Revenue | P1: Daily Cost %
A2: Tuesday/Wednesday | B2: 3650.7 | C2: 1373.24 | D2: 242 | E2: 390 | F2: 2982.6 | G2: 82.5 | H2: 1173.55 | K2: 162.65 | L2: 100 | N2: =SUM(B2:M2) -> 10157.24 | O2: 8453 | P2: =N2/O2 -> 1.2016136
A3: Thursday | B3: 2111.76 | N3: =SUM(B3:M3) -> 2111.76 | O3: 10247 | P3: =N3/O3 -> 0.20608568
A4: Friday | B4: 1538.23 | C4: 643.56 | F4: 1069.1 | G4: 227.5 | I4: 56.23 | L4: 100 | M4: 277.41 | N4: =SUM(B4:M4) -> 3912.03 | O4: 13983.8 | P4: =N4/O4 -> 0.27975443
A5: Saturday | B5: 2342.7 | C5: 1056.41 | G5: 82.5 | N5: =SUM(B5:M5) -> 3481.61 | O5: =3316+15249.5 -> 18565.5 | P5: =N5/O5 -> 0.18753117
A6: Sunday | B6: N/A | C6: N/A | D6: N/A | E6: N/A | F6: N/A | G6: N/A | H6: N/A | I6: N/A | J6: N/A | K6: N/A | L6: N/A | M6: N/A | N6: 0 | O6: 18508.8 | P6: =N6/O6 -> 0
A9: Budget | B9: 14000
A10: Total Weekly Spend | B10: =SUM(B2:M6) -> 19662.64
A11: Remaing Spend | B11: =SUM(B9-B10) -> -5662.64
A13: Weekly Food Revenue | B13: =SUM(O2:O6) -> 69758.1
A14: Weekly Cost % | B14: =B10/B13 -> 0.28186892
A17: End of week status
A18: list items over $100
A19: Items carrying over | B19: Amount | C19: Items discarded | D19: Amount
A32: Total | B32: =sum(B20:B31) -> 0 | D32: =sum(D20:D31) -> 0

Sheet Roister week of (75-710)
B1: CW | C1: Fortune | D1: Closed Loop | E1: A1 Firewood | F1: Superior | G1: Aya | H1: Rocker Bros | I1: D'artagnan | J1: Regalis | K1: Cornille | L1: Rare Tea Cellar | M1: Steve's | N1: Turano | O1: Daily Spend | P1: Daily Revenue | Q1: Daily Cost %
A2: Tuesday/Wednesday | B2: 3430.07 | C2: 604.75 | E2: 390 | G2: 82.5 | M2: 100 | O2: =SUM(B2:N2) -> 4607.32 | P2: 7888 | Q2: =O2/P2 -> 0.58409229
A3: Thursday | B3: 2342.8 | C3: 696.9 | F3: 870.05 | H3: 672.5 | J3: 260.72 | L3: 39 | O3: =SUM(B3:N3) -> 4881.97 | P3: 10906 | Q3: =O3/P3 -> 0.44764075
A4: Friday | B4: 2710.15 | C4: 201.78 | F4: 1754.05 | G4: 49.5 | I4: 1252.1 | M4: 100 | N4: 302.37 | O4: =SUM(B4:N4) -> 6369.95 | P4: 14630 | Q4: =O4/P4 -> 0.43540328
A5: Saturday | B5: 2621.28 | C5: 702.67 | J5: 136.58 | O5: =SUM(B5:N5) -> 3460.53 | P5: =4888+14419 -> 19307 | Q5: =O5/P5 -> 0.17923706
A6: Sunday | B6: N/A | C6: N/A | D6: N/A | E6: N/A | F6: N/A | G6: N/A | H6: N/A | J6: N/A | K6: N/A | L6: N/A | M6: N/A | N6: N/A | O6: 0 | P6: 17791.6 | Q6: =O6/P6 -> 0
A9: Budget | B9: 14000
A10: Total Weekly Spend | B10: =SUM(B2:N6) -> 19319.77
A11: Remaing Spend | B11: =SUM(B9-B10) -> -5319.77
A13: Weekly Food Revenue | B13: =SUM(P2:P6) -> 70522.6
A14: Weekly Cost % | B14: =B10/B13 -> 0.27395147
A17: End of week status
A18: list items over $100
A19: Items carrying over | B19: Amount | C19: Items discarded | D19: Amount
A32: Total | B32: =sum(B20:B31) -> 0 | D32: =sum(D20:D31) -> 0

Sheet Roister week of (712-717)
B1: CW | C1: Fortune | D1: Closed Loop | E1: A1 Firewood | F1: Superior | G1: Aya | H1: Rocker Bros | I1: D'artagnan | J1: Regalis | K1: Cornille | L1: Rare Tea Cellar | M1: Steve's | N1: Turano | O1: Daily Spend | P1: Daily Revenue | Q1: Daily Cost %
A2: Tuesday/Wednesday | B2: 4131.8 | C2: 618 | E2: 390 | F2: 1277.45 | G2: 49.5 | M2: 100 | O2: =SUM(B2:N2) -> 6566.75 | P2: 10545.84 | Q2: =O2/P2 -> 0.62268629
A3: Thursday | B3: 739.6 | C3: 709.33 | F3: 904.51 | G3: 194.5 | O3: =SUM(B3:N3) -> 2547.94 | P3: 14145.68 | Q3: =O3/P3 -> 0.18012142
A4: Friday | B4: 2899.89 | C4: 764.08 | G4: 49.5 | M4: 100 | N4: 302.37 | O4: =SUM(B4:N4) -> 4115.84 | P4: 12887.61 | Q4: =O4/P4 -> 0.3193641
A5: Saturday | B5: 2073.58 | C5: 542.98 | O5: =SUM(B5:N5) -> 2616.56 | P5: =4552.1+16729 -> 21281.1 | Q5: =O5/P5 -> 0.12295229
A6: Sunday | B6: N/A | C6: N/A | D6: N/A | E6: N/A | F6: N/A | G6: N/A | H6: N/A | J6: N/A | K6: N/A | L6: N/A | M6: N/A | N6: N/A | O6: 0 | P6: 14696.6 | Q6: =O6/P6 -> 0
A9: Budget | B9: 14000
A10: Total Weekly Spend | B10: =SUM(B2:N6) -> 15847.09 | C10: 21k
A11: Remaing Spend | B11: =SUM(B9-B10) -> -1847.09
A13: Weekly Food Revenue | B13: =SUM(P2:P6) -> 73556.83
A14: Weekly Cost % | B14: =B10/B13 -> 0.21544009
A17: End of week status
A18: list items over $100
A19: Items carrying over | B19: Amount | C19: Items discarded | D19: Amount
A32: Total | B32: =sum(B20:B31) -> 0 | D32: =sum(D20:D31) -> 0

Sheet Roister week of (719-724)
B1: CW | C1: Fortune | D1: Closed Loop | E1: A1 Firewood | F1: Superior | G1: Aya | H1: Rocker Bros | I1: D'artagnan | J1: Four Star | K1: Regalis | L1: Cornille | M1: Rare Tea Cellar | N1: Steve's | O1: Turano | P1: Daily Spend | Q1: Daily Revenue | R1: Daily Cost %
A2: Tuesday/Wednesday | B2: 4051.48 | C2: 1270.4 | E2: 260 | F2: 933.6 | G2: 49.5 | H2: 1793 | J2: 180 | M2: 33.9 | N2: 100 | P2: =SUM(B2:O2) -> 8671.88 | Q2: 15069.64 | R2: =P2/Q2 -> 0.57545369
A3: Thursday | B3: 2002.14 | C3: 205.09 | G3: 194.5 | P3: =SUM(B3:O3) -> 2401.73 | Q3: 13352.1 | R3: =P3/Q3 -> 0.17987657
A4: Friday | B4: 2457.27 | C4: 1386.56 | F4: 870.95 | G4: 49.5 | H4: 1099.31 | K4: 57.85 | L4: 3000 | M4: 25 | N4: 100 | O4: 302.37 | P4: =SUM(B4:O4) -> 9348.81 | Q4: 13200.2 | R4: =P4/Q4 -> 0.70823245
A5: Saturday | B5: 4291.02 | C5: 1098.12 | F5: 126 | P5: =SUM(B5:O5) -> 5515.14 | Q5: 19915.74 | R5: =P5/Q5 -> 0.27692368
A6: Sunday | B6: N/A | C6: N/A | D6: N/A | E6: N/A | F6: N/A | G6: N/A | H6: N/A | I6: N/A | J6: N/A | K6: N/A | L6: N/A | M6: N/A | N6: N/A | O6: N/A | P6: 0 | Q6: 15444 | R6: =P6/Q6 -> 0
B7: =sum(B2:B5) -> 12801.91
B8: 13211.75 | C8: =B8-B7 -> 409.84 | E8: CW
A9: Budget | B9: 14000 | E9: 44760 | F9: 0
A10: Total Weekly Spend | B10: =SUM(B2:O6) -> 25937.56 | E10: 44761 | F10: 2233.88
A11: Remaing Spend | B11: =SUM(B9-B10) -> -11937.56 | E11: 44762 | F11: 1925.2 | G11: 4159.08
E12: 44763 | F12: 2018.1
A13: Weekly Food Revenue | B13: =SUM(Q2:Q6) -> 76981.68 | E13: 44764 | F13: 2467.58
A14: Weekly Cost % | B14: =B10/B13 -> 0.33693159 | E14: 44765 | F14: 4291.02
E15: 44766 | F15: 0
F16: 12935.78 | G16: 13211.75 | H16: =G16-F16 -> 275.97
A17: End of week status
A18: list items over $100 | E18: Duplicate copy from 7/21 total:
A19: Items carrying over | B19: Amount | C19: Items discarded | D19: Amount
A20: Short Ribs | B20: 1138.79
A21: Jamon | B21: 390.66
A32: Total | B32: =sum(B20:B31) -> 1529.45 | D32: =sum(D20:D31) -> 0

Sheet Roister week of (726-731)
B1: CW | C1: Fortune | D1: Closed Loop | E1: A1 Firewood | F1: Superior | G1: Aya | H1: Rocker Bros | I1: D'artagnan | J1: Four Star | K1: Regalis | L1: Testa | M1: Cornille | N1: Rare Tea Cellar | O1: Steve's | P1: Turano | Q1: Daily Spend | R1: Daily Revenue | S1: Daily Cost %
A2: Tuesday/Wednesday | B2: 3937.84 | C2: 486.24 | E2: 260 | F2: 504 | G2: 49.5 | I2: 1138.79 | J2: 180 | K2: 147.19 | O2: 100 | Q2: =SUM(B2:P2) -> 6803.56 | R2: 9127.34 | S2: =Q2/R2 -> 0.74540447
A3: Thursday | B3: 1487.48 | C3: 819.54 | G3: 194.5 | Q3: =SUM(B3:P3) -> 2501.52 | R3: 9555 | S3: =Q3/R3 -> 0.2618022
A4: Friday | B4: 1804.99 | C4: 144.9 | F4: 272.98 | G4: 49.5 | H4: 1067.72 | L4: 136.35 | O4: 100 | P4: 302.37 | Q4: =SUM(B4:P4) -> 3878.81 | R4: 12853.4 | S4: =Q4/R4 -> 0.30177307
A5: Saturday | B5: 1153.48 | C5: 580.1 | M5: 1674.5 | Q5: =SUM(B5:P5) -> 3408.08 | R5: 16202 | S5: =Q5/R5 -> 0.21034934
A6: Sunday | B6: N/A | C6: N/A | D6: N/A | E6: N/A | F6: N/A | G6: N/A | H6: N/A | I6: N/A | J6: N/A | K6: N/A | L6: N/A | M6: N/A | N6: N/A | O6: N/A | P6: N/A | Q6: 0 | R6: 12304.46 | S6: =Q6/R6 -> 0
B7: =sum(B2:B5) -> 8383.79 | C7: =sum(C2:C5) -> 2030.78 | D7: =sum(D2:D5) -> 0 | E7: =sum(E2:E5) -> 260 | F7: =sum(F2:F5) -> 776.98 | G7: =sum(G2:G5) -> 293.5 | H7: =sum(H2:H5) -> 1067.72 | I7: =sum(I2:I5) -> 1138.79 | ... Q7: =sum(Q2:Q5) -> 16591.97
A9: Budget | B9: 14000
A10: Total Weekly Spend | B10: =SUM(B2:P6) -> 16591.97 | D10: Carryover Items from last week | F10: Jamon $390.66
A11: Remaing Spend | B11: =SUM(B9-B10) -> -2591.97 | F11: Crisp Film $212.62
F12: Short Ribs $1,138.79
A13: Weekly Food Revenue | B13: =SUM(R2:R6) -> 60042.2
A14: Weekly Cost % | B14: =B10/B13 -> 0.27633848
A17: End of week status
A18: list items over $100
A19: Items carrying over | B19: Amount | C19: Items discarded | D19: Amount
A20: Potato Pellets | B20: 136.35
A21: Olives | B21: 101.28
A32: Total | B32: =sum(B20:B31) -> 237.63 | D32: =sum(D20:D31) -> 0

Sheet Roister week of (82-87)
B1: CW | C1: Fortune | D1: Closed Loop | E1: A1 Firewood | F1: Superior | G1: Aya | H1: Rocker Bros | I1: D'artagnan | J1: Four Star | K1: Truffles | L1: Regalis | M1: Cornille | N1: Rare Tea Cellar | O1: Steve's | P1: Turano | Q1: Daily Spend | R1: Daily Revenue | S1: Daily Cost %
A2: Tuesday/Wednesday | B2: 4299.5 | C2: 960.39 | E2: 390 | F2: 504 | G2: 49.5 | H2: 1020.11 | J2: 180 | O2: 100 | Q2: =SUM(B2:P2) -> 7503.5 | R2: 8503 | S2: =Q2/R2 -> 0.88245325
A3: Thursday | B3: 881.83 | C3: 0 | I3: 492 | Q3: =SUM(B3:P3) -> 1373.83 | R3: 11756 | S3: =Q3/R3 -> 0.11686203
A4: Friday | B4: 1427.35 | C4: 324.9 | F4: 493.65 | G4: 161.5 | N4: 39 | O4: 100 | P4: 302.37 | Q4: =SUM(B4:P4) -> 2848.77 | R4: 13016 | S4: =Q4/R4 -> 0.21886678
A5: Saturday | B5: 999.72 | C5: 135.3 | D5: 600 | F5: 189.38 | G5: 33 | K5: 440 | M5: 1421.35 | Q5: =SUM(B5:P5) -> 3818.75 | R5: 15453.6 | S5: =Q5/R5 -> 0.24711071
A6: Sunday | B6: N/A | C6: N/A | D6: N/A | E6: N/A | F6: N/A | G6: N/A | H6: N/A | I6: N/A | J6: N/A | K6: N/A | L6: N/A | M6: N/A | N6: N/A | O6: N/A | P6: N/A | Q6: 0 | R6: 15326.6 | S6: =Q6/R6 -> 0
B7: =8135.61 -> 8135.61 | C7: 1425.59 | D7: 747 | E7: 340 | F7: 997.65 | G7: 244 | H7: 1269.47 | I7: 569.4 | J7: 180 | M7: 1421.35 | N7: 39
B8: =sum(B2:B5)-B7 -> -527.21 | C8: =sum(C2:C5)-C7 -> -5 | D8: =sum(D2:D5)-D7 -> -147 | E8: =sum(E2:E5)-E7 -> 50 | F8: =sum(F2:F5)-F7 -> 189.38 | G8: =sum(G2:G5)-G7 -> 0 | H8: =sum(H2:H5)-H7 -> -249.36 | I8: =sum(I2:I5)-I7 -> -77.4 | J8: =sum(J2:J5)-J7 -> 0 | M8: =sum(M2:M5)-M7 -> 0 | N8: =sum(N2:N5)-N7 -> 0
A9: Budget | B9: 12000 | E9: Truffle | F9: 440
A10: Total Weekly Spend | B10: =SUM(B2:P6) -> 15544.85
A11: Remaing Spend | B11: =SUM(B9-B10) -> -3544.85
A13: Weekly Food Revenue | B13: =SUM(R2:R6) -> 64055.2
A14: Weekly Cost % | B14: =B10/B13 -> 0.24267897
A17: End of week status
A18: list items over $100
A19: Items carrying over | B19: Amount | C19: Items discarded | D19: Amount
A20: Short Ribs | B20: 492.45
A32: Total | B32: =sum(B20:B31) -> 492.45 | D32: =sum(D20:D31) -> 0

Sheet Roister week of (89-814)
B1: CW | C1: Fortune | D1: Closed Loop | E1: A1 Firewood | F1: Superior | G1: Aya | H1: Rocker Bros | I1: D'artagnan | J1: Four Star | K1: Regalis | L1: Cornille | M1: Truffles | N1: Rare Tea Cellar | O1: Steve's | P1: Turano | Q1: Daily Spend | R1: Daily Revenue | S1: Daily Cost %
A2: Tuesday | B2: 3152.12 | C2: 625.65 | Q2: =SUM(B2:P2) -> 3777.77 | R2: 0 | S2: =Q2/R2 -> #DIV/0!
A3: Wednesday | B3: 740.16 | E3: 390 | F3: 685.63 | G3: 49.5 | I3: 492.45 | J3: 180 | N3: 44.5 | O3: 100 | Q3: =SUM(B3:P3) -> 2682.24 | R3: 8392.2 | S3: =Q3/R3 -> 0.31961107
A4: Thursday | B4: 1042.57 | C4: 189.45 | Q4: =SUM(B4:P4) -> 1232.02 | R4: 11455 | S4: =Q4/R4 -> 0.10755303
A5: Friday | B5: 2162.55 | C5: 491.16 | F5: 449.5 | G5: 161.5 | O5: 100 | P5: 306.93 | Q5: =SUM(B5:P5) -> 3671.64 | R5: 13821 | S5: =Q5/R5 -> 0.26565661
A6: Saturday | B6: 2486.32 | C6: 460.9 | G6: 33 | H6: 1122.96 | K6: 84.83 | L6: 1191.5 | M6: 440 | Q6: =SUM(B6:P6) -> 5819.51 | R6: 18719.4 | S6: =Q6/R6 -> 0.31088122
A7: Sunday | B7: N/A | C7: N/A | D7: N/A | E7: N/A | F7: N/A | G7: N/A | H7: N/A | I7: N/A | J7: N/A | K7: N/A | L7: N/A | M7: N/A | N7: N/A | O7: N/A | P7: N/A | Q7: 0 | R7: 12914.6 | S7: =Q7/R7 -> 0
B8: =sum(B2:B6) -> 9583.72 | C8: =sum(C2:C6) -> 1767.16 | D8: =sum(D2:D6) -> 0 | E8: =sum(E2:E6) -> 390 | F8: =sum(F2:F6) -> 1135.13 | G8: =sum(G2:G6) -> 244 | H8: =sum(H2:H6) -> 1122.96 | I8: =sum(I2:I6) -> 492.45 | ... P8: =sum(P2:P6) -> 306.93
B9: 10446.05 | C9: 1922 | D9: 477 | E9: 390 | F9: 1420.03 | G9: 244 | H9: 1122.96 | J9: 180 | K9: 84.83 | L9: 1191.5 | M9: 440 | N9: 44.5 | P9: 306.93
A10: Budget | B10: 14000 | C10: =B8-B9 -> -862.33 | F10: =F8-F9 -> -284.9
A11: Total Weekly Spend | B11: =SUM(B2:P7) -> 17183.18
A12: Remaing Spend | B12: =SUM(B10-B11) -> -3183.18
A14: Weekly Food Revenue | B14: =SUM(R3:R7) -> 65302.2
A15: Weekly Cost % | B15: =B11/B14 -> 0.26313325
A18: End of week status | G18: Scallops
A19: list items over $100 | G19: Date delivered | H19: Weight billed (lbs) | I19: Weight received (lbs)
A20: Items carrying over | B20: Amount | C20: Items discarded | D20: Amount | G20: 44783 | H20: 16# | I20: 16# | J20: 4# = 53pc
A21: Jamon | B21: 584.45 | G21: 44785 | H21: 12# | I21: 12#
A22: Short Ribs | B22: 1078.63
H28: Total left at EOW
I30: =16+12 -> 28
I31: =I30/90 -> 0.31111111
A33: Total | B33: =sum(B21:B32) -> 1663.08 | D33: =sum(D21:D32) -> 0

Sheet Roister week of (816-821)
B1: CW | C1: Fortune | D1: Closed Loop | E1: A1 Firewood | F1: Superior | G1: Aya | H1: Rocker Bros | I1: D'artagnan | J1: Four Star | K1: Regalis | L1: Cornille | M1: Truffles | N1: Rare Tea Cellar | O1: Steve's | P1: Turano | Q1: Daily Spend | R1: Daily Revenue | S1: Daily Cost %
A2: Tuesday | B2: 3999.84 | F2: 374.4 | I2: 1078.63 | Q2: =SUM(B2:P2) -> 5452.87 | R2: 0 | S2: =Q2/R2 -> #DIV/0!
A3: Wednesday | B3: 629.22 | C3: 433.37 | E3: 290 | F3: 298.51 | G3: 49.5 | H3: 1038.96 | J3: 180 | K3: 60.45 | M3: 440 | O3: 100 | Q3: =SUM(B3:P3) -> 3520.01 | R3: 10638.8 | S3: =Q3/R3 -> 0.33086532
A4: Thursday | B4: 1126.01 | C4: 161.66 | Q4: =SUM(B4:P4) -> 1287.67 | R4: 14444.95 | S4: =Q4/R4 -> 0.089143265
A5: Friday | B5: 934.83 | F5: 120 | G5: 161.5 | K5: 69.95 | O5: 100 | P5: 302.37 | Q5: =SUM(B5:P5) -> 1688.65 | R5: 14415.6 | S5: =Q5/R5 -> 0.11714046
A6: Saturday | B6: 2025.52 | C6: 762.15 | D6: 600 | G6: 33 | L6: 416.5 | Q6: =SUM(B6:P6) -> 3837.17 | R6: 18145.2 | S6: =Q6/R6 -> 0.21147025
A7: Sunday | B7: N/A | C7: N/A | D7: N/A | E7: N/A | F7: N/A | G7: N/A | H7: N/A | I7: N/A | J7: N/A | K7: N/A | L7: N/A | M7: N/A | N7: N/A | O7: N/A | P7: N/A | Q7: 0 | R7: 13500 | S7: =Q7/R7 -> 0
B8: 8363.82 | C8: 1591.91 | E8: 290 | F8: 898.51 | G8: 244 | H8: 1038.96 | I8: 1078.63 | J8: 180 | K8: 129.4 | L8: 416.5 | M8: 440
B9: =SUM(B2:B6)-B8 -> 351.6 | C9: =SUM(C2:C6)-C8 -> -234.73 | E9: =SUM(E2:E6)-E8 -> 0 | F9: =SUM(F2:F6)-F8 -> -105.6 | G9: =SUM(G2:G6)-G8 -> 0 | H9: =SUM(H2:H6)-H8 -> 0 | I9: =SUM(I2:I6)-I8 -> 0 | J9: =SUM(J2:J6)-J8 -> 0 | K9: =SUM(K2:K6)-K8 -> 1 | L9: =SUM(L2:L6)-L8 -> 0 | M9: =SUM(M2:M6)-M8 -> 0 | O9: =SUM(O2:O6)-O8 -> 200 | P9: =SUM(P2:P6)-P8 -> 302.37
A10: Budget | B10: 12000
A11: Total Weekly Spend | B11: =SUM(B2:P7) -> 15786.37
A12: Remaing Spend | B12: =SUM(B10-B11) -> -3786.37
A14: Weekly Food Revenue | B14: =SUM(R3:R7) -> 71144.55
A15: Weekly Cost % | B15: =B11/B14 -> 0.22189149
A18: End of week status | G18: Scallops
A19: list items over $100 | G19: Date delivered | H19: Weight billed (lbs) | I19: Weight received (lbs)
A20: Items carrying over | B20: Amount | C20: Items discarded | D20: Amount | G20: 44790 | H20: 16# | I20: 16#
A21: Trout | B21: 597.02 | G21: 44792 | H21: 4# | I21: 4#
A22: Short Ribs | B22: 1045.05
H28: Total left at EOW
A33: Total | B33: =sum(B21:B32) -> 1642.07 | D33: =sum(D21:D32) -> 0

Sheet Roister (913-918)
B1: CW | C1: Fortune | D1: Closed Loop | E1: A1 Firewood | F1: Superior | G1: Aya | H1: Rocker Bros | I1: D'artagnan | J1: Four Star | K1: Regalis | L1: Cornille | M1: Truffles | N1: Rare Tea Cellar | O1: Steve's | P1: Turano | Q1: Daily Spend | R1: Daily Revenue | S1: Daily Cost %
A2: Tuesday | B2: 3642.14 | Q2: =SUM(B2:P2) -> 3642.14 | S2: =Q2/R2 -> #DIV/0!
A3: Wednesday | B3: 839.16 | C3: 628.09 | E3: 390 | F3: 764.9 | G3: 49.5 | H3: 1087.23 | J3: 180 | O3: 100 | Q3: =SUM(B3:P3) -> 4038.88 | R3: 7126 | S3: =Q3/R3 -> 0.5667808
A4: Thursday | B4: 1663.26 | C4: 664.86 | K4: 82.6 | Q4: =SUM(B4:P4) -> 2410.72 | R4: 11095.83 | S4: =Q4/R4 -> 0.2172636
A5: Friday | B5: 2077.72 | C5: 196.19 | F5: 404.9 | G5: 142.5 | K5: 41.42 | O5: 100 | P5: 221.94 | Q5: =SUM(B5:P5) -> 3184.67 | R5: 13477 | S5: =Q5/R5 -> 0.23630407
A6: Saturday | B6: 1499.73 | C6: 350.89 | G6: 33 | L6: 924.7 | Q6: =SUM(B6:P6) -> 2808.32 | R6: 18696.8 | S6: =Q6/R6 -> 0.15020324
A7: Sunday | B7: N/A | C7: N/A | D7: N/A | E7: N/A | F7: N/A | G7: N/A | H7: N/A | I7: N/A | J7: N/A | K7: N/A | L7: N/A | M7: N/A | N7: N/A | O7: N/A | P7: N/A | Q7: 0 | R7: 8958 | S7: =Q7/R7 -> 0
A8: Reported on COGS | B8: 9795.36 | C8: 1948.6 | D8: 847 | E8: 390 | F8: 1628.93 | G8: 225 | H8: 1087.24 | J8: 180 | K8: 124.02 | L8: 924.7 | O8: 316.96 | P8: 221.94 | Q8: 325.55
B9: =sum(B2:B6)-B8 -> -73.35 | C9: =sum(C2:C6)-C8 -> -108.57 | D9: =sum(D2:D6)-D8 -> -847 | E9: =sum(E2:E6)-E8 -> 0 | F9: =sum(F2:F6)-F8 -> -459.13 | G9: =sum(G2:G6)-G8 -> 0 | H9: =sum(H2:H6)-H8 -> -0.01 | J9: =sum(J2:J6)-J8 -> 0 | K9: =sum(K2:K6)-K8 -> 0 | L9: =sum(L2:L6)-L8 -> 0 | O9: =sum(O2:O6)-O8 -> -116.96 | P9: =sum(P2:P6)-P8 -> 0 | Q9: =0-Q8 -> -325.55 | R9: Wabash Seafood
A10: Budget | B10: 12000 | F10: Trout carry over
A11: Total Weekly Spend | B11: =SUM(B2:P7) -> 16084.73
A12: Remaing Spend | B12: =SUM(B10-B11) -> -4084.73
A14: Weekly Food Revenue | B14: =SUM(R3:R7) -> 59353.63
A15: Weekly Cost % | B15: =B11/B14 -> 0.27099825
A18: End of week status | G18: Scallops
A19: list items over $100 | G19: Date delivered | H19: Weight billed (lbs) | I19: Weight received (lbs)
A20: Items carrying over | B20: Amount | C20: Items discarded | D20: Amount
A21: Jamon | B21: 511.12 | G21: 44818 | H21: 16# | I21: 16#
A22: Short Ribs | B22: 696.7 | G22: 44820 | H22: 4# | I22: 4#
H28: Total left at EOW
A33: Total | B33: =sum(B21:B32) -> 1207.82 | D33: =sum(D21:D32) -> 0

Sheet Roister week of (823-828)
B1: CW | C1: Fortune | D1: Closed Loop | E1: A1 Firewood | F1: Wabash | G1: Superior | H1: Aya | I1: Rocker Bros | J1: D'artagnan | K1: Four Star | L1: Regalis | M1: Cornille | N1: Truffles | O1: Rare Tea Cellar | P1: Steve's | Q1: Turano | R1: Daily Spend | S1: Daily Revenue | T1: Daily Cost %
A2: Tuesday | B2: 4162.17 | C2: 531.65 | G2: 298.51 | J2: 1045.05 | O2: 126.9 | R2: =SUM(B2:Q2) -> 6164.28 | S2: 0 | T2: =R2/S2 -> #DIV/0!
A3: Wednesday | B3: 355.18 | C3: 441.51 | F3: 289.58 | G3: 765.68 | H3: 49.5 | K3: 180 | P3: 100 | R3: =SUM(B3:Q3) -> 2181.45 | S3: 9165 | T3: =R3/S3 -> 0.23801964
A4: Thursday | B4: 1003.5 | R4: =SUM(B4:Q4) -> 1003.5 | S4: 11088 | T4: =R4/S4 -> 0.090503247
A5: Friday | B5: 1384.57 | C5: 238 | G5: 120 | H5: 142.5 | I5: 795.83 | N5: 440 | P5: 100 | Q5: 302.37 | R5: =SUM(B5:Q5) -> 3523.27 | S5: 13991.2 | T5: =R5/S5 -> 0.25182043
A6: Saturday | B6: 1493.52 | C6: 637.17 | D6: 600 | H6: 33 | M6: 1485.5 | R6: =SUM(B6:Q6) -> 4249.19 | S6: 18492.8 | T6: =R6/S6 -> 0.22977537
A7: Sunday | B7: N/A | C7: N/A | D7: N/A | E7: N/A | G7: N/A | H7: N/A | I7: N/A | J7: N/A | K7: N/A | L7: N/A | M7: N/A | N7: N/A | O7: N/A | P7: N/A | Q7: N/A | R7: 0 | S7: 14128 | T7: =R7/S7 -> 0
B8: 8650.91 | C8: 1995.44 | D8: 427 | E8: 280 | F8: 297.53 | G8: 885.68 | H8: 225 | I8: 795.83 | K8: 180 | M8: 1485.5 | N8: 440 | O8: 126.9
B9: =sum(B2:B6)-B8 -> -251.97 | C9: =sum(C2:C6)-C8 -> -147.11 | D9: =sum(D2:D6)-D8 -> 173 | E9: =sum(E2:E6)-E8 -> -280 | F9: =sum(F2:F6)-F8 -> -7.95 | G9: =sum(G2:G6)-G8 -> 298.51 | H9: =sum(H2:H6)-H8 -> 0 | I9: =sum(I2:I6)-I8 -> 0 | ... Q9: =sum(Q2:Q6)-Q8 -> 302.37
A10: Budget | B10: 14000
A11: Total Weekly Spend | B11: =SUM(B2:Q7) -> 17121.69
A12: Remaing Spend | B12: =SUM(B10-B11) -> -3121.69
A14: Weekly Food Revenue | B14: =SUM(S3:S7) -> 66865
A15: Weekly Cost % | B15: =B11/B14 -> 0.25606356
A18: End of week status | H18: Scallops
A19: list items over $100 | H19: Date delivered | I19: Weight billed (lbs) | J19: Weight received (lbs)
A20: Items carrying over | B20: Amount | C20: Items discarded | D20: Amount | H20: 44797 | I20: 16#
A21: Trout | B21: 298.51 | H21: 44799 | I21: 4#
A22: Potato Pellets | B22: 161.7
A23: Jamon | B23: 441.51
A24: Trout | B24: 895
I28: Total left at EOW
A33: Total | B33: =sum(B21:B32) -> 1796.72 | D33: =sum(D21:D32) -> 0

Sheet Roister (830-94)
B1: CW | C1: Fortune | D1: Closed Loop | E1: A1 Firewood | F1: Superior | G1: Aya | H1: Rocker Bros | I1: D'artagnan | J1: Four Star | K1: Regalis | L1: Cornille | M1: Truffles | N1: Rare Tea Cellar | O1: Steve's | P1: Turano | Q1: Daily Spend | R1: Daily Revenue | S1: Daily Cost %
A2: Tuesday | B2: 4048.52 | C2: 855.57 | F2: 298.51 | I2: 561 | Q2: =SUM(B2:P2) -> 5763.6 | S2: =Q2/R2 -> #DIV/0!
A3: Wednesday | B3: 1258.75 | C3: 82.05 | E3: 290 | F3: 1224.02 | G3: 49.5 | J3: 180 | O3: 100 | Q3: =SUM(B3:P3) -> 3184.32 | R3: 9178 | S3: =Q3/R3 -> 0.34695141
A4: Thursday | B4: 1054.62 | G4: 142.5 | I4: 507.84 | N4: 58.9 | Q4: =SUM(B4:P4) -> 1763.86 | R4: 7985 | S4: =Q4/R4 -> 0.22089668
A5: Friday | B5: 2230.81 | C5: 528.45 | F5: 120 | O5: 100 | P5: 306.93 | Q5: =SUM(B5:P5) -> 3286.19 | R5: 14292.8 | S5: =Q5/R5 -> 0.22991926
A6: Saturday | B6: 1367.3 | C6: 381.18 | D6: 600 | G6: 71 | H6: 1132.12 | L6: 972.5 | M6: 440 | Q6: =SUM(B6:P6) -> 4964.1 | R6: 18043.26 | S6: =Q6/R6 -> 0.27512212
A7: Sunday | B7: N/A | C7: N/A | D7: N/A | E7: N/A | F7: N/A | G7: N/A | H7: N/A | I7: N/A | J7: N/A | K7: N/A | L7: N/A | M7: N/A | N7: N/A | O7: N/A | P7: N/A | Q7: 0 | R7: 21919 | S7: =Q7/R7 -> 0
A10: Budget | B10: 14000
A11: Total Weekly Spend | B11: =SUM(B2:P7)+sum(B21:B24) -> 21662.43
A12: Remaing Spend | B12: =SUM(B10-B11) -> -7662.43
A14: Weekly Food Revenue | B14: =SUM(R3:R7) -> 71418.06
A15: Weekly Cost % | B15: =B11/B14 -> 0.30331866
A18: End of week status | G18: Scallops
A19: list items over $100 | G19: Date delivered | H19: Weight billed (lbs) | I19: Weight received (lbs)
A20: Items carrying over | B20: Amount | C20: Items discarded | D20: Amount | G20: 44804 | H20: 16# | I20: 16#
A21: Trout | B21: 298.51 | G21: 44806 | H21: 4# | I21: 4#
A22: Jamon | B22: 441.51
A23: Trout | B23: 895
A24: Short Ribs | B24: 1065.34
H28: Total left at EOW
A33: Total | B33: =sum(B21:B32) -> 2700.36 | D33: =sum(D21:D32) -> 0

Sheet Roister (96-911)
B1: CW | C1: Fortune | D1: Closed Loop | E1: A1 Firewood | F1: Superior | G1: Aya | H1: Rocker Bros | I1: D'artagnan | J1: Four Star | K1: Regalis | L1: Cornille | M1: Truffles | N1: Rare Tea Cellar | O1: Steve's | P1: Turano | Q1: Daily Spend | R1: Daily Revenue | S1: Daily Cost %
A2: Tuesday | B2: 3362.87 | F2: 459.15 | I2: 1065.34 | Q2: =SUM(B2:P2) -> 4887.36 | S2: =Q2/R2 -> #DIV/0!
A3: Wednesday | B3: 1263.4 | C3: 767.89 | E3: 390 | F3: 884.9 | G3: 49.5 | J3: 180 | K3: 326.99 | O3: 100 | Q3: =SUM(B3:P3) -> 3962.68 | R3: 11182.98 | S3: =Q3/R3 -> 0.3543492
A4: Thursday | B4: 1331.79 | N4: 64 | Q4: =SUM(B4:P4) -> 1395.79 | R4: 7765.5 | S4: =Q4/R4 -> 0.17974245
A5: Friday | B5: 1928.48 | C5: 673.95 | F5: 284.9 | G5: 142.5 | K5: 100.66 | M5: 440 | O5: 100 | P5: 306.93 | Q5: =SUM(B5:P5) -> 3977.42 | R5: 13255 | S5: =Q5/R5 -> 0.30006941
A6: Saturday | B6: 2049.67 | C6: 197.24 | D6: 600 | G6: 33 | H6: 716.37 | L6: 1482.2 | Q6: =SUM(B6:P6) -> 5078.48 | R6: 17911.9 | S6: =Q6/R6 -> 0.28352548
A7: Sunday | B7: N/A | C7: N/A | D7: N/A | E7: N/A | F7: N/A | G7: N/A | H7: N/A | I7: N/A | J7: N/A | K7: N/A | L7: N/A | M7: N/A | N7: N/A | O7: N/A | P7: N/A | Q7: 0 | R7: 11186.2 | S7: =Q7/R7 -> 0
A10: Budget | B10: 14000
A11: Total Weekly Spend | B11: =SUM(B2:P7) -> 19301.73
A12: Remaing Spend | B12: =SUM(B10-B11) -> -5301.73
A14: Weekly Food Revenue | B14: =SUM(R3:R7) -> 61301.58
A15: Weekly Cost % | B15: =B11/B14 -> 0.31486513
A18: End of week status | G18: Scallops
A19: list items over $100 | G19: Date delivered | H19: Weight billed (lbs) | I19: Weight received (lbs)
A20: Items carrying over | B20: Amount | C20: Items discarded | D20: Amount | G20: 44811 | H20: 20# | I20: 20#
A21: Trout | B21: 459.13
A22: Short Ribs | B22: 1065.35
H28: Total left at EOW
A33: Total | B33: =sum(B21:B32) -> 1524.48 | D33: =sum(D21:D32) -> 0

Sheet Roister (920 - 925)
B1: CW | C1: Fortune | D1: Closed Loop | E1: A1 Firewood | F1: Superior | G1: Aya | H1: Rocker Bros | I1: D'artagnan | J1: Four Star | K1: Regalis | L1: Cornille | M1: Truffles | N1: Rare Tea Cellar | O1: Steve's | P1: Turano | Q1: Daily Spend | R1: Daily Revenue | S1: Daily Cost %
A2: Tuesday | B2: 3745.04 | C2: 511.22 | I2: 696.7 | Q2: =SUM(B2:P2) -> 4952.96 | R2: 13096.56 | S2: =Q2/R2 -> 0.37818786
A3: Wednesday | B3: 1080.82 | C3: 432.52 | E3: 390 | G3: 49.5 | J3: 180 | O3: 100 | Q3: =SUM(B3:P3) -> 2232.84 | R3: 23246 | S3: =Q3/R3 -> 0.096052654
A4: Thursday | Q4: =SUM(B4:P4) -> 0 | S4: =Q4/R4 -> #DIV/0!
A5: Friday | B5: 2387.65 | F5: 764.9 | G5: 142.5 | M5: 440 | N5: 72.9 | O5: 100 | P5: 302.37 | Q5: =SUM(B5:P5) -> 4210.32 | R5: 13789.26 | S5: =Q5/R5 -> 0.30533328
A6: Saturday | B6: 1348.79 | C6: 610.44 | D6: 473 | H6: 943.7 | L6: 577 | Q6: =SUM(B6:P6) -> 3952.93 | R6: 17199.04 | S6: =Q6/R6 -> 0.22983434
A7: Sunday | B7: N/A | C7: N/A | D7: N/A | E7: N/A | F7: N/A | G7: N/A | H7: N/A | I7: N/A | J7: N/A | K7: N/A | L7: N/A | M7: N/A | N7: N/A | O7: N/A | P7: N/A | Q7: 0 | R7: 16078 | S7: =Q7/R7 -> 0
A8: Reported on COGS | B8: 8338.39 | C8: 1188.51 | D8: 473 | E8: 390 | F8: 764.9 | G8: 225 | H8: 1518.7 | I8: 2147.46 | J8: 180 | L8: 577 | M8: 440 | P8: 221.94
B9: =sum(B2:B6)-B8 -> 223.91 | C9: =sum(C2:C6)-C8 -> 365.67 | D9: =sum(D2:D6)-D8 -> 0 | E9: =sum(E2:E6)-E8 -> 0 | F9: =sum(F2:F6)-F8 -> 0 | G9: =sum(G2:G6)-G8 -> -33 | H9: =sum(H2:H6)-H8 -> -575 | I9: =sum(I2:I6)-I8 -> -1450.76 | ... M9: =sum(M2:M6)-M8 -> 0 | O9: =sum(O2:O6)-O8 -> 200 | P9: =sum(P2:P6)-P8 -> 80.43 | Q9: =0-Q8 -> 0
A10: Budget | B10: 12000
A11: Total Weekly Spend | B11: =SUM(B2:P7) -> 15349.05
A12: Remaing Spend | B12: =SUM(B10-B11) -> -3349.05
A14: Weekly Food Revenue | B14: =SUM(R3:R7) -> 70312.3
A15: Weekly Cost % | B15: =B11/B14 -> 0.21829822
A18: End of week status | G18: Scallops
A19: list items over $100 | G19: Date delivered | H19: Weight billed (lbs) | I19: Weight received (lbs)
A20: Items carrying over | B20: Amount | C20: Items discarded | D20: Amount | G20: 44827 | H20: 16# | I20: 16#
A21: Jamon | B21: 511.12
A22: Short Ribs | B22: 1061.84
H28: Total left at EOW
A33: Total | B33: =sum(B21:B32) -> 1572.96 | D33: =sum(D21:D32) -> 0

Sheet Roister (926 - 102)
B1: CW | C1: Fortune | D1: Closed Loop | E1: A1 Firewood | F1: Superior | G1: Aya | H1: Rocker Bros | I1: D'artagnan | J1: Four Star | K1: Regalis | L1: Cornille | M1: Truffles | N1: Rare Tea Cellar | O1: Steve's | P1: Turano | Q1: Daily Spend | R1: Daily Revenue | S1: Daily Cost %
A2: Monday | B2: 2822.86 | C2: 444.21 | Q2: =SUM(B2:P2) -> 3267.07 | R2: 5074.85 | S2: =Q2/R2 -> 0.64377666
A3: Tuesday | B3: 1615.02 | F3: 566.65 | I3: 1061.84 | Q3: =SUM(B3:P3) -> 3243.51 | R3: 4921 | S3: =Q3/R3 -> 0.65911603
A4: Wednesday | B4: 1946.22 | C4: 344.86 | E4: 390 | F4: 240 | G4: 49.5 | J4: 180 | N4: 85 | O4: 100 | Q4: =SUM(B4:P4) -> 3335.58 | R4: 7563.4 | S4: =Q4/R4 -> 0.44101595
A5: Thursday | B5: 1896.93 | C5: 318.91 | Q5: =SUM(B5:P5) -> 2215.84 | R5: 9782.85 | S5: =Q5/R5 -> 0.2265025
A6: Friday | B6: 1692.84 | C6: 65.79 | F6: 284.9 | G6: 142.5 | M6: 440 | O6: 100 | P6: 302.37 | Q6: =SUM(B6:P6) -> 3028.4 | R6: 27222.3 | S6: =Q6/R6 -> 0.11124703
A7: Saturday | B7: 1743.99 | C7: 323.7 | D7: 438 | G7: 33 | H7: 1038.22 | L7: 453 | Q7: =SUM(B7:P7) -> 4029.91 | R7: 20347.16 | S7: =Q7/R7 -> 0.19805762
A8: Sunday | B8: N/A | C8: N/A | D8: N/A | E8: N/A | F8: N/A | G8: N/A | H8: N/A | I8: N/A | J8: N/A | K8: N/A | L8: N/A | M8: N/A | N8: N/A | O8: N/A | P8: N/A | Q8: 0 | S8: =Q8/R8 -> #DIV/0!
B9: 11558.76 | C9: 1873.21 | D9: 906 | E9: 390 | F9: 1091.55 | G9: 225 | H9: 1049.76 | J9: 180 | L9: 595 | M9: 440 | N9: 85 | P9: 221.94
B10: =sum(B2:B7)-B9 -> 159.1 | C10: =sum(C2:C7)-C9 -> -375.74 | D10: =sum(D2:D7)-D9 -> -468 | E10: =sum(E2:E7)-E9 -> 0 | F10: =sum(F2:F7)-F9 -> 0 | G10: =sum(G2:G7)-G9 -> 0 | H10: =sum(H2:H7)-H9 -> -11.54 | I10: =sum(I2:I7)-I9 -> 1061.84 | ... P10: =sum(P2:P7)-P9 -> 80.43
A11: Budget | B11: 12000
A12: Total Weekly Spend | B12: =SUM(B2:P8) -> 19120.31
A13: Remaing Spend | B13: =SUM(B11-B12) -> -7120.31
A15: Weekly Food Revenue | B15: =SUM(R2:R8) -> 74911.56
A16: Weekly Cost % | B16: =B12/B15 -> 0.25523844
A19: End of week status | G19: Scallops
A20: list items over $100 | G20: Date delivered | H20: Weight billed (lbs) | I20: Weight received (lbs)
A21: Items carrying over | B21: Amount | C21: Items discarded | D21: Amount | G21: 44831 | H21: 8.75# | I21: 8.75#
A22: Short Ribs | B22: 1453.28 | G22: 44832 | H22: 8# | I22: 8#
H29: Total left at EOW
A34: Total | B34: =sum(B22:B33) -> 1453.28 | D34: =sum(D22:D33) -> 0

Sheet Roister (103 - 109)
B1: CW | C1: Fortune | D1: Closed Loop | E1: A1 Firewood | F1: Superior | G1: Aya | H1: Rocker Bros | I1: D'artagnan | J1: Four Star | K1: Regalis | L1: Cornille | M1: Truffles | N1: Rare Tea Cellar | O1: Steve's | P1: Turano | Q1: Daily Spend | R1: Daily Revenue | S1: Daily Cost %
A2: 44837 | B2: 2583.21 | C2: 1070.23 | I2: 1453.28 | Q2: =SUM(B2:P2) -> 5106.72 | R2: 6942.4 | S2: =Q2/R2 -> 0.73558424 | T2: =A2 -> 44837
A3: 44838 | B3: 2262.57 | C3: 133.15 | Q3: =SUM(B3:P3) -> 2395.72 | R3: 6371.65 | S3: =Q3/R3 -> 0.3759968 | T3: =A3 -> 44838
A4: 44839 | B4: 1448.37 | E4: 390 | F4: 748.9 | G4: 49.5 | J4: 300 | M4: 440 | O4: 100 | Q4: =SUM(B4:P4) -> 3476.77 | R4: 7168 | S4: =Q4/R4 -> 0.48504046 | T4: =A4 -> 44839
A5: 44840 | B5: 1487.24 | C5: 50 | N5: 50.85 | Q5: =SUM(B5:P5) -> 1588.09 | R5: 8632 | S5: =Q5/R5 -> 0.18397706 | T5: =A5 -> 44840
A6: 44841 | B6: 2456.99 | F6: 516.9 | G6: 142.5 | O6: 100 | P6: 221.94 | Q6: =SUM(B6:P6) -> 3438.33 | R6: 11710 | S6: =Q6/R6 -> 0.2936234 | T6: =A6 -> 44841
A7: 44842 | B7: 1573.9 | C7: 449.52 | D7: 882 | G7: 33 | H7: 495.48 | L7: 1000 | Q7: =SUM(B7:P7) -> 4433.9 | R7: 17551 | S7: =Q7/R7 -> 0.25262948 | T7: =A7 -> 44842
A8: 44843 | B8: N/A | C8: N/A | D8: N/A | E8: N/A | F8: N/A | G8: N/A | H8: N/A | I8: N/A | J8: N/A | K8: N/A | L8: N/A | M8: N/A | N8: N/A | O8: N/A | P8: N/A | Q8: 0 | R8: 13629.15 | S8: =Q8/R8 -> 0 | T8: =A8 -> 44843
Q9: Wabash seafood
A10: Actuals | B10: 11334.13 | C10: 1702.9 | D10: 882 | E10: 390 | F10: 1265.8 | G10: 258 | H10: 495.48 | I10: 1453.28 | L10: 969 | M10: 513.98 | N10: 50.85 | O10: 466.62 | P10: 221.94 | Q10: 488.35
A11: Difference | B11: =sum(B2:B8)-B10 -> 478.15 | C11: =sum(C2:C8)-C10 -> 0 | D11: =sum(D2:D8)-D10 -> 0 | E11: =sum(E2:E8)-E10 -> 0 | F11: =sum(F2:F8)-F10 -> 0 | G11: =sum(G2:G8)-G10 -> -33 | H11: =sum(H2:H8)-H10 -> 0 | I11: =sum(I2:I8)-I10 -> 0 | ... P11: =sum(P2:P8)-P10 -> 0 | Q11: =Q10-0 -> 488.35
A13: Budget | B13: 12000
A14: Total Weekly Spend | B14: =SUM(B2:P8) -> 20439.53
A15: Remaing Spend | B15: =SUM(B13-B14) -> -8439.53
A17: Weekly Food Revenue | B17: =SUM(R2:R8) -> 72004.2
A18: Weekly Cost % | B18: =B14/B17 -> 0.2838658
A21: End of week status | G21: Scallops
A22: list items over $100 | G22: Date delivered | H22: Weight billed (lbs) | I22: Weight received (lbs)
A23: Items carrying over | B23: Amount | C23: Items discarded | D23: Amount
A24: Jamon | B24: 431.37
H31: Total left at EOW
A36: Total | B36: =sum(B24:B35) -> 431.37 | D36: =sum(D24:D35) -> 0

Sheet Roister (1010 - 1016)
B1: CW | C1: Fortune | D1: Closed Loop | E1: A1 Firewood | F1: Superior | G1: Aya | H1: Rocker Bros | I1: D'artagnan | J1: Four Star | K1: Regalis | L1: Cornille | M1: Truffles | N1: Rare Tea Cellar | O1: Steve's | P1: Turano | Q1: Daily Spend | R1: Daily Revenue | S1: Daily Cost %
A2: 44844 | B2: 3070.18 | C2: 50 | J2: 180 | Q2: =SUM(B2:P2) -> 3300.18 | R2: 8964 | S2: =Q2/R2 -> 0.3681593 | T2: ='Roister (1010 - 1016)'!A2 -> 44844
A3: 44845 | B3: 2364.25 | C3: 604.66 | Q3: =SUM(B3:P3) -> 2968.91 | R3: 6832 | S3: =Q3/R3 -> 0.43455943 | T3: ='Roister (1010 - 1016)'!A3 -> 44845
A4: 44846 | B4: 1820.05 | C4: 204.17 | E4: 390 | F4: 922.9 | G4: 49.5 | O4: 100 | Q4: =SUM(B4:P4) -> 3486.62 | R4: 7365.6 | S4: =Q4/R4 -> 0.47336537 | T4: ='Roister (1010 - 1016)'!A4 -> 44846
A5: 44847 | B5: 1934.91 | C5: 209.2 | K5: 129.19 | Q5: =SUM(B5:P5) -> 2273.3 | R5: 7981.4 | S5: =Q5/R5 -> 0.28482472 | T5: ='Roister (1010 - 1016)'!A5 -> 44847
A6: 44848 | B6: 1401.16 | C6: 537.49 | F6: 632.9 | G6: 142.5 | O6: 100 | P6: 302.37 | Q6: =SUM(B6:P6) -> 3116.42 | R6: 12383.2 | S6: =Q6/R6 -> 0.25166516 | T6: ='Roister (1010 - 1016)'!A6 -> 44848
A7: 44849 | B7: 1905.34 | C7: 290.91 | D7: 228.5 | G7: 33 | H7: 885.7 | L7: 1727.5 | Q7: =SUM(B7:P7) -> 5070.95 | R7: 17276 | S7: =Q7/R7 -> 0.2935257 | T7: ='Roister (1010 - 1016)'!A7 -> 44849
A8: 44850 | B8: N/A | C8: N/A | D8: N/A | E8: N/A | F8: N/A | G8: N/A | H8: N/A | I8: N/A | J8: N/A | K8: N/A | L8: N/A | M8: N/A | N8: N/A | O8: N/A | P8: N/A | Q8: 0 | R8: 11233 | S8: =Q8/R8 -> 0 | T8: ='Roister (1010 - 1016)'!A8 -> 44850
A11: Budget | B11: 14000
A12: Total Weekly Spend | B12: =SUM(B2:P8) -> 20216.38
A13: Remaing Spend | B13: =SUM(B11-B12) -> -6216.38
A15: Weekly Food Revenue | B15: =SUM(R2:R8) -> 72035.2
A16: Weekly Cost % | B16: =B12/B15 -> 0.28064585
A19: End of week status | G19: Scallops
A20: list items over $100 | G20: Date delivered | H20: Weight billed (lbs) | I20: Weight received (lbs)
A21: Items carrying over | B21: Amount | C21: Items discarded | D21: Amount
A22: Short Rib | B22: 1338.36
A23: Trout | B23: 686.64
A24: Cheddar | B24: 129.19
H29: Total left at EOW
A34: Total | B34: =sum(B22:B33) -> 2154.19 | D34: =sum(D22:D33) -> 0

Sheet Roister (1017-1023)
B1: CW | C1: Fortune | D1: Closed Loop | E1: A1 Firewood | F1: Superior | G1: Aya | H1: Rocker Bros | I1: D'artagnan | J1: Four Star | K1: Regalis | L1: Cornille | M1: Truffles | N1: Rare Tea Cellar | O1: Steve's | P1: Turano | Q1: Daily Spend | R1: Daily Revenue | S1: Daily Cost %
A2: 44851 | B2: 3671.82 | C2: 594.91 | F2: 343.32 | I2: 1338.36 | J2: 441.97 | K2: 129.19 | O2: 100 | Q2: =SUM(B2:P2) -> 6619.57 | R2: 7080.5 | S2: =Q2/R2 -> 0.93490149 | T2: =A2 -> 44851
A3: 44852 | B3: 1298.79 | C3: 63.45 | Q3: =SUM(B3:P3) -> 1362.24 | R3: 6313.1 | S3: =Q3/R3 -> 0.21577989 | T3: =A3 -> 44852
A4: 44853 | B4: 855.25 | C4: 574.78 | E4: 390 | F4: 748.9 | G4: 49.5 | O4: 100 | Q4: =SUM(B4:P4) -> 2718.43 | R4: 6976 | S4: =Q4/R4 -> 0.3896832 | T4: =A4 -> 44853
A5: 44854 | B5: 2150.1 | C5: 315.71 | N5: 61.9 | Q5: =SUM(B5:P5) -> 2527.71 | R5: 7550.4 | S5: =Q5/R5 -> 0.33477829 | T5: =A5 -> 44854
A6: 44855 | B6: 2000.37 | C6: 247.26 | F6: 748.9 | G6: 142.5 | K6: 116.45 | O6: 100 | P6: 221.94 | Q6: =SUM(B6:P6) -> 3577.42 | R6: 11938.6 | S6: =Q6/R6 -> 0.29965155 | T6: =A6 -> 44855
A7: 44856 | B7: 2206.37 | C7: 332.41 | D7: 876 | G7: 33 | H7: 379.35 | L7: 912 | Q7: =SUM(B7:P7) -> 4739.13 | R7: 13995.4 | S7: =Q7/R7 -> 0.33862055 | T7: =A7 -> 44856
A8: 44857 | B8: N/A | C8: N/A | D8: N/A | E8: N/A | F8: N/A | G8: N/A | H8: N/A | I8: N/A | J8: N/A | K8: N/A | L8: N/A | M8: N/A | N8: N/A | O8: N/A | P8: N/A | Q8: 0 | R8: 10065.2 | S8: =Q8/R8 -> 0 | T8: =A8 -> 44857
Q9: Spirit Tea | R9: Wabash
A10: Actuals | B10: 13968.7 | C10: 2850.99 | D10: 876 | E10: 390 | F10: 1841.12 | G10: 225 | H10: 663.53 | I10: 1898.41 | J10: 441.97 | K10: 245.64 | L10: 912 | M10: 424 | N10: 61.9 | O10: 316.96 | P10: 221.94 | Q10: 242.77 | R10: 415.43
A11: Difference | B11: =sum(B2:B8)-B10 -> -1786 | C11: =sum(C2:C8)-C10 -> -722.47 | D11: =sum(D2:D8)-D10 -> 0 | E11: =sum(E2:E8)-E10 -> 0 | F11: =sum(F2:F8)-F10 -> 0 | G11: =sum(G2:G8)-G10 -> 0 | H11: =sum(H2:H8)-H10 -> -284.18 | I11: =sum(I2:I8)-I10 -> -560.05 | ... P11: =sum(P2:P8)-P10 -> 0 | Q11: =Q10-0 -> 242.77 | R11: =R10-0 -> 415.43
E12: CW
A13: Budget | B13: 12000 | E13: 44851 | F13: 3671.74
A14: Total Weekly Spend | B14: =SUM(B2:P8) -> 21544.5 | E14: 44852 | F14: 1298.79
A15: Remaing Spend | B15: =SUM(B13-B14) -> -9544.5 | E15: 44853 | F15: 825.31
E16: 44854 | F16: 2016.69
A17: Weekly Food Revenue | B17: =SUM(R2:R8) -> 63919.2 | E17: 44855 | F17: 1994.43
A18: Weekly Cost % | B18: =B14/B17 -> 0.33705835 | E18: 44856 | F18: 1961.87
E19: Total | F19: 11768.83
A21: End of week status | G21: Scallops
A22: list items over $100 | G22: Date delivered | H22: Weight billed (lbs) | I22: Weight received (lbs)
A23: Items carrying over | B23: Amount | C23: Items discarded | D23: Amount | G23: 44853
A24: Trout | B24: 343.32
A25: Duck | B25: 381.3
A26: Jamon | B26: 465.59
A27: Short Rib | B27: 560.05
A28: Short Rib | B28: 312.78
H31: Total left at EOW
A36: Total | B36: =sum(B24:B35) -> 2063.04 | D36: =sum(D24:D35) -> 0

Sheet Roister (1024-1030)
B1: CW | C1: Fortune | D1: Closed Loop | E1: A1 Firewood | F1: Superior | G1: Aya | H1: Rocker Bros | I1: D'artagnan | J1: Four Star | K1: Regalis | L1: Cornille | M1: Truffles | N1: Rare Tea Cellar | O1: Steve's | P1: Turano | Q1: Daily Spend | R1: Daily Revenue | S1: Daily Cost %
A2: 44858 | B2: 1880.22 | C2: 778.37 | F2: 343.32 | H2: 381.3 | I2: 560.05 | J2: 180 | M2: 424 | O2: 100 | Q2: =SUM(B2:P2) -> 4647.26 | R2: 5113.6 | S2: =Q2/R2 -> 0.90880397 | T2: =A2 -> 44858
A3: 44859 | B3: 1957.31 | C3: 242.4 | K3: 97.75 | N3: 16.95 | Q3: =SUM(B3:P3) -> 2314.41 | R3: 7416.4 | S3: =Q3/R3 -> 0.3120665 | T3: =A3 -> 44859
A4: 44860 | B4: 1227.57 | C4: 718.67 | E4: 390 | F4: 649.95 | G4: 49.5 | O4: 100 | Q4: =SUM(B4:P4) -> 3135.69 | R4: 7212.26 | S4: =Q4/R4 -> 0.43477218 | T4: =A4 -> 44860
A5: 44861 | B5: 1133.02 | C5: 93.28 | Q5: =SUM(B5:P5) -> 1226.3 | R5: 6019 | S5: =Q5/R5 -> 0.20373816 | T5: =A5 -> 44861
A6: 44862 | B6: 1687.16 | C6: 238.59 | G6: 142.5 | O6: 100 | P6: 221.94 | Q6: =SUM(B6:P6) -> 2390.19 | R6: 10827 | S6: =Q6/R6 -> 0.22076198 | T6: =A6 -> 44862
A7: 44863 | B7: 1034.79 | C7: 192.23 | D7: 362 | G7: 33 | H7: 625.07 | L7: 766.5 | Q7: =SUM(B7:P7) -> 3013.59 | R7: 13140.5 | S7: =Q7/R7 -> 0.22933602 | T7: =A7 -> 44863
A8: 44864 | B8: N/A | C8: N/A | D8: N/A | E8: N/A | F8: N/A | G8: N/A | H8: N/A | I8: N/A | J8: N/A | K8: N/A | L8: N/A | M8: N/A | N8: N/A | O8: N/A | P8: N/A | Q8: 0 | R8: 8890.5 | S8: =Q8/R8 -> 0 | T8: =A8 -> 44864
Q9: Wabash | R9: Wine dinner
A10: Actuals | B10: 8904.62 | C10: 2463.54 | D10: 418 | E10: 390 | F10: 1526.85 | G10: 225 | H10: 625.07 | I10: 2046.35 | J10: 180 | K10: 97.75 | L10: 810.75 | M10: 424 | N10: 16.95 | O10: 466.62 | Q10: 257.99 | R10: 413.23
A11: Difference | B11: =sum(B2:B8)-B10 -> 15.45 | C11: =sum(C2:C8)-C10 -> -200 | D11: =sum(D2:D8)-D10 -> -56 | E11: =sum(E2:E8)-E10 -> 0 | F11: =sum(F2:F8)-F10 -> -533.58 | G11: =sum(G2:G8)-G10 -> 0 | H11: =sum(H2:H8)-H10 -> 381.3 | I11: =sum(I2:I8)-I10 -> -1486.3 | ... P11: =sum(P2:P8)-P10 -> 221.94 | Q11: =Q10-0 -> 257.99 | R11: =R10-0 -> 413.23
L12: Currently using an estimate
A13: Budget | B13: 12000 | F13: Superior - in COGS | O13: Steve's - COGS
A14: Total Weekly Spend | B14: =SUM(B2:P8) -> 16727.44 | C14: 18414 | D14: =C14-B14 -> 1686.56 | F14: 10/26 - 1009.95 | O14: Includes sunflowers, tax, and delivery fee
A15: Remaing Spend | B15: =SUM(B13-B14) -> -4727.44 | F15: 10/28 - 516.9
A17: Weekly Food Revenue | B17: =SUM(R2:R8) -> 58619.26
A18: Weekly Cost % | B18: =B14/B17 -> 0.28535741
A21: End of week status | G21: Scallops
A22: list items over $100 | G22: Date delivered | H22: Weight billed (lbs) | I22: Weight received (lbs)
A23: Items carrying over | B23: Amount | C23: Items discarded | D23: Amount | G23: 44858 | H23: 16# | I23: 16#
A24: Scallops | B24: 380 | G24: 44862 | H24: 8#
A25: Oysters | B25: 200
H31: Total left at EOW
A36: Total | B36: =sum(B24:B35) -> 580 | D36: =sum(D24:D35) -> 0

Sheet Roister (1031-116)
B1: CW | C1: Fortune | D1: Closed Loop | E1: A1 Firewood | F1: Wabash | G1: Superior | H1: Aya | I1: Rocker Bros | J1: D'artagnan | K1: Four Star | L1: Regalis | M1: Cornille | N1: Truffles | O1: Rare Tea Cellar | P1: Steve's | Q1: Turano | R1: Daily Spend | S1: Daily Revenue | T1: Daily Cost %
A2: 44865 | B2: 1230.47 | C2: 315.71 | G2: 380 | J2: 1335.17 | K2: 180 | N2: 424 | P2: 100 | R2: =SUM(B2:Q2) -> 3965.35 | S2: 2368.2 | T2: =R2/S2 -> 1.6744152 | U2: =A2 -> 44865
A3: 44866 | B3: 3004.87 | C3: 103.35 | O3: 16.95 | Q3: 221.94 | R3: =SUM(B3:Q3) -> 3347.11 | S3: 5955.3 | T3: =R3/S3 -> 0.56203886 | U3: =A3 -> 44866
A4: 44867 | B4: 1001.9 | C4: 52.88 | E4: 240 | H4: 49.5 | P4: 100 | R4: =SUM(B4:Q4) -> 1444.28 | S4: =6755+369 -> 7124 | T4: =R4/S4 -> 0.20273442 | U4: =A4 -> 44867
A5: 44868 | B5: 1773.17 | C5: 422.3 | G5: 126.72 | R5: =SUM(B5:Q5) -> 2322.19 | S5: 8641.3 | T5: =R5/S5 -> 0.26873156 | U5: =A5 -> 44868
A6: 44869 | B6: 982.6 | G6: 516.9 | H6: 142.5 | P6: 100 | R6: =SUM(B6:Q6) -> 1742 | S6: 13867 | T6: =R6/S6 -> 0.12562198 | U6: =A6 -> 44869
A7: 44870 | B7: 2056.02 | C7: 326.95 | D7: 800 | H7: 33 | M7: 800 | R7: =SUM(B7:Q7) -> 4015.97 | S7: 15821.01 | T7: =R7/S7 -> 0.25383778 | U7: =A7 -> 44870
A8: 44871 | B8: N/A | C8: N/A | D8: N/A | E8: N/A | G8: N/A | H8: N/A | I8: N/A | J8: N/A | K8: N/A | L8: N/A | M8: N/A | N8: N/A | O8: N/A | P8: N/A | Q8: N/A | R8: 0 | S8: 9909.2 | T8: =R8/S8 -> 0 | U8: =A8 -> 44871
A10: Actuals | B10: 10564.26 | C10: 1664.25 | D10: 679 | E10: 290 | F10: 132.97 | G10: 1169.87 | H10: 225 | J10: 1460.63 | K10: 180 | M10: 828.33 | P10: 616.28 | Q10: 221.94
A11: Difference | B11: =sum(B2:B8)-B10 -> -515.23 | C11: =sum(C2:C8)-C10 -> -443.06 | D11: =sum(D2:D8)-D10 -> 121 | E11: =sum(E2:E8)-E10 -> -50 | F11: =sum(F2:F8)-F10 -> -132.97 | G11: =sum(G2:G8)-G10 -> -146.25 | H11: =sum(H2:H8)-H10 -> 0 | I11: =sum(I2:I8)-I10 -> 0 | ... P11: =sum(P2:P8)-P10 -> -316.28 | Q11: =Q10-0 -> 221.94 | R11: =R10-0 -> 0
M12: Estimate based on 6-week avg
C13: 383.47 | D13: $197 in oysterd carried into this week | F13: 126.72 - Bronzini on 11/3
A14: Budget | B14: 12000 | C14: 103.35 | G14: Carried $380 in scallops + $272 of smoked trout | P14: Missing sunflowers, tax, and delivery fee
A15: Total Weekly Spend | B15: =SUM(B2:Q8) -> 16836.9 | C15: 133.38 | D15: Beeef knuckle bones -- Kaysen event + $5 fuel surcharge
A16: Remaing Spend | B16: =SUM(B14-B15) -> -4836.9 | C16: 722.1 | D16: 195 clams kaysen, $295 in oysters. Some for SCSC?
A18: Weekly Food Revenue | B18: =SUM(S2:S8) -> 63686.01 | C18: 321.95
A19: Weekly Cost % | B19: =B15/B18 -> 0.2643736
A22: End of week status | H22: Scallops
A23: list items over $100 | H23: Date delivered | I23: Weight billed (lbs) | J23: Weight received (lbs)
A24: Items carrying over | B24: Amount | C24: Items discarded | D24: Amount | H24: 44869 | I24: 4# | J24: 4#
A25: Chicken Breasts | B25: 208.5 | I25: 8#
A26: 16# short Ribs | B26: 255.84
A27: White Chocolate | B27: 104.55
I32: Total left at EOW

Sheet Roister (117-1113)
B1: CW | C1: Fortune | D1: Closed Loop | E1: A1 Firewood | F1: Wabash | G1: Superior | H1: Aya | I1: Rocker Bros | J1: D'artagnan | K1: Four Star | L1: Regalis | M1: Cornille | N1: Truffles | O1: Rare Tea Cellar | P1: Steve's | Q1: Turano | R1: Daily Spend | S1: Daily Revenue | T1: Daily Cost %
A2: 44872 | B2: 2133.64 | C2: 1221.35 | E2: 190 | F2: 157.72 | J2: 255.84 | K2: 180 | P2: 100 | R2: =SUM(B2:Q2) -> 4238.55 | S2: 4604.4 | T2: =R2/S2 -> 0.92054339 | U2: =A2 -> 44872
A3: 44873 | B3: 1813.64 | C3: 781.22 | G3: 232 | J3: 607.94 | O3: 80 | R3: =SUM(B3:Q3) -> 3514.8 | S3: 5745 | T3: =R3/S3 -> 0.61180157 | U3: =A3 -> 44873
A4: 44874 | B4: 679.96 | C4: 29 | E4: 390 | F4: 516.9 | H4: 49.5 | O4: 19 | P4: 100 | Q4: 221.78 | R4: =SUM(B4:Q4) -> 2006.14 | S4: 8323 | T4: =R4/S4 -> 0.24103568 | U4: =A4 -> 44874
A5: 44875 | B5: 1879.41 | R5: =SUM(B5:Q5) -> 1879.41 | S5: 7674.4 | T5: =R5/S5 -> 0.24489341 | U5: =A5 -> 44875
A6: 44876 | B6: 2227.33 | C6: 234.15 | G6: 846.82 | H6: 142.5 | P6: 100 | R6: =SUM(B6:Q6) -> 3550.8 | S6: 13619.95 | T6: =R6/S6 -> 0.2607058 | U6: =A6 -> 44876
A7: 44877 | B7: 1035.32 | C7: 228.39 | D7: 800 | E7: 190 | H7: 33 | M7: 401 | R7: =SUM(B7:Q7) -> 2687.71 | S7: 15575.4 | T7: =R7/S7 -> 0.17256122 | U7: =A7 -> 44877
A8: 44878 | B8: N/A | C8: N/A | D8: N/A | E8: N/A | G8: N/A | H8: N/A | I8: N/A | J8: N/A | K8: N/A | L8: N/A | M8: N/A | N8: N/A | O8: N/A | P8: N/A | Q8: N/A | R8: 0 | S8: 9738 | T8: =R8/S8 -> 0 | U8: =A8 -> 44878
A10: Actuals | B10: 9967.53 | C10: 2499.11 | D10: 714 | E10: 670 | F10: 169.15 | G10: 1595.72 | H10: 225 | J10: 863.78 | K10: 180 | M10: 401 | O10: 99 | P10: 299.32
A11: Difference | B11: =sum(B2:B8)-B10 -> -198.23 | C11: =sum(C2:C8)-C10 -> -5 | D11: =sum(D2:D8)-D10 -> 86 | E11: =sum(E2:E8)-E10 -> 100 | F11: =sum(F2:F8)-F10 -> 505.47 | G11: =sum(G2:G8)-G10 -> -516.9 | H11: =sum(H2:H8)-H10 -> 0 | I11: =sum(I2:I8)-I10 -> 0 | ... P11: =sum(P2:P8)-P10 -> 0.68 | Q11: =Q10-0 -> 0 | R11: =R10-0 -> 0
A14: Budget | B14: 12000
A15: Total Weekly Spend | B15: =SUM(B2:Q8) -> 17877.41
A16: Remaing Spend | B16: =SUM(B14-B15) -> -5877.41
A18: Weekly Food Revenue | B18: =SUM(S2:S8) -> 65280.15
A19: Weekly Cost % | B19: =B15/B18 -> 0.27385675
A22: End of week status | H22: Scallops
A23: list items over $100 | H23: Date delivered | I23: Weight billed (lbs) | J23: Weight received (lbs)
A24: Items carrying over | B24: Amount | C24: Items discarded | D24: Amount | I24: 8#
A25: Jamon | B25: 490.94 | I25: 8#
A26: Short Ribs | B26: 607.94
A27: Trout | B27: 248.36
A28: Collars | B28: 142.45
A29: Scallops | B29: 116
I32: Total left at EOW

Sheet Roister (1114-1120)
B1: CW | C1: Fortune | D1: Closed Loop | E1: A1 Firewood | F1: Wabash | G1: Superior | H1: Aya | I1: Rocker Bros | J1: D'artagnan | K1: Four Star | L1: Regalis | M1: Cornille | N1: Truffles | O1: Rare Tea Cellar | P1: Steve's | Q1: Turano | R1: Daily Spend | S1: Daily Revenue | T1: Daily Cost %
A2: 44879 | B2: 3213.91 | C2: 797.34 | E2: 190 | G2: 506.81 | J2: 607.94 | K2: 180 | P2: 100 | R2: =SUM(B2:Q2) -> 5596 | S2: 5665 | T2: =R2/S2 -> 0.98781995 | U2: =A2 -> 44879
A3: 44880 | B3: 712.94 | Q3: 221.94 | R3: =SUM(B3:Q3) -> 934.88 | S3: 6862 | T3: =R3/S3 -> 0.13624016 | U3: =A3 -> 44880
A4: 44881 | B4: 1002.7 | C4: 505.24 | G4: 827.14 | H4: 49.5 | O4: 58 | P4: 100 | R4: =SUM(B4:Q4) -> 2542.58 | S4: 11288 | T4: =R4/S4 -> 0.22524628 | U4: =A4 -> 44881
A5: 44882 | B5: 1748.03 | C5: 252.96 | E5: 390 | F5: 55.46 | R5: =SUM(B5:Q5) -> 2446.45 | S5: =8787.13+433 -> 9220.13 | T5: =R5/S5 -> 0.26533791 | U5: =A5 -> 44882
A6: 44883 | B6: 1566.26 | G6: 686.9 | H6: 142.5 | P6: 100 | R6: =SUM(B6:Q6) -> 2495.66 | S6: 9112.21 | T6: =R6/S6 -> 0.27388087 | U6: =A6 -> 44883
A7: 44884 | B7: 1506.27 | C7: 66.8 | D7: 800 | E7: 190 | H7: 33 | M7: 628.5 | R7: =SUM(B7:Q7) -> 3224.57 | S7: 12970.8 | T7: =R7/S7 -> 0.24860224 | U7: =A7 -> 44884
A8: 44885 | B8: N/A | C8: N/A | D8: N/A | E8: N/A | G8: N/A | H8: N/A | I8: N/A | J8: N/A | K8: N/A | L8: N/A | M8: N/A | N8: N/A | O8: N/A | P8: N/A | Q8: N/A | R8: 0 | S8: =3457+5428 -> 8885 | T8: =R8/S8 -> 0 | U8: =A8 -> 44885
A10: Actuals | B10: 10519.55 | C10: 1617.34 | D10: 47.5 | E10: 580 | F10: 57.96 | G10: 2022.77 | H10: 225 | J10: 1225.96 | K10: 120 | M10: 628.5 | O10: 58 | P10: 422.52 | Q10: 221.78
A11: Difference | B11: =sum(B2:B8)-B10 -> -769.44 | C11: =sum(C2:C8)-C10 -> 5 | D11: =sum(D2:D8)-D10 -> 752.5 | E11: =sum(E2:E8)-E10 -> 190 | F11: =sum(F2:F8)-F10 -> -2.5 | G11: =sum(G2:G8)-G10 -> -1.92 | H11: =sum(H2:H8)-H10 -> 0 | I11: =sum(I2:I8)-I10 -> 0 | ... P11: =sum(P2:P8)-P10 -> -122.52 | Q11: =Q10-0 -> 221.78 | R11: =R10-0 -> 0
A14: Budget | B14: 12000
A15: Total Weekly Spend | B15: =SUM(B2:Q8) -> 17240.14
A16: Remaing Spend | B16: =SUM(B14-B15) -> -5240.14
A18: Weekly Food Revenue | B18: =SUM(S2:S8) -> 64003.14
A19: Weekly Cost % | B19: =B15/B18 -> 0.26936397
A22: End of week status | H22: Scallops
A23: list items over $100 | H23: Date delivered | I23: Weight billed (lbs) | J23: Weight received (lbs)
A24: Items carrying over | B24: Amount | C24: Items discarded | D24: Amount
A25: Short Ribs | B25: 618.01
I32: Total left at EOW

Sheet Roister (1121-1127)
B1: CW | C1: Fortune | D1: Closed Loop | E1: A1 Firewood | F1: Wabash | G1: Superior | H1: Aya | I1: Rocker Bros | J1: D'artagnan | K1: Four Star | L1: Regalis | M1: Cornille | N1: Truffles | O1: Rare Tea Cellar | P1: Steve's | Q1: Turano | R1: Daily Spend | S1: Daily Revenue | T1: Daily Cost %
A2: 44886 | J2: 618.01 | K2: 180 | P2: 100 | R2: =SUM(B2:Q2) -> 898.01 | S2: 0 | T2: =R2/S2 -> #DIV/0! | U2: =A2 -> 44886
A3: 44887 | Q3: 221.94 | R3: =SUM(B3:Q3) -> 221.94 | S3: 0 | T3: =R3/S3 -> #DIV/0! | U3: =A3 -> 44887
A4: 44888 | P4: 100 | R4: =SUM(B4:Q4) -> 100 | S4: 0 | T4: =R4/S4 -> #DIV/0! | U4: =A4 -> 44888
A5: 44889 | R5: =SUM(B5:Q5) -> 0 | S5: 0 | T5: =R5/S5 -> #DIV/0! | U5: =A5 -> 44889
A6: 44890 | B6: 2112.52 | P6: 100 | R6: =SUM(B6:Q6) -> 2212.52 | S6: 0 | T6: =R6/S6 -> #DIV/0! | U6: =A6 -> 44890
A7: 44891 | B7: 1199.04 | C7: 960.37 | D7: 266 | E7: 190 | G7: 804.15 | H7: 109 | M7: 298.5 | R7: =SUM(B7:Q7) -> 3827.06 | S7: 7680 | T7: =R7/S7 -> 0.4983151 | U7: =A7 -> 44891
A8: 44892 | B8: N/A | C8: N/A | D8: N/A | E8: N/A | G8: N/A | H8: N/A | I8: N/A | J8: N/A | K8: N/A | L8: N/A | M8: N/A | N8: N/A | O8: N/A | P8: N/A | Q8: N/A | R8: 0 | S8: 9344 | T8: =R8/S8 -> 0 | U8: =A8 -> 44892
A11: Budget | B11: 12000
A12: Total Weekly Spend | B12: =SUM(B2:Q8) -> 7259.53
A13: Remaing Spend | B13: =SUM(B11-B12) -> 4740.47
A15: Weekly Food Revenue | B15: =SUM(S2:S8) -> 17024
A16: Weekly Cost % | B16: =B12/B15 -> 0.42642916
A19: End of week status | H19: Scallops
A20: list items over $100 | H20: Date delivered | I20: Weight billed (lbs) | J20: Weight received (lbs)
A21: Items carrying over | B21: Amount | C21: Items discarded | D21: Amount
A22: Jamon | B22: 365.04
I29: Total left at EOW

Sheet Roister (1128 - 124)
B1: CW | C1: Fortune | D1: Closed Loop | E1: A1 Firewood | F1: Wabash | G1: Superior | H1: Aya | I1: Rocker Bros | J1: D'artagnan | K1: Four Star | L1: Regalis | M1: Cornille | N1: Truffles | O1: Rare Tea Cellar | P1: Steve's | Q1: Turano | R1: Daily Spend | S1: Daily Revenue | T1: Daily Cost %
A2: 44893 | B2: 3126.3 | C2: 604.51 | F2: 330.68 | K2: 180 | P2: 100 | R2: =SUM(B2:Q2) -> 4341.49 | S2: 5133.1 | T2: =R2/S2 -> 0.84578325 | U2: =A2 -> 44893
A3: 44894 | B3: 1127.07 | C3: 356.42 | Q3: 221.94 | R3: =SUM(B3:Q3) -> 1705.43 | S3: 5907 | T3: =R3/S3 -> 0.28871339 | U3: =A3 -> 44894
A4: 44895 | B4: 2081.34 | G4: 729.4 | H4: 49.5 | J4: 823.48 | P4: 100 | R4: =SUM(B4:Q4) -> 3783.72 | S4: =7087+305 -> 7392 | T4: =R4/S4 -> 0.51186688 | U4: =A4 -> 44895
A5: 44896 | B5: 1948.12 | C5: 226.22 | E5: 290 | F5: 168.96 | R5: =SUM(B5:Q5) -> 2633.3 | S5: 7085.75 | T5: =R5/S5 -> 0.37163321 | U5: =A5 -> 44896
A6: 44897 | B6: 1059.6 | C6: 430.81 | G6: 170 | H6: 142.5 | O6: 49 | P6: 100 | R6: =SUM(B6:Q6) -> 1951.91 | S6: =10454.4+612 -> 11066.4 | T6: =R6/S6 -> 0.17638166 | U6: =A6 -> 44897
A7: 44898 | B7: 1737.69 | C7: 149.2 | D7: 400 | E7: 190 | F7: 370.1 | H7: 33 | M7: 460.5 | R7: =SUM(B7:Q7) -> 3340.49 | S7: 13261 | T7: =R7/S7 -> 0.25190333 | U7: =A7 -> 44898
A8: 44899 | B8: N/A | C8: N/A | D8: N/A | E8: N/A | G8: N/A | H8: N/A | I8: N/A | J8: N/A | K8: N/A | L8: N/A | M8: N/A | N8: N/A | O8: N/A | P8: N/A | Q8: N/A | R8: 0 | S8: 6332 | T8: =R8/S8 -> 0 | U8: =A8 -> 44899
A11: Budget | B11: 14000
A12: Total Weekly Spend | B12: =SUM(B2:Q8) -> 17756.34
A13: Remaing Spend | B13: =SUM(B11-B12) -> -3756.34
A15: Weekly Food Revenue | B15: =SUM(S2:S8) -> 56177.25
A16: Weekly Cost % | B16: =B12/B15 -> 0.31607706
A19: End of week status | H19: Scallops
A20: list items over $100 | H20: Date delivered | I20: Weight billed (lbs) | J20: Weight received (lbs)
A21: Items carrying over | B21: Amount | C21: Items discarded | D21: Amount
A22: Short Ribs | B22: 823.48
A23: Mayo | B23: 106.91
A24: Oysters | B24: 250
A25: Chicken breasts | B25: 200
I29: Total left at EOW

Sheet Roister (1205 - 1211)
B1: CW | C1: Fortune | D1: Closed Loop | E1: A1 Firewood | F1: Wabash | G1: Superior | H1: Aya | I1: Rocker Bros | J1: D'artagnan | K1: Four Star | L1: Regalis | M1: Cornille | N1: Truffles | O1: Rare Tea Cellar | P1: Steve's | Q1: Turano | R1: Daily Spend | S1: Daily Revenue | T1: Daily Cost %
A2: 44900 | B2: 1570.77 | C2: 280.56 | F2: 568.14 | J2: 823.48 | K2: 180 | L2: 63.18 | P2: 100 | R2: =SUM(B2:Q2) -> 3586.13 | S2: 4188.5 | T2: =R2/S2 -> 0.85618479 | U2: =A2 -> 44900
A3: 44901 | B3: 1335.54 | C3: 227.36 | I3: 322.8 | Q3: 221.94 | R3: =SUM(B3:Q3) -> 2107.64 | S3: 5218 | T3: =R3/S3 -> 0.40391721 | U3: =A3 -> 44901
A4: 44902 | B4: 2501.03 | G4: 454.9 | H4: 49.5 | J4: 811.17 | P4: 100 | R4: =SUM(B4:Q4) -> 3916.6 | S4: 5696.3 | T4: =R4/S4 -> 0.68756912 | U4: =A4 -> 44902
A5: 44903 | B5: 1561.42 | C5: 198.69 | E5: 290 | R5: =SUM(B5:Q5) -> 2050.11 | S5: 12995.2 | T5: =R5/S5 -> 0.15775902 | U5: =A5 -> 44903
A6: 44904 | B6: 1256.27 | C6: 578.6 | F6: 85.8 | G6: 709.9 | H6: 114 | P6: 100 | R6: =SUM(B6:Q6) -> 2844.57 | S6: 11736.5 | T6: =R6/S6 -> 0.24236953 | U6: =A6 -> 44904
A7: 44905 | B7: 1454.81 | C7: 84 | D7: 298 | E7: 190 | F7: 310.75 | H7: 33 | M7: 496 | R7: =SUM(B7:Q7) -> 2866.56 | S7: 15580.7 | T7: =R7/S7 -> 0.18398146 | U7: =A7 -> 44905
A8: 44906 | B8: N/A | C8: N/A | D8: N/A | E8: N/A | G8: N/A | H8: N/A | I8: N/A | J8: N/A | K8: N/A | L8: N/A | M8: N/A | N8: N/A | O8: N/A | P8: N/A | Q8: N/A | R8: 0 | S8: 9820 | T8: =R8/S8 -> 0 | U8: =A8 -> 44906
A10: Actuals | B10: 9575.14 | C10: 1606.11 | D10: 298 | E10: 480 | F10: 964.4 | G10: 1164.8 | H10: 196.5 | I10: 322.8 | J10: 1634.66 | K10: 195 | L10: 63.18 | M10: 551 | N10: 540.84 | P10: 466.62 | Q10: 221.78
A11: Difference | B11: =sum(B2:B8)-B10 -> 104.7 | C11: =sum(C2:C8)-C10 -> -236.9 | D11: =sum(D2:D8)-D10 -> 0 | E11: =sum(E2:E8)-E10 -> 0 | F11: =sum(F2:F8)-F10 -> 0.29 | G11: =sum(G2:G8)-G10 -> 0 | H11: =sum(H2:H8)-H10 -> 0 | I11: =sum(I2:I8)-I10 -> 0 | ... Q11: =sum(Q2:Q8)-Q10 -> 0.16 | R11: =R10-0 -> 0
A13: Budget | B13: 12000
A14: Total Weekly Spend | B14: =SUM(B2:Q8) -> 17371.61
A15: Remaing Spend | B15: =SUM(B13-B14) -> -5371.61
A17: Weekly Food Revenue | B17: =SUM(S2:S8) -> 65235.2
A18: Weekly Cost % | B18: =B14/B17 -> 0.26629197
A21: End of week status | H21: Scallops
A22: list items over $100 | H22: Date delivered | I22: Weight billed (lbs) | J22: Weight received (lbs)
A23: Items carrying over | B23: Amount | C23: Items discarded | D23: Amount
A24: Short Ribs | B24: 811.17
A25: Jamon | B25: 471.51
I31: Total left at EOW

Sheet Roister (1212 - 1218)
B1: CW | C1: Fortune | D1: Closed Loop | E1: A1 Firewood | F1: Wabash | G1: Superior | H1: Aya | I1: Rocker Bros | J1: D'artagnan | K1: Four Star | L1: Regalis | M1: Cornille | N1: Truffles | O1: Rare Tea Cellar | P1: Steve's | Q1: Turano | R1: Daily Spend | S1: Daily Revenue | T1: Daily Cost %
A2: 44907 | B2: 1482.69 | C2: 1181.37 | F2: 156.41 | J2: 811.17 | K2: 180 | O2: 19 | P2: 100 | R2: =SUM(B2:Q2) -> 3930.64 | S2: 5290 | T2: =R2/S2 -> 0.74303214 | U2: =A2 -> 44907
A3: 44908 | B3: 2316.18 | C3: 239.62 | F3: 161.01 | Q3: 208.59 | R3: =SUM(B3:Q3) -> 2925.4 | S3: 6434.04 | T3: =R3/S3 -> 0.45467545 | U3: =A3 -> 44908
A4: 44909 | B4: 1847.76 | E4: 290 | F4: 345.85 | H4: 33 | P4: 100 | R4: =SUM(B4:Q4) -> 2616.61 | S4: =651+22528.8 -> 23179.8 | T4: =R4/S4 -> 0.1128832 | U4: =A4 -> 44909
A5: 44910 | B5: 1731.62 | C5: 173.86 | F5: 109.88 | G5: 284.9 | H5: 114 | J5: 678.61 | R5: =SUM(B5:Q5) -> 3092.87 | S5: =2721+9316 -> 12037 | T5: =R5/S5 -> 0.25694691 | U5: =A5 -> 44910
A6: 44911 | B6: 1374.68 | C6: 142.8 | F6: 273.02 | G6: 454.9 | P6: 100 | R6: =SUM(B6:Q6) -> 2345.4 | S6: =3113.4+11208.4 -> 14321.8 | T6: =R6/S6 -> 0.16376433 | U6: =A6 -> 44911
A7: 44912 | B7: 2131.34 | C7: 353.37 | D7: 300 | F7: 159.2 | H7: 33 | M7: 400 | Q7: 92.08 | R7: =SUM(B7:Q7) -> 3468.99 | S7: =4643+12368 -> 17011 | T7: =R7/S7 -> 0.20392628 | U7: =A7 -> 44912
A8: 44913 | B8: N/A | C8: N/A | D8: N/A | E8: N/A | G8: N/A | H8: N/A | I8: N/A | J8: N/A | K8: N/A | L8: N/A | M8: N/A | N8: N/A | O8: N/A | P8: N/A | Q8: N/A | R8: 0 | S8: 10072.6 | T8: =R8/S8 -> 0 | U8: =A8 -> 44913
A11: Budget | B11: 12000
A12: Total Weekly Spend | B12: =SUM(B2:Q8) -> 18379.91
A13: Remaing Spend | B13: =SUM(B11-B12) -> -6379.91
A15: Weekly Food Revenue | B15: =SUM(S2:S8) -> 88346.24
A16: Weekly Cost % | B16: =B12/B15 -> 0.20804405
A19: End of week status | H19: Scallops
A20: list items over $100 | H20: Date delivered | I20: Weight billed (lbs) | J20: Weight received (lbs)
A21: Items carrying over | B21: Amount | C21: Items discarded | D21: Amount
A22: Short Ribs | B22: 678.61
I29: Total left at EOW

Sheet Roister (1219 - 1225)
B1: CW | C1: Fortune | D1: Closed Loop | E1: A1 Firewood | F1: Wabash | G1: Superior | H1: Aya | I1: Rocker Bros | J1: D'artagnan | K1: Four Star | L1: Regalis | M1: Cornille | N1: Truffles | O1: Rare Tea Cellar | P1: Steve's | Q1: Turano | R1: Daily Spend | S1: Daily Revenue | T1: Daily Cost %
A2: 44914 | B2: 2119 | C2: 285.2 | F2: 152.28 | J2: 678.61 | K2: 180 | P2: 100 | R2: =SUM(B2:Q2) -> 3515.09 | S2: 6634.4 | T2: =R2/S2 -> 0.52982787 | U2: =A2 -> 44914
A3: 44915 | B3: 1398.71 | F3: 223.83 | H3: 33 | Q3: 208.59 | R3: =SUM(B3:Q3) -> 1864.13 | S3: 7955 | T3: =R3/S3 -> 0.23433438 | U3: =A3 -> 44915
A4: 44916 | B4: 2290.94 | C4: 246.04 | E4: 290 | F4: 190.62 | G4: 340 | J4: 900.03 | O4: 87.5 | P4: 100 | R4: =SUM(B4:Q4) -> 4445.13 | S4: =2131+3256.5 -> 5387.5 | T4: =R4/S4 -> 0.82508213 | U4: =A4 -> 44916
A5: 44917 | B5: 797.5 | F5: 208.27 | R5: =SUM(B5:Q5) -> 1005.77 | S5: =2909+1072 -> 3981 | T5: =R5/S5 -> 0.25264255 | U5: =A5 -> 44917
A6: 44918 | P6: 100 | R6: =SUM(B6:Q6) -> 100 | S6: =1398.6+4749 -> 6147.6 | T6: =R6/S6 -> 0.016266511 | U6: =A6 -> 44918
A7: 44919 | M7: 604.25 | R7: =SUM(B7:Q7) -> 604.25 | S7: 0 | T7: =R7/S7 -> #DIV/0! | U7: =A7 -> 44919
A8: 44920 | B8: N/A | C8: N/A | D8: N/A | E8: N/A | G8: N/A | H8: N/A | I8: N/A | J8: N/A | K8: N/A | L8: N/A | M8: N/A | N8: N/A | O8: N/A | P8: N/A | Q8: N/A | R8: 0 | S8: 0 | T8: =R8/S8 -> #DIV/0! | U8: =A8 -> 44920
A11: Budget | B11: 12000
A12: Total Weekly Spend | B12: =SUM(B2:Q8) -> 11534.37
A13: Remaining Spend | B13: =SUM(B11-B12) -> 465.63
A15: Weekly Food Revenue | B15: =SUM(S2:S8) -> 30105.5
A16: Weekly Cost % | B16: =B12/B15 -> 0.38313165
A19: End of week status | H19: Scallops
A20: list items over $100 | H20: Date delivered | I20: Weight billed (lbs) | J20: Weight received (lbs)
A21: Items carrying over | B21: Amount | C21: Items discarded | D21: Amount
A22: Short Ribs | B22: 900.03
A23: parm | B23: 106.3
I29: Total left at EOW

Sheet Roister (1226 - 11)
B1: CW | C1: Fortune | D1: Closed Loop | E1: A1 Firewood | F1: Wabash | G1: Superior | H1: Aya | I1: Rocker Bros | J1: D'artagnan | K1: Four Star | L1: Regalis | M1: Cornille | N1: Truffles | O1: Rare Tea Cellar | P1: Steve's | Q1: Turano | R1: Daily Spend | S1: Daily Revenue | T1: Daily Cost %
A2: 44921 | B2: 106.3 | J2: 900.03 | K2: 180 | P2: 100 | R2: =SUM(B2:Q2) -> 1286.33 | S2: 0 | T2: =R2/S2 -> #DIV/0! | U2: =A2 -> 44921
A3: 44922 | B3: 1728.94 | C3: 501.92 | H3: 33 | Q3: 208.59 | R3: =SUM(B3:Q3) -> 2472.45 | S3: 7741.8 | T3: =R3/S3 -> 0.31936371 | U3: =A3 -> 44922
A4: 44923 | B4: 2213.45 | C4: 437.32 | F4: 416.42 | G4: 340 | P4: 100 | R4: =SUM(B4:Q4) -> 3507.19 | S4: =2041+7402.4 -> 9443.4 | T4: =R4/S4 -> 0.3713906 | U4: =A4 -> 44923
A5: 44924 | B5: 1377.37 | C5: 247.8 | J5: 879.45 | R5: =SUM(B5:Q5) -> 2504.62 | S5: =2605+8349.5 -> 10954.5 | T5: =R5/S5 -> 0.22863846 | U5: =A5 -> 44924
A6: 44925 | B6: 1347.55 | C6: 457.14 | P6: 100 | R6: =SUM(B6:Q6) -> 1904.69 | S6: 13294.6 | T6: =R6/S6 -> 0.14326794 | U6: =A6 -> 44925
A7: 44926 | B7: 1578.81 | C7: 503.82 | E7: 190 | H7: 33 | I7: 134.5 | L7: 720 | M7: 652 | R7: =SUM(B7:Q7) -> 3812.13 | S7: 24311.01 | T7: =R7/S7 -> 0.15680673 | U7: =A7 -> 44926
A8: 44927 | B8: N/A | C8: N/A | D8: N/A | E8: N/A | G8: N/A | H8: N/A | I8: N/A | J8: N/A | K8: N/A | L8: N/A | M8: N/A | N8: N/A | O8: N/A | P8: N/A | Q8: N/A | R8: 0 | S8: 0 | T8: =R8/S8 -> #DIV/0! | U8: =A8 -> 44927
A11: Budget | B11: 12000
A12: Total Weekly Spend | B12: =SUM(B2:Q8) -> 15487.41
A13: Remaing Spend | B13: =SUM(B11-B12) -> -3487.41
A15: Weekly Food Revenue | B15: =SUM(S2:S8) -> 65745.31
A16: Weekly Cost % | B16: =B12/B15 -> 0.23556677
A19: End of week status
A20: list items over $100
A21: Items carrying over | B21: Amount | C21: Items discarded | D21: Amount
A22: Short ribs | B22: 879.45
A23: Jamon | B23: 457.14
A24: Haus select cheddar | B24: 267.28
A25: Caviar | B25: 480

Sheet Roister (12 - 18)
B1: CW | C1: Fortune | D1: Closed Loop | E1: A1 Firewood | F1: Wabash | G1: Superior | H1: Aya | I1: Rocker Bros | J1: D'artagnan | K1: Four Star | L1: Regalis | M1: Cornille | N1: Truffles | O1: Rare Tea Cellar | P1: Steve's | Q1: Turano | R1: Daily Spend | S1: Daily Revenue | T1: Daily Cost %
A2: 44928 | C2: 724.42 | J2: 879.45 | K2: 180 | L2: 480 | P2: 105.65 | R2: =SUM(B2:Q2) -> 2369.52 | S2: 0 | T2: =R2/S2 -> #DIV/0! | U2: =A2 -> 44928
A3: 44929 | B3: 2062.9 | C3: 436.81 | F3: 147.7 | H3: 33 | Q3: 208.59 | R3: =SUM(B3:Q3) -> 2889 | S3: 4065.8 | T3: =R3/S3 -> 0.71056127 | U3: =A3 -> 44929
A4: 44930 | B4: 2137.57 | C4: 189.54 | E4: 190 | G4: 255 | H4: 38 | O4: 25 | P4: 105.65 | R4: =SUM(B4:Q4) -> 2940.76 | S4: =1020+3068.4 -> 4088.4 | T4: =R4/S4 -> 0.71929361 | U4: =A4 -> 44930
A5: 44931 | B5: 1595.24 | C5: 119.1 | F5: 243.1 | R5: =SUM(B5:Q5) -> 1957.44 | S5: 6039.6 | T5: =R5/S5 -> 0.32410093 | U5: =A5 -> 44931
A6: 44932 | B6: 642.7 | G6: 170 | P6: 105.65 | R6: =SUM(B6:Q6) -> 918.35 | S6: 10449.2 | T6: =R6/S6 -> 0.087887111 | U6: =A6 -> 44932
A7: 44933 | B7: 340.81 | D7: 191 | E7: 190 | H7: 38 | M7: 406 | Q7: 57.55 | R7: =SUM(B7:Q7) -> 1223.36 | S7: 12483 | T7: =R7/S7 -> 0.098002083 | U7: =A7 -> 44933
A8: 44934 | B8: N/A | C8: N/A | D8: N/A | E8: N/A | G8: N/A | H8: N/A | I8: N/A | J8: N/A | K8: N/A | L8: N/A | M8: N/A | N8: N/A | O8: N/A | P8: N/A | Q8: N/A | R8: 0 | S8: 5660 | T8: =R8/S8 -> 0 | U8: =A8 -> 44934
A10: Actuals | B10: 7105.04 | C10: 1471.87 | D10: 191 | E10: 380 | F10: 441.31 | G10: 425 | H10: 190 | J10: 879.45 | K10: 195 | L10: 480 | O10: 25 | P10: 316.96 | Q10: 266.14
A11: Difference | B11: =sum(B2:B8)-B10 -> -325.82 | C11: =sum(C2:C8)-C10 -> -2 | D11: =sum(D2:D8)-D10 -> 0 | E11: =sum(E2:E8)-E10 -> 0 | F11: =sum(F2:F8)-F10 -> -50.51 | G11: =sum(G2:G8)-G10 -> 0 | H11: =sum(H2:H8)-H10 -> -81 | I11: =sum(I2:I8)-I10 -> 0 | ... L11: =sum(L2:L8)-L10 -> 0 | N11: =sum(N2:N8)-N10 -> 0 | O11: =sum(O2:O8)-O10 -> 0 | P11: =sum(P2:P8)-P10 -> -0.01 | Q11: =sum(Q2:Q8)-Q10 -> 0 | R11: =R10-0 -> 0
A13: Budget | B13: 11200
A14: Total Weekly Spend | B14: =SUM(B2:Q8) -> 12298.43
A15: Remaing Spend | B15: =SUM(B13-B14) -> -1098.43
A17: Weekly Food Revenue | B17: =SUM(S2:S8) -> 42786
A18: Weekly Cost % | B18: =B14/B17 -> 0.28744052
A21: End of week status
A22: list items over $100
A23: Items carrying over | B23: Amount | C23: Items discarded | D23: Amount
A24: mayo | B24: 102.01
A25: chicken thigh | B25: 231.2
A26: chicken breast | B26: 175.6
A27: ground pork | B27: 41.5
A28: 00 flour | B28: 99.11

Sheet Roister (19 - 115)
B1: CW | C1: Fortune | D1: Closed Loop | E1: A1 Firewood | F1: Wabash | G1: Superior | H1: Aya | I1: Rocker Bros | J1: D'artagnan | K1: Four Star | L1: Regalis | M1: Cornille | N1: Truffles | O1: Rare Tea Cellar | P1: Steve's | Q1: Turano | R1: Daily Spend | S1: Daily Revenue | T1: Daily Cost %
A2: 44935 | B2: 2269.34 | C2: 510.51 | F2: 193.8 | K2: 180 | P2: 105.65 | R2: =SUM(B2:Q2) -> 3259.3 | S2: 1663 | T2: =R2/S2 -> 1.9598918 | U2: =A2 -> 44935
A3: 44936 | B3: 930.18 | C3: 213.9 | F3: 109.13 | H3: 38 | Q3: 208.59 | R3: =SUM(B3:Q3) -> 1499.8 | S3: 4947.6 | T3: =R3/S3 -> 0.30313687 | U3: =A3 -> 44936
A4: 44937 | B4: 982.75 | C4: 260.73 | E4: 290 | G4: 170 | H4: 38 | O4: 39 | P4: 105.65 | R4: =SUM(B4:Q4) -> 1886.13 | S4: 6502 | T4: =R4/S4 -> 0.29008459 | U4: =A4 -> 44937
A5: 44938 | B5: 1203.4 | E5: 190 | F5: 259.3 | H5: 114 | R5: =SUM(B5:Q5) -> 1766.7 | S5: 6999 | T5: =R5/S5 -> 0.25242177 | U5: =A5 -> 44938
A6: 44939 | B6: 1535.24 | C6: 58 | F6: 196.54 | G6: 340 | H6: 38 | P6: 105.65 | R6: =SUM(B6:Q6) -> 2273.43 | S6: 9940 | T6: =R6/S6 -> 0.22871529 | U6: =A6 -> 44939
A7: 44940 | B7: 1457.7 | C7: 97.65 | D7: 100.5 | E7: 190 | M7: 400 | R7: =SUM(B7:Q7) -> 2245.85 | S7: 15048.39 | T7: =R7/S7 -> 0.14924188 | U7: =A7 -> 44940
A8: 44941 | B8: N/A | C8: N/A | D8: N/A | E8: N/A | G8: N/A | H8: N/A | I8: N/A | J8: N/A | K8: N/A | L8: N/A | M8: N/A | N8: N/A | O8: N/A | P8: N/A | Q8: N/A | R8: 0 | S8: 11205 | T8: =R8/S8 -> 0 | U8: =A8 -> 44941
A11: Budget | B11: 13000
A12: Total Weekly Spend | B12: =SUM(B2:Q8) -> 12931.21
A13: Remaing Spend | B13: =SUM(B11-B12) -> 68.79
A15: Weekly Food Revenue | B15: =SUM(S2:S8) -> 56304.99
A16: Weekly Cost % | B16: =B12/B15 -> 0.22966366
A19: End of week status | H19: Scallops
A20: list items over $100 | H20: Date delivered | I20: Weight billed (lbs) | J20: Weight received (lbs)
A21: Items carrying over | B21: Amount | C21: Items discarded | D21: Amount
I29: Total left at EOW

Sheet Roister (116 - 122)
B1: CW | C1: Fortune | D1: Closed Loop | E1: A1 Firewood | F1: Wabash | G1: Superior | H1: Aya | I1: Rocker Bros | J1: D'artagnan | K1: Four Star | L1: Regalis | M1: Cornille | N1: Truffles | O1: Rare Tea Cellar | P1: Steve's | Q1: Turano | R1: Daily Spend | S1: Daily Revenue | T1: Daily Cost %
A2: 44942 | B2: 2451.06 | C2: 364.59 | F2: 271.78 | J2: 822.28 | K2: 180 | O2: 39.95 | P2: 105.65 | R2: =SUM(B2:Q2) -> 4235.31 | S2: 3290.5 | T2: =R2/S2 -> 1.2871327 | U2: =A2 -> 44942
A3: 44943 | B3: 967.94 | G3: 170 | H3: 38 | Q3: 208.59 | R3: =SUM(B3:Q3) -> 1384.53 | S3: 3913 | T3: =R3/S3 -> 0.35382826 | U3: =A3 -> 44943
A4: 44944 | B4: 1371.49 | C4: 211.01 | E4: 390 | R4: =SUM(B4:Q4) -> 1972.5 | S4: =1013+5937 -> 6950 | T4: =R4/S4 -> 0.28381295 | U4: =A4 -> 44944
A5: 44945 | B5: 1647.76 | C5: 238.05 | F5: 461.67 | H5: 114 | R5: =SUM(B5:Q5) -> 2461.48 | S5: 13215.6 | T5: =R5/S5 -> 0.18625564 | U5: =A5 -> 44945
A6: 44946 | B6: 2042.8 | C6: 304.5 | H6: 38 | O6: 68 | P6: 105.65 | R6: =SUM(B6:Q6) -> 2558.95 | S6: 11791 | T6: =R6/S6 -> 0.2170257 | U6: =A6 -> 44946
A7: 44947 | B7: 1515.75 | C7: 214.05 | D7: 167 | F7: 214.38 | M7: 1187.2 | R7: =SUM(B7:Q7) -> 3298.38 | S7: =2322+13839.5 -> 16161.5 | T7: =R7/S7 -> 0.20408873 | U7: =A7 -> 44947
A8: 44948 | B8: N/A | C8: N/A | D8: N/A | E8: N/A | G8: N/A | H8: N/A | I8: N/A | J8: N/A | K8: N/A | L8: N/A | M8: N/A | N8: N/A | O8: N/A | P8: N/A | Q8: N/A | R8: 0 | S8: 6136.9 | T8: =R8/S8 -> 0 | U8: =A8 -> 44948
A10: Actuals | B10: 10183.99 | C10: 1380.94 | D10: 167 | E10: 390 | F10: =526.56+271.78 -> 798.34 | G10: 170 | H10: 190 | J10: 822.29 | K10: 375 | M10: 1187.2 | O10: 122.9 | P10: 158.48 | Q10: 208.59
A11: Difference | B11: =sum(B2:B8)-B10 -> -187.19 | C11: =sum(C2:C8)-C10 -> -48.74 | D11: =sum(D2:D8)-D10 -> 0 | E11: =sum(E2:E8)-E10 -> 0 | F11: =sum(F2:F8)-F10 -> 149.49 | G11: =sum(G2:G8)-G10 -> 0 | H11: =sum(H2:H8)-H10 -> 0 | I11: =sum(I2:I8)-I10 -> 0 | ... Q11: =sum(Q2:Q8)-Q10 -> 0 | R11: =R10-0 -> 0
A13: Budget | B13: 13000
A14: Total Weekly Spend | B14: =SUM(B2:Q8) -> 15911.15
A15: Remaing Spend | B15: =SUM(B13-B14) -> -2911.15
A17: Weekly Food Revenue | B17: =SUM(S2:S8) -> 61458.5
A18: Weekly Cost % | B18: =B14/B17 -> 0.25889259
A21: End of week status | H21: Scallops
A22: list items over $100 | H22: Date delivered | I22: Weight billed (lbs) | J22: Weight received (lbs)
A23: Items carrying over | B23: Amount | C23: Items discarded | D23: Amount
A24: Short ribs | B24: 822.28
I31: Total left at EOW

Sheet Roister (123-129)
B1: CW | C1: Fortune | D1: Closed Loop | E1: A1 Firewood | F1: Wabash | G1: Superior | H1: Aya | I1: Rocker Bros | J1: D'artagnan | K1: Four Star | L1: Regalis | M1: Cornille | N1: Truffles | O1: Rare Tea Cellar | P1: Steve's | Q1: Turano | R1: Daily Spend | S1: Daily Revenue | T1: Daily Cost %
A2: 44949 | B2: 1933.97 | C2: 719.57 | F2: 283.9 | J2: 822.28 | K2: 180 | P2: 105.65 | R2: =SUM(B2:Q2) -> 4045.37 | S2: 5087.6 | T2: =R2/S2 -> 0.79514309 | U2: =A2 -> 44949
A3: 44950 | B3: 1124.96 | C3: 137.15 | H3: 38 | J3: 762.64 | Q3: 208.59 | R3: =SUM(B3:Q3) -> 2271.34 | S3: 5667.8 | T3: =R3/S3 -> 0.40074456 | U3: =A3 -> 44950
A4: 44951 | B4: 1621.88 | C4: 443.14 | E4: 280 | F4: 664.55 | G4: 255 | H4: 33 | R4: =SUM(B4:Q4) -> 3297.57 | S4: 6034.6 | T4: =R4/S4 -> 0.54644384 | U4: =A4 -> 44951
A5: 44952 | B5: 1437.65 | C5: 156.53 | H5: 114 | R5: =SUM(B5:Q5) -> 1708.18 | S5: 7042.6 | T5: =R5/S5 -> 0.24254963 | U5: =A5 -> 44952
A6: 44953 | B6: 520.65 | C6: 211 | G6: 284.9 | H6: 38 | P6: 105.65 | R6: =SUM(B6:Q6) -> 1160.2 | S6: 12211 | T6: =R6/S6 -> 0.095012693 | U6: =A6 -> 44953
A7: 44954 | B7: 2029.88 | D7: 200 | M7: 400 | R7: =SUM(B7:Q7) -> 2629.88 | S7: 14070 | T7: =R7/S7 -> 0.186914 | U7: =A7 -> 44954
A8: 44955 | B8: N/A | C8: N/A | D8: N/A | E8: N/A | G8: N/A | H8: N/A | I8: N/A | J8: N/A | K8: N/A | L8: N/A | M8: N/A | N8: N/A | O8: N/A | P8: N/A | Q8: N/A | R8: 0 | S8: 6634.7 | T8: =R8/S8 -> 0 | U8: =A8 -> 44955
A11: Budget | B11: 13000
A12: Total Weekly Spend | B12: =SUM(B2:Q8) -> 15112.54
A13: Remaing Spend | B13: =SUM(B11-B12) -> -2112.54
A15: Weekly Food Revenue | B15: =SUM(S2:S8) -> 56748.3
A16: Weekly Cost % | B16: =B12/B15 -> 0.26630824
A19: End of week status
A20: list items over $100
A21: Items carrying over | B21: Amount | C21: Items discarded | D21: Amount
A22: Jamon | B22: 350.67
A23: Short Ribs | B23: 953.31
A24: Bacon | B24: 112.49
A25: ICB Stabilizer | B25: 114.4
A26: mayo | B26: 102.01
A27: Chicken Thigh | B27: 119.6

Sheet Roister (130 - 25)
B1: CW | C1: Fortune | D1: Closed Loop | E1: A1 Firewood | F1: Wabash | G1: Superior | H1: Aya | I1: Rocker Bros | J1: D'artagnan | K1: Four Star | L1: Regalis | M1: Cornille | N1: Truffles | O1: Rare Tea Cellar | P1: Steve's | Q1: Turano | R1: Daily Spend | S1: Daily Revenue | T1: Daily Cost %
A2: 44956 | B2: 1991.59 | C2: 782.92 | F2: 317.54 | J2: 1143.97 | K2: 180 | O2: 139.5 | P2: 105.65 | R2: =SUM(B2:Q2) -> 4661.17 | S2: 4200 | T2: =R2/S2 -> 1.1098024 | U2: =A2 -> 44956
A3: 44957 | B3: 1139.94 | C3: 112.35 | E3: 280 | F3: 110.17 | H3: 38 | J3: 995.19 | Q3: 208.59 | R3: =SUM(B3:Q3) -> 2884.24 | S3: 8985.75 | T3: =R3/S3 -> 0.32097933 | U3: =A3 -> 44957
A4: 44958 | B4: 1782.19 | C4: 66.22 | E4: 180 | G4: 340 | H4: 38 | R4: =SUM(B4:Q4) -> 2406.41 | S4: 3982 | T4: =R4/S4 -> 0.60432195 | U4: =A4 -> 44958
A5: 44959 | B5: 1240.42 | C5: 164.6 | R5: =SUM(B5:Q5) -> 1405.02 | S5: 6103 | T5: =R5/S5 -> 0.23021793 | U5: =A5 -> 44959
A6: 44960 | B6: 1566.01 | F6: 247.07 | G6: 170 | H6: 38 | P6: 105.65 | R6: =SUM(B6:Q6) -> 2126.73 | S6: 9375 | T6: =R6/S6 -> 0.2268512 | U6: =A6 -> 44960
A7: 44961 | B7: 1099.39 | D7: 200 | F7: 263.04 | H7: 33 | M7: 400 | R7: =SUM(B7:Q7) -> 1995.43 | S7: 15844.5 | T7: =R7/S7 -> 0.12593834 | U7: =A7 -> 44961
A8: 44962 | B8: N/A | C8: N/A | D8: N/A | E8: N/A | G8: N/A | H8: N/A | I8: N/A | J8: N/A | K8: N/A | L8: N/A | M8: N/A | N8: N/A | O8: N/A | P8: N/A | Q8: N/A | R8: 0 | S8: 10229.4 | T8: =R8/S8 -> 0 | U8: =A8 -> 44962
A11: Budget | B11: 13000
A12: Total Weekly Spend | B12: =SUM(B2:Q8) -> 15479
A13: Remaing Spend | B13: =SUM(B11-B12) -> -2479
A15: Weekly Food Revenue | B15: =SUM(S2:S8) -> 58719.65
A16: Weekly Cost % | B16: =B12/B15 -> 0.26360852
A19: End of week status | H19: Scallops
A20: list items over $100 | H20: Date delivered | I20: Weight billed (lbs) | J20: Weight received (lbs)
A21: Items carrying over | B21: Amount | C21: Items discarded | D21: Amount
A22: Short ribs | B22: 995.19
I29: Total left at EOW

Sheet Roister (26 - 212)
B1: CW | C1: Fortune | D1: Closed Loop | E1: A1 Firewood | F1: Wabash | G1: Superior | H1: Aya | I1: Rocker Bros | J1: D'artagnan | K1: Four Star | L1: Booze | M1: Cornille | N1: D'amatos | O1: Rare Tea Cellar | P1: Steve's | Q1: Turano | R1: Daily Spend | S1: Daily Revenue | T1: Daily Cost %
A2: 44963 | B2: 1959.53 | C2: 225.94 | F2: 370.72 | G2: 454.9 | J2: 995.19 | K2: 180 | P2: 105.65 | R2: =SUM(B2:Q2) -> 4291.93 | S2: 4397 | T2: =R2/S2 -> 0.97610416 | U2: =A2 -> 44963
A3: 44964 | B3: 1636.22 | C3: 312.95 | H3: 38 | J3: 199.76 | Q3: 219.08 | R3: =SUM(B3:Q3) -> 2406.01 | S3: 4109 | T3: =R3/S3 -> 0.58554636 | U3: =A3 -> 44964
A4: 44965 | B4: 1030.56 | E4: 280 | L4: 21.47 | N4: 21.6 | R4: =SUM(B4:Q4) -> 1353.63 | S4: 4658 | T4: =R4/S4 -> 0.29060326 | U4: =A4 -> 44965
A5: 44966 | B5: 579.26 | C5: 125.45 | F5: 266.57 | G5: 255 | H5: 91.2 | O5: 59.45 | R5: =SUM(B5:Q5) -> 1376.93 | S5: 6201 | T5: =R5/S5 -> 0.22204967 | U5: =A5 -> 44966
A6: 44967 | B6: 1399.46 | R6: =SUM(B6:Q6) -> 1399.46 | S6: 11816 | T6: =R6/S6 -> 0.11843771 | U6: =A6 -> 44967
A7: 44968 | B7: 2017.41 | C7: 442 | D7: 200 | E7: 180 | F7: 467.48 | H7: 10.2 | M7: 324.5 | R7: =SUM(B7:Q7) -> 3641.59 | S7: 16212 | T7: =R7/S7 -> 0.22462312 | U7: =A7 -> 44968
A8: 44969 | B8: N/A | C8: N/A | D8: N/A | E8: N/A | G8: N/A | H8: N/A | I8: N/A | J8: N/A | K8: N/A | L8: N/A | M8: N/A | N8: N/A | O8: N/A | P8: N/A | Q8: N/A | R8: 0 | S8: 4458.6 | T8: =R8/S8 -> 0 | U8: =A8 -> 44969
A11: Budget | B11: 13000
A12: Total Weekly Spend | B12: =SUM(B2:Q8) -> 14469.55
A13: Remaing Spend | B13: =SUM(B11-B12) -> -1469.55
A15: Weekly Food Revenue | B15: =SUM(S2:S8) -> 51851.6
A16: Weekly Cost % | B16: =B12/B15 -> 0.27905696
A19: End of week status
A20: list items over $100
A21: Items carrying over | B21: Amount | C21: Items discarded | D21: Amount
A22: Short Ribs | B22: 1005.89
A23: V-day Ducks | B23: 1381.38
A24: Potato Pellets | B24: 117.78
A25: Jamon | B25: 486.72
A26: Chicken | B26: 281

Sheet Roister (213 - 219)
B1: CW | C1: Fortune | D1: Closed Loop | E1: A1 Firewood | F1: Wabash | G1: Superior | H1: Aya | I1: Rocker Bros | J1: D'artagnan | K1: Four Star | L1: Regalis | M1: D'amatos | N1: Cornille | O1: Truffles | P1: Rare Tea Cellar | Q1: Steve's | R1: Turano | S1: Daily Spend | T1: Daily Revenue | U1: Daily Cost %
A2: 44970 | B2: 2931.32 | C2: 281 | G2: 759.9 | J2: 1036.11 | K2: 180 | Q2: 105.65 | S2: =SUM(B2:R2) -> 5293.98 | T2: 7067 | U2: =S2/T2 -> 0.74911278 | V2: =A2 -> 44970
A3: 44971 | B3: 1737.53 | C3: 677.82 | F3: 349.39 | O3: 424 | R3: 219.08 | S3: =SUM(B3:R3) -> 3407.82 | T3: 18077.47 | U3: =S3/T3 -> 0.188512 | V3: =A3 -> 44971
A4: 44972 | B4: 1338.85 | E4: 280 | F4: 95 | H4: 38 | M4: 21.6 | S4: =SUM(B4:R4) -> 1773.45 | T4: 8616.4 | U4: =S4/T4 -> 0.20582262 | V4: =A4 -> 44972
A5: 44973 | B5: 1263.64 | C5: 132.05 | F5: 140.08 | J5: 413.31 | S5: =SUM(B5:R5) -> 1949.08 | T5: 7706.47 | U5: =S5/T5 -> 0.25291476 | V5: =A5 -> 44973
A6: 44974 | B6: 1097.03 | H6: 114 | M6: 21.6 | Q6: 105.65 | S6: =SUM(B6:R6) -> 1338.28 | T6: 12478 | U6: =S6/T6 -> 0.10725116 | V6: =A6 -> 44974
A7: 44975 | B7: 2361.77 | C7: 219.34 | D7: 200 | F7: 190 | H7: 33 | N7: 129.5 | R7: 36.27 | S7: =SUM(B7:R7) -> 3169.88 | T7: 15467.1 | U7: =S7/T7 -> 0.2049434 | V7: =A7 -> 44975
A8: 44976 | B8: N/A | C8: N/A | D8: N/A | E8: N/A | G8: N/A | H8: N/A | I8: N/A | J8: N/A | K8: N/A | L8: N/A | N8: N/A | O8: N/A | P8: N/A | Q8: N/A | R8: N/A | S8: 0 | T8: 9645.8 | U8: =S8/T8 -> 0 | V8: =A8 -> 44976
A11: Budget | B11: 13000
A12: Total Weekly Spend | B12: =SUM(B2:R8) -> 16932.49
A13: Remaing Spend | B13: =SUM(B11-B12) -> -3932.49
A15: Weekly Food Revenue | B15: =SUM(T2:T8) -> 79058.24
A16: Weekly Cost % | B16: =B12/B15 -> 0.21417742
A19: End of week status
A20: list items over $100
A21: Items carrying over | B21: Amount | C21: Items discarded | D21: Amount
A22: 1/2cs short ribs | B22: 345.25

Sheet Roister (220 - 226)
B1: CW | C1: Fortune | D1: Closed Loop | E1: A1 Firewood | F1: Wabash | G1: Superior | H1: Aya | I1: Rocker Bros | J1: D'artagnan | K1: Four Star | L1: Regalis | M1: D'amatos | N1: Cornille | O1: Truffles | P1: Rare Tea Cellar | Q1: Steve's | R1: Turano | S1: Daily Spend | T1: Daily Revenue | U1: Daily Cost %
A2: 44977 | B2: 1991.71 | C2: 724.7 | F2: 265.52 | J2: 345.25 | K2: 180 | Q2: 105.65 | S2: =SUM(B2:R2) -> 3612.83 | T2: 2400.8 | U2: =S2/T2 -> 1.5048442 | V2: =A2 -> 44977
A3: 44978 | B3: 867.16 | C3: 274.1 | J3: 923.06 | R3: 179.96 | S3: =SUM(B3:R3) -> 2244.28 | T3: 5443 | U3: =S3/T3 -> 0.41232409 | V3: =A3 -> 44978
A4: 44979 | B4: 1552.82 | C4: 589.75 | E4: 480 | F4: 581.08 | H4: 38 | M4: 21.6 | P4: 39 | S4: =SUM(B4:R4) -> 3302.25 | T4: 6826 | U4: =S4/T4 -> 0.48377527 | V4: =A4 -> 44979
A5: 44980 | B5: 1450 | C5: 175.63 | H5: 114 | M5: 21.6 | P5: 19 | S5: =SUM(B5:R5) -> 1780.23 | T5: 7563.2 | U5: =S5/T5 -> 0.23538053 | V5: =A5 -> 44980
A6: 44981 | B6: 1381.36 | C6: 58 | G6: 474.9 | H6: 38 | M6: 21.6 | Q6: 105.65 | S6: =SUM(B6:R6) -> 2079.51 | T6: 11291.8 | U6: =S6/T6 -> 0.18416107 | V6: =A6 -> 44981
A7: 44982 | B7: 1414.91 | C7: 161 | D7: 200 | F7: 152.35 | N7: 85 | S7: =SUM(B7:R7) -> 2013.26 | T7: 16064 | U7: =S7/T7 -> 0.12532744 | V7: =A7 -> 44982
A8: 44983 | B8: N/A | C8: N/A | D8: N/A | E8: N/A | G8: N/A | H8: N/A | I8: N/A | J8: N/A | K8: N/A | L8: N/A | N8: N/A | O8: N/A | P8: N/A | Q8: N/A | R8: N/A | S8: 0 | T8: 8296.6 | U8: =S8/T8 -> 0 | V8: =A8 -> 44983
A11: Budget | B11: 13000
A12: Total Weekly Spend | B12: =SUM(B2:R8) -> 15032.36
A13: Remaing Spend | B13: =SUM(B11-B12) -> -2032.36
A15: Weekly Food Revenue | B15: =SUM(T2:T8) -> 57885.4
A16: Weekly Cost % | B16: =B12/B15 -> 0.25969174
A19: End of week status
A20: list items over $100
A21: Items carrying over | B21: Amount | C21: Items discarded | D21: Amount
A22: Short Ribs | B22: 923.06
A23: Fortune | B23: 484.18

Sheet Roister (227 - 35)
B1: CW | C1: Fortune | D1: Closed Loop | E1: A1 Firewood | F1: Wabash | G1: Superior | H1: Aya | I1: Rocker Bros | J1: D'artagnan | K1: Four Star | L1: Regalis | M1: D'amatos | N1: Cornille | O1: Truffles | P1: Rare Tea Cellar | Q1: Steve's | R1: Turano | S1: Daily Spend | T1: Daily Revenue | U1: Daily Cost %
A2: 44984 | B2: 2240.67 | C2: 554.72 | F2: 445.17 | J2: 923.06 | K2: 180 | Q2: 105.65 | S2: =SUM(B2:R2) -> 4449.27 | T2: 9503 | U2: =S2/T2 -> 0.46819636 | V2: =A2 -> 44984
A3: 44985 | B3: 1479.19 | C3: 277.45 | F3: 350.9 | H3: 33 | J3: 827.41 | R3: 179.96 | S3: =SUM(B3:R3) -> 3147.91 | T3: 5464 | U3: =S3/T3 -> 0.57611823 | V3: =A3 -> 44985
A4: 44986 | B4: 475.86 | C4: 52.2 | E4: 280 | G4: 284.9 | M4: 21.6 | S4: =SUM(B4:R4) -> 1114.56 | T4: 4234 | U4: =S4/T4 -> 0.26324043 | V4: =A4 -> 44986
A5: 44987 | B5: 699.98 | H5: 114 | M5: 21.6 | S5: =SUM(B5:R5) -> 835.58 | T5: 6429.8 | U5: =S5/T5 -> 0.12995428 | V5: =A5 -> 44987
A6: 44988 | B6: 1920.22 | F6: 265.61 | G6: 664.9 | M6: 21.6 | P6: 63.5 | Q6: 105.65 | S6: =SUM(B6:R6) -> 3041.48 | T6: 9601.5 | U6: =S6/T6 -> 0.31677134 | V6: =A6 -> 44988
A7: 44989 | B7: 1177.91 | C7: 131.78 | D7: 200 | E7: 280 | H7: 33 | N7: 200 | R7: 49.17 | S7: =SUM(B7:R7) -> 2071.86 | T7: 13943 | U7: =S7/T7 -> 0.14859499 | V7: =A7 -> 44989
A8: 44990 | B8: N/A | C8: N/A | D8: N/A | E8: N/A | G8: N/A | H8: N/A | I8: N/A | J8: N/A | K8: N/A | L8: N/A | N8: N/A | O8: N/A | P8: N/A | Q8: N/A | R8: N/A | S8: 0 | U8: =S8/T8 -> #DIV/0! | V8: =A8 -> 44990
A11: Budget | B11: 13000
A12: Total Weekly Spend | B12: =SUM(B2:R8) -> 14660.66
A13: Remaing Spend | B13: =SUM(B11-B12) -> -1660.66
A15: Weekly Food Revenue | B15: =SUM(T2:T8) -> 49175.3
A16: Weekly Cost % | B16: =B12/B15 -> 0.29813057
A19: End of week status
A20: list items over $100
A21: Items carrying over | B21: Amount | C21: Items discarded | D21: Amount
A22: Short Ribs | B22: 827.41
A23: Cream Cheese | B23: 108.54

Sheet Roister (36 - 312)
B1: CW | C1: Fortune | D1: Closed Loop | E1: A1 Firewood | F1: Wabash | G1: Superior | H1: Aya | I1: Rocker Bros | J1: D'artagnan | K1: Four Star | L1: Regalis | M1: D'amatos | N1: Cornille | O1: Truffles | P1: Rare Tea Cellar | Q1: Steve's | R1: Turano | S1: Daily Spend | T1: Daily Revenue | U1: Daily Cost %
A2: 44991 | B2: 2053.51 | C2: 161.94 | J2: 827.41 | K2: 180 | Q2: 105.65 | S2: =SUM(B2:R2) -> 3328.51 | T2: 3954.4 | U2: =S2/T2 -> 0.84172314 | V2: =A2 -> 44991
A3: 44992 | B3: 904.49 | C3: 263.17 | F3: 314.08 | H3: 33 | R3: 179.96 | S3: =SUM(B3:R3) -> 1694.7 | T3: 0 | U3: =S3/T3 -> #DIV/0! | V3: =A3 -> 44992
A4: 44993 | B4: 876.49 | C4: 117.7 | E4: 280 | M4: 21.6 | P4: 49 | S4: =SUM(B4:R4) -> 1344.79 | T4: 0 | U4: =S4/T4 -> #DIV/0! | V4: =A4 -> 44993
A5: 44994 | B5: 125.68 | S5: =SUM(B5:R5) -> 125.68 | T5: 2719 | U5: =S5/T5 -> 0.046222876 | V5: =A5 -> 44994
A6: 44995 | B6: 1164.33 | C6: 382.3 | F6: 192.39 | G6: 474.9 | H6: 114 | M6: 21.6 | Q6: 105.65 | S6: =SUM(B6:R6) -> 2455.17 | T6: 8972 | U6: =S6/T6 -> 0.27364802 | V6: =A6 -> 44995
A7: 44996 | B7: 1488.04 | C7: 330.6 | D7: 200 | E7: 180 | H7: 33 | N7: 200 | R7: 24.18 | S7: =SUM(B7:R7) -> 2455.82 | T7: 13707 | U7: =S7/T7 -> 0.17916539 | V7: =A7 -> 44996
A8: 44997 | B8: N/A | C8: N/A | D8: N/A | E8: N/A | G8: N/A | H8: N/A | I8: N/A | J8: N/A | K8: N/A | L8: N/A | N8: N/A | O8: N/A | P8: N/A | Q8: N/A | R8: N/A | S8: 0 | T8: 6485 | U8: =S8/T8 -> 0 | V8: =A8 -> 44997
A11: Budget | B11: 13000
A12: Total Weekly Spend | B12: =SUM(B2:R8) -> 11404.67
A13: Remaing Spend | B13: =SUM(B11-B12) -> 1595.33
A15: Weekly Food Revenue | B15: =SUM(T2:T8) -> 35837.4
A16: Weekly Cost % | B16: =B12/B15 -> 0.31823374
A19: End of week status
A20: list items over $100
A21: Items carrying over | B21: Amount | C21: Items discarded | D21: Amount
A22: Mixed Olives | B22: 100.82
A23: Cream Cheese | B23: 108.54
A24: Ducks | B24: 399.97

Sheet Roister (313 - 319)
B1: CW | C1: Fortune | D1: Closed Loop | E1: A1 Firewood | F1: Wabash/Allen | G1: Superior | H1: Aya | I1: Rocker Bros | J1: D'artagnan | K1: Four Star | L1: Regalis | M1: D'amatos | N1: Cornille | O1: Truffles | P1: Rare Tea Cellar | Q1: Steve's | R1: Turano | S1: Daily Spend | T1: Daily Revenue | U1: Daily Cost %
A2: 44998 | B2: 1791.96 | C2: 466.99 | J2: 827.41 | K2: 180 | Q2: 105.65 | S2: =SUM(B2:R2) -> 3372.01 | T2: 4227 | U2: =S2/T2 -> 0.79773125 | V2: =A2 -> 44998
A3: 44999 | B3: 1149.58 | C3: 517.24 | F3: 129.25 | R3: 179.96 | S3: =SUM(B3:R3) -> 1976.03 | T3: 4285.63 | U3: =S3/T3 -> 0.46108273 | V3: =A3 -> 44999
A4: 45000 | B4: 1258.63 | C4: 157.26 | E4: 190 | F4: 196.68 | G4: 95 | H4: 39 | M4: 18.5 | S4: =SUM(B4:R4) -> 1955.07 | T4: 9699.69 | U4: =S4/T4 -> 0.20156005 | V4: =A4 -> 45000
A5: 45001 | B5: 1262.8 | C5: 260.71 | F5: 868.11 | K5: 375 | M5: 18.5 | S5: =SUM(B5:R5) -> 2785.12 | T5: 5179.2 | U5: =S5/T5 -> 0.537751 | V5: =A5 -> 45001
A6: 45002 | B6: 1302.15 | C6: 29.45 | G6: 285 | H6: 114 | M6: 18.5 | P6: 129 | Q6: 105.65 | S6: =SUM(B6:R6) -> 1983.75 | T6: 10543.78 | U6: =S6/T6 -> 0.1881441 | V6: =A6 -> 45002
A7: 45003 | B7: 1183.09 | D7: 200 | H7: 39 | N7: 100 | S7: =SUM(B7:R7) -> 1522.09 | T7: 17562.98 | U7: =S7/T7 -> 0.086664678 | V7: =A7 -> 45003
A8: 45004 | B8: N/A | C8: N/A | D8: N/A | E8: N/A | G8: N/A | H8: N/A | I8: N/A | J8: N/A | K8: N/A | L8: N/A | N8: N/A | O8: N/A | P8: N/A | Q8: N/A | R8: N/A | S8: 0 | T8: 10633.22 | U8: =S8/T8 -> 0 | V8: =A8 -> 45004
A11: Budget | B11: 13000
A12: Total Weekly Spend | B12: =SUM(B2:R8) -> 13594.07
A13: Remaing Spend | B13: =SUM(B11-B12) -> -594.07
A15: Weekly Food Revenue | B15: =SUM(T2:T8) -> 62131.5
A16: Weekly Cost % | B16: =B12/B15 -> 0.21879514
A19: End of week status
A20: list items over $100
A21: Items carrying over | B21: Amount | C21: Items discarded | D21: Amount
A22: Ducks | B22: 620.54
A23: Short Ribs | B23: 513.7
A24: Lump Crab | B24: 138
A25: Pork Belly | B25: 253.69

Sheet Roister (320 - 326)
B1: CW | C1: Fortune | D1: Closed Loop | E1: A1 Firewood | F1: Wabash/Allen | G1: Superior | H1: Aya | I1: Rocker Bros | J1: D'artagnan | K1: Four Star | L1: Regalis | M1: D'amatos | N1: Cornille | O1: Truffles | P1: Rare Tea Cellar | Q1: Steve's | R1: Turano | S1: Daily Spend | T1: Daily Revenue | U1: Daily Cost %
A2: 45005 | B2: 2696.61 | C2: 807.79 | F2: 624.91 | J2: 620.54 | K2: 385 | Q2: 105.65 | S2: =SUM(B2:R2) -> 5240.5 | T2: 3520.4 | U2: =S2/T2 -> 1.4886092 | V2: =A2 -> 45005
A3: 45006 | B3: 1049.47 | C3: 256.49 | F3: 339.35 | R3: 179.96 | S3: =SUM(B3:R3) -> 1825.27 | T3: 8341.77 | U3: =S3/T3 -> 0.21881088 | V3: =A3 -> 45006
A4: 45007 | B4: 1154.15 | C4: 113.4 | F4: 219.18 | G4: 142.5 | M4: 18.5 | S4: =SUM(B4:R4) -> 1647.73 | T4: 5673.88 | U4: =S4/T4 -> 0.29040621 | V4: =A4 -> 45007
A5: 45008 | B5: 722.03 | C5: 243.06 | M5: 18.5 | S5: =SUM(B5:R5) -> 983.59 | T5: 6073.88 | U5: =S5/T5 -> 0.16193767 | V5: =A5 -> 45008
A6: 45009 | B6: 1820.46 | C6: 117.3 | F6: 289.42 | G6: 285 | H6: 123 | M6: 18.5 | Q6: 105.65 | S6: =SUM(B6:R6) -> 2759.33 | T6: 9213 | U6: =S6/T6 -> 0.29950396 | V6: =A6 -> 45009
A7: 45010 | B7: 1362.9 | C7: 346 | D7: 200 | F7: 167.3 | N7: 200 | P7: 19.5 | R7: 24.18 | S7: =SUM(B7:R7) -> 2319.88 | T7: 14288.82 | U7: =S7/T7 -> 0.1623563 | V7: =A7 -> 45010
A8: 45011 | B8: N/A | C8: N/A | D8: N/A | E8: N/A | G8: N/A | H8: N/A | I8: N/A | J8: N/A | K8: N/A | L8: N/A | N8: N/A | O8: N/A | P8: N/A | Q8: N/A | R8: N/A | S8: 0 | T8: 9031.95 | U8: =S8/T8 -> 0 | V8: =A8 -> 45011
A11: Budget | B11: 13000
A12: Total Weekly Spend | B12: =SUM(B2:R8) -> 14776.3
A13: Remaing Spend | B13: =SUM(B11-B12) -> -1776.3
A15: Weekly Food Revenue | B15: =SUM(T2:T8) -> 56143.7
A16: Weekly Cost % | B16: =B12/B15 -> 0.26318714
A19: End of week status
A20: list items over $100
A21: Items carrying over | B21: Amount | C21: Items discarded | D21: Amount
A22: Ducks (3/27) | B22: 1165.98
A23: Ducks (4/3) | B23: 1133.55
A24: Jamon | B24: 496.56
A25: lump crab | B25: 103.5

Sheet Roister (327 - 42)
B1: CW | C1: Fortune | D1: Closed Loop | E1: A1 Firewood | F1: Wabash/Allen | G1: Superior | H1: Aya | I1: D'artagnan | J1: Four Star | K1: Regalis | L1: D'amatos | M1: Cornille | N1: Rare Tea Cellar | O1: Steve's | P1: Turano | Q1: Daily Spend | R1: Daily Revenue | S1: Daily Cost %
A2: 45012 | B2: 3149.31 | C2: 331.46 | I2: 1165.98 | J2: 385 | O2: 105.65 | Q2: =SUM(B2:P2) -> 5137.4 | R2: 4840.9 | S2: =Q2/R2 -> 1.0612489 | T2: =A2 -> 45012
A3: 45013 | B3: 391.84 | F3: 104.44 | P3: 179.96 | Q3: =SUM(B3:P3) -> 676.24 | R3: 7064.86 | S3: =Q3/R3 -> 0.095718811 | T3: =A3 -> 45013
A4: 45014 | B4: 968.32 | C4: 498.59 | G4: 270 | L4: 18.5 | Q4: =SUM(B4:P4) -> 1755.41 | R4: 4474.65 | S4: =Q4/R4 -> 0.39230107 | T4: =A4 -> 45014
A5: 45015 | B5: 974.2 | C5: 551.65 | F5: 398.89 | L5: 18.5 | Q5: =SUM(B5:P5) -> 1943.24 | R5: 6931 | S5: =Q5/R5 -> 0.28036936 | T5: =A5 -> 45015
A6: 45016 | B6: 963.18 | C6: 166.5 | H6: 123 | L6: 18.5 | O6: 105.65 | Q6: =SUM(B6:P6) -> 1376.83 | R6: 10944.2 | S6: =Q6/R6 -> 0.12580454 | T6: =A6 -> 45016
A7: 45017 | B7: 1638.35 | C7: 552.5 | D7: 200 | F7: 163.27 | M7: 100 | P7: 37.08 | Q7: =SUM(B7:P7) -> 2691.2 | R7: 14841.08 | S7: =Q7/R7 -> 0.18133451 | T7: =A7 -> 45017
A8: 45018 | B8: N/A | C8: N/A | D8: N/A | E8: N/A | G8: N/A | H8: N/A | I8: N/A | J8: N/A | K8: N/A | M8: N/A | N8: N/A | O8: N/A | P8: N/A | Q8: 0 | R8: 6608.69 | S8: =Q8/R8 -> 0 | T8: =A8 -> 45018
A11: Budget | B11: 13000
A12: Total Weekly Spend | B12: =SUM(B2:P8) -> 13580.32
A13: Remaing Spend | B13: =SUM(B11-B12) -> -580.32
A15: Weekly Food Revenue | B15: =SUM(R2:R8) -> 55705.38
A16: Weekly Cost % | B16: =B12/B15 -> 0.2437883
A19: End of week status
A20: list items over $100
A21: Items carrying over | B21: Amount | C21: Items discarded | D21: Amount
A22: Ducks (4/10) | B22: 1214.86
A23: Short Ribs | B23: 598.32
A24: Ducks (4/17) | B24: 1563.2

Sheet Roister (43 - 49)
B1: CW | C1: Fortune | D1: Closed Loop | E1: A1 Firewood | F1: Wabash/Allen | G1: Superior | H1: Aya | I1: Rocker Bros | J1: D'artagnan | K1: Four Star | L1: Regalis | M1: D'amatos | N1: Cornille | O1: Truffles | P1: Rare Tea Cellar | Q1: Steve's | R1: Turano | S1: Daily Spend | T1: Daily Revenue | U1: Daily Cost %
A2: 45019 | B2: 2798.99 | C2: 947.86 | F2: 819.44 | J2: 1133.55 | K2: 445 | P2: 34.45 | Q2: 105.65 | S2: =SUM(B2:R2) -> 6284.94 | T2: 3612 | U2: =S2/T2 -> 1.7400166
A3: 45020 | B3: 320.98 | F3: 163.18 | I3: 322.8 | R3: 179.96 | S3: =SUM(B3:R3) -> 986.92 | T3: 10018.41 | U3: =S3/T3 -> 0.098510642
A4: 45021 | B4: 2030.44 | C4: 173.68 | F4: 205.09 | G4: 95 | M4: 18.5 | S4: =SUM(B4:R4) -> 2522.71 | T4: 8916.29 | U4: =S4/T4 -> 0.2829327
A5: 45022 | B5: 2097.89 | C5: 240.63 | M5: 18.5 | S5: =SUM(B5:R5) -> 2357.02 | T5: 6758.5 | U5: =S5/T5 -> 0.34874898
A6: 45023 | B6: 1621.73 | C6: 300.08 | E6: 180 | G6: 569.9 | H6: 328 | M6: 18.5 | Q6: 105.65 | S6: =SUM(B6:R6) -> 3123.86 | T6: 10444 | U6: =S6/T6 -> 0.29910571
A7: 45024 | B7: 2341.16 | D7: 200 | F7: 221.72 | N7: 200 | P7: 39 | R7: 73.35 | S7: =SUM(B7:R7) -> 3075.23 | T7: 12435.62 | U7: =S7/T7 -> 0.24729205
A8: 45025 | B8: N/A | C8: N/A | D8: N/A | E8: N/A | G8: N/A | H8: N/A | I8: N/A | J8: N/A | K8: N/A | L8: N/A | N8: N/A | O8: N/A | P8: N/A | Q8: N/A | R8: N/A | S8: 0 | T8: 17886.89 | U8: =S8/T8 -> 0
A11: Budget | B11: 13000
A12: Total Weekly Spend | B12: =SUM(B2:R8) -> 18350.68
A13: Remaing Spend | B13: =SUM(B11-B12) -> -5350.68
A15: Weekly Food Revenue | B15: =SUM(T2:T8) -> 70071.71
A16: Weekly Cost % | B16: =B12/B15 -> 0.26188429
A19: End of week status
A20: list items over $100
A21: Items carrying over | B21: Amount | C21: Items discarded | D21: Amount
A22: Jamon | B22: 463.24
A23: Salmon | B23: 138.26
A24: Ducks | B24: 1280.64

Sheet Roister (410-416)
B1: CW | C1: Fortune | D1: Closed Loop | E1: A1 Firewood | F1: Wabash/Allen | G1: Superior | H1: Aya | I1: Rocker Bros | J1: D'artagnan | K1: Four Star | L1: Regalis | M1: D'amatos | N1: Cornille | O1: Truffles | P1: Rare Tea Cellar | Q1: Steve's | R1: Turano | S1: Daily Spend | T1: Daily Revenue | U1: Daily Cost %
A2: 45026 | B2: 2376.41 | C2: 1980.51 | F2: 247.07 | J2: 1214.86 | K2: 325 | P2: 30 | Q2: 105.65 | S2: =SUM(B2:R2) -> 6279.5 | T2: 5480.2 | U2: =S2/T2 -> 1.1458523
A3: 45027 | B3: 443.73 | C3: 59.25 | F3: 144.6 | R3: 179.96 | S3: =SUM(B3:R3) -> 827.54 | T3: 4740 | U3: =S3/T3 -> 0.1745865
A4: 45028 | B4: 685.88 | G4: 140 | M4: 18.5 | P4: 38.5 | S4: =SUM(B4:R4) -> 882.88 | T4: 5528.43 | U4: =S4/T4 -> 0.15969814
A5: 45029 | B5: 1418.5 | C5: 380.28 | E5: 180 | F5: 733.32 | H5: 123 | M5: 18.5 | S5: =SUM(B5:R5) -> 2853.6 | T5: 7394.3 | U5: =S5/T5 -> 0.38591888
A6: 45030 | B6: 1074.66 | C6: 208.2 | G6: 380 | M6: 18.5 | Q6: 105.65 | S6: =SUM(B6:R6) -> 1787.01 | T6: 11354 | U6: =S6/T6 -> 0.15739035
A7: 45031 | B7: 1777.21 | C7: 212.8 | D7: 200 | F7: 322.82 | N7: 200 | S7: =SUM(B7:R7) -> 2712.83 | T7: 16435.05 | U7: =S7/T7 -> 0.16506369
A8: 45032 | B8: N/A | C8: N/A | D8: N/A | E8: N/A | G8: N/A | H8: N/A | I8: N/A | J8: N/A | K8: N/A | L8: N/A | N8: N/A | O8: N/A | P8: N/A | Q8: N/A | R8: N/A | S8: 0 | U8: =S8/T8 -> #DIV/0!
A11: Budget | B11: 13000
A12: Total Weekly Spend | B12: =SUM(B2:R8) -> 15343.36
A13: Remaing Spend | B13: =SUM(B11-B12) -> -2343.36
H14: Clam Prices
A15: Weekly Food Revenue | B15: =SUM(T2:T8) -> 50931.98 | H15: Fortune | I15: Bill | J15: Fortune
A16: Weekly Cost % | B16: =B12/B15 -> 0.30125198 | H16: $7.99/12pc | I16: $45/50pc | J16: $17.50/50pc
H17: Cherrystone | I17: White Water | J17: Littleneck
A19: End of week status
A20: list items over $100
A21: Items carrying over | B21: Amount | C21: Items discarded | D21: Amount
A22: Jamon | B22: 541.5
A23: Ducks (week of 5/1) | B23: 1440.71
A24: Chuck Flap | B24: 528.23

Sheet Roister (417-423)
B1: CW | C1: Fortune | D1: Closed Loop | E1: A1 Firewood | F1: Wabash/Allen | G1: Superior | H1: Aya | I1: Rocker Bros | J1: D'artagnan | K1: Four Star | L1: Regalis | M1: D'amatos | N1: Cornille | O1: Truffles | P1: Rare Tea Cellar | Q1: Steve's | R1: Turano | S1: Daily Spend | T1: Daily Revenue | U1: Daily Cost %
A2: 45033 | B2: 2012.59 | C2: 1463.61 | F2: 783.83 | J2: 1563.2 | K2: 130 | Q2: 105.65 | S2: =SUM(B2:R2) -> 6058.88 | T2: 4882 | U2: =S2/T2 -> 1.2410651
A3: 45034 | B3: 694.49 | C3: 516.7 | R3: 179.96 | S3: =SUM(B3:R3) -> 1391.15 | T3: 6916.35 | U3: =S3/T3 -> 0.20113933
A4: 45035 | B4: 1178.4 | C4: 250.14 | F4: 198.32 | K4: 160 | M4: 18.5 | S4: =SUM(B4:R4) -> 1805.36 | T4: 8139.31 | U4: =S4/T4 -> 0.2218075
A5: 45036 | B5: 1460.62 | C5: 341.2 | M5: 18.5 | P5: 89 | S5: =SUM(B5:R5) -> 1909.32 | T5: 7176.2 | U5: =S5/T5 -> 0.26606282
A6: 45037 | B6: 1351.97 | C6: 170.17 | F6: 261.71 | G6: 285 | H6: 114.8 | M6: 18.5 | Q6: 105.65 | S6: =SUM(B6:R6) -> 2307.8 | T6: 10164.8 | U6: =S6/T6 -> 0.22703841
A7: 45038 | B7: 1976.13 | D7: 200 | F7: 210.83 | N7: 200 | R7: 36.27 | S7: =SUM(B7:R7) -> 2623.23 | T7: 22073.19 | U7: =S7/T7 -> 0.11884236
A8: 45039 | B8: N/A | C8: N/A | D8: N/A | E8: N/A | G8: N/A | H8: N/A | I8: N/A | J8: N/A | K8: N/A | L8: N/A | N8: N/A | O8: N/A | P8: N/A | Q8: N/A | R8: N/A | S8: 0 | T8: 8421.24 | U8: =S8/T8 -> 0
A11: Budget | B11: 13000
A12: Total Weekly Spend | B12: =SUM(B2:R8) -> 16095.74
A13: Remaing Spend | B13: =SUM(B11-B12) -> -3095.74
A15: Weekly Food Revenue | B15: =SUM(T2:T8) -> 67773.09
A16: Weekly Cost % | B16: =B12/B15 -> 0.23749456
A19: End of week status
A20: list items over $100
A21: Items carrying over | B21: Amount | C21: Items discarded | D21: Amount

Sheet Roister (424-430)
B1: CW | C1: Fortune | D1: Closed Loop | E1: A1 Firewood | F1: Wabash/Allen | G1: Superior | H1: Aya | I1: Rocker Bros | J1: D'artagnan | K1: Four Star | L1: Regalis | M1: D'amatos | N1: Cornille | O1: Truffles | P1: Rare Tea Cellar | Q1: Steve's | R1: Turano | S1: Daily Spend | T1: Daily Revenue | U1: Daily Cost %
A2: 45040 | B2: 1919.71 | C2: 430.1 | F2: 92.44 | J2: 1280.64 | K2: 120 | Q2: 105.65 | S2: =SUM(B2:R2) -> 3948.54 | T2: 4986 | U2: =S2/T2 -> 0.79192539
A3: 45041 | B3: 638.8 | C3: 485.74 | R3: 173.47 | S3: =SUM(B3:R3) -> 1298.01 | T3: 5422.2 | U3: =S3/T3 -> 0.23938807
A4: 45042 | B4: 1423.76 | C4: 412 | G4: 664.9 | M4: 18.5 | S4: =SUM(B4:R4) -> 2519.16 | T4: 8271.77 | U4: =S4/T4 -> 0.30454909
A5: 45043 | B5: 799.66 | C5: 252.65 | E5: 180 | F5: 197.53 | M5: 18.5 | S5: =SUM(B5:R5) -> 1448.34 | T5: 7712.5 | U5: =S5/T5 -> 0.18779125
A6: 45044 | B6: 1870.7 | C6: 224.72 | G6: 190 | H6: 114.8 | M6: 18.5 | Q6: 105.65 | S6: =SUM(B6:R6) -> 2524.37 | T6: 10935.6 | U6: =S6/T6 -> 0.23083964
A7: 45045 | B7: 1625.67 | C7: 437.35 | D7: 200 | N7: 200 | P7: 39 | S7: =SUM(B7:R7) -> 2502.02 | T7: 16080.43 | U7: =S7/T7 -> 0.1555941
A8: 45046 | B8: N/A | C8: N/A | D8: N/A | E8: N/A | G8: N/A | H8: N/A | I8: N/A | J8: N/A | K8: N/A | L8: N/A | N8: N/A | O8: N/A | P8: N/A | Q8: N/A | R8: N/A | S8: 0 | T8: 10669 | U8: =S8/T8 -> 0
A11: Budget | B11: 13000
A12: Total Weekly Spend | B12: =SUM(B2:R8) -> 14240.44
A13: Remaing Spend | B13: =SUM(B11-B12) -> -1240.44
A15: Weekly Food Revenue | B15: =SUM(T2:T8) -> 64077.5
A16: Weekly Cost % | B16: =B12/B15 -> 0.22223776
A19: End of week status
A20: list items over $100
A21: Items carrying over | B21: Amount | C21: Items discarded | D21: Amount
A22: Jamon | B22: 323.55

Sheet Roister (51-57)
B1: CW | C1: Fortune | D1: Closed Loop | E1: A1 Firewood | F1: Wabash/Allen | G1: Superior | H1: Aya | I1: Rocker Bros | J1: D'artagnan | K1: Four Star | L1: Regalis | M1: D'amatos | N1: Cornille | O1: Truffles | P1: Rare Tea Cellar | Q1: Steve's | R1: Turano | S1: Daily Spend | T1: Daily Revenue | U1: Daily Cost %
A2: 45047 | B2: 2039.95 | C2: 75.98 | F2: 248.57 | J2: 1440 | K2: 120 | Q2: 105.65 | S2: =SUM(B2:R2) -> 4030.15 | T2: 5048.73 | U2: =S2/T2 -> 0.79825025
A3: 45048 | B3: 1094.75 | G3: 284.9 | R3: 173.47 | S3: =SUM(B3:R3) -> 1553.12 | T3: 4345.99 | U3: =S3/T3 -> 0.35736852
A4: 45049 | B4: 1281.63 | C4: 277.4 | F4: 360.73 | G4: 190 | H4: 47 | M4: 18.5 | S4: =SUM(B4:R4) -> 2175.26 | T4: 6211.7 | U4: =S4/T4 -> 0.35018755
A5: 45050 | B5: 979.19 | C5: 477.03 | F5: 491.01 | H5: 123 | M5: 18.5 | S5: =SUM(B5:R5) -> 2088.73 | T5: 8245 | U5: =S5/T5 -> 0.25333293
A6: 45051 | B6: 1851.67 | C6: 231.4 | F6: 140.08 | G6: 664.9 | M6: 18.5 | Q6: 105.65 | S6: =SUM(B6:R6) -> 3012.2 | T6: 11875.5 | U6: =S6/T6 -> 0.25364827
A7: 45052 | B7: 1850.79 | C7: 130.95 | D7: 200 | F7: 176.94 | N7: 200 | R7: 62.07 | S7: =SUM(B7:R7) -> 2620.75 | T7: 15937.74 | U7: =S7/T7 -> 0.16443674
A8: 45053 | B8: N/A | C8: N/A | D8: N/A | E8: N/A | G8: N/A | H8: N/A | I8: N/A | J8: N/A | K8: N/A | L8: N/A | N8: N/A | O8: N/A | P8: N/A | Q8: N/A | R8: N/A | S8: 0 | T8: 11349.26 | U8: =S8/T8 -> 0
A11: Budget | B11: 13000
A12: Total Weekly Spend | B12: =SUM(B2:R8) -> 15480.21
A13: Remaing Spend | B13: =SUM(B11-B12) -> -2480.21
A15: Weekly Food Revenue | B15: =SUM(T2:T8) -> 63013.92
A16: Weekly Cost % | B16: =B12/B15 -> 0.24566334
A19: End of week status
A20: list items over $100
A21: Items carrying over | B21: Amount | C21: Items discarded | D21: Amount
A22: Tail Flap(short Ribs) | B22: 491.01

Sheet Roister (58-514)
B1: CW | C1: Fortune | D1: Closed Loop | E1: A1 Firewood | F1: Wabash/Allen | G1: Superior | H1: Aya | I1: Rocker Bros | J1: D'artagnan | K1: Four Star | L1: Regalis | M1: D'amatos | N1: Cornille | O1: Truffles | P1: Rare Tea Cellar | Q1: Steve's | R1: Turano | S1: Daily Spend | T1: Daily Revenue | U1: Daily Cost %
A2: 45054 | B2: 2844.59 | C2: 407.2 | F2: 479.88 | J2: 74.68 | K2: 130 | P2: 39 | S2: =SUM(B2:R2) -> 3975.35 | T2: 6101.4 | U2: =S2/T2 -> 0.65154719 | V2: =A2 -> 45054
A3: 45055 | B3: 556.88 | C3: 29 | H3: 42 | R3: 179.96 | S3: =SUM(B3:R3) -> 807.84 | T3: 6687.17 | U3: =S3/T3 -> 0.12080447 | V3: =A3 -> 45055
A4: 45056 | B4: 2371.02 | C4: 422.46 | M4: 18.5 | S4: =SUM(B4:R4) -> 2811.98 | T4: 5383.53 | U4: =S4/T4 -> 0.52233014 | V4: =A4 -> 45056
A5: 45057 | B5: 2280.81 | C5: 1265.26 | E5: 180 | F5: 904.68 | H5: 278.8 | K5: 360 | M5: 18.5 | P5: 88.5 | S5: =SUM(B5:R5) -> 5376.55 | T5: 8139 | U5: =S5/T5 -> 0.66059098 | V5: =A5 -> 45057
A6: 45058 | B6: 1355.79 | C6: 475.16 | M6: 18.5 | Q6: 105.65 | S6: =SUM(B6:R6) -> 1955.1 | T6: 11242.05 | U6: =S6/T6 -> 0.17390956 | V6: =A6 -> 45058
A7: 45059 | B7: 1873 | C7: 344.82 | D7: 200 | F7: 109.66 | N7: 100 | S7: =SUM(B7:R7) -> 2627.48 | T7: 19082.37 | U7: =S7/T7 -> 0.13769149 | V7: =A7 -> 45059
A8: 45060 | B8: N/A | C8: N/A | D8: N/A | E8: N/A | G8: N/A | H8: N/A | I8: N/A | J8: N/A | K8: N/A | L8: N/A | N8: N/A | O8: N/A | P8: N/A | Q8: N/A | R8: N/A | S8: 0 | T8: 21972 | U8: =S8/T8 -> 0 | V8: =A8 -> 45060
A11: Budget | B11: 13000
A12: Total Weekly Spend | B12: =SUM(B2:R8) -> 17554.3
A13: Remaing Spend | B13: =SUM(B11-B12) -> -4554.3
A15: Weekly Food Revenue | B15: =SUM(T2:T8) -> 78607.52
A16: Weekly Cost % | B16: =B12/B15 -> 0.22331578
A19: End of week status
A20: list items over $100
A21: Items carrying over | B21: Amount | C21: Items discarded | D21: Amount
A22: Hamachi Collars | B22: 284.9
A23: Bellota Ham BNLS | B23: 551.39
A26: Duck week 1
A28: Duck Week 2
A30: Third week it become Dartagnan spend

Sheet Roister (515-521)
B1: CW | C1: Fortune | D1: Closed Loop | E1: A1 Firewood | F1: Wabash/Allen | G1: Superior | H1: Aya | I1: Rocker Bros | J1: D'artagnan | K1: Four Star | L1: Regalis | M1: D'amatos | N1: Cornille | O1: Truffles | P1: Rare Tea Cellar | Q1: Steve's | R1: Turano | S1: Daily Spend | T1: Daily Revenue | U1: Daily Cost %
A2: 45061 | B2: 2481.64 | C2: 903.19 | F2: 152 | K2: 130 | N2: 298 | P2: 57.5 | Q2: 109.97 | S2: =SUM(B2:R2) -> 4132.3 | T2: 6135.08 | U2: =S2/T2 -> 0.67355275 | V2: =A2 -> 45061
A3: 45062 | B3: 630.74 | C3: 452.71 | D3: 156 | G3: 284.9 | H3: 42 | R3: 179.96 | S3: =SUM(B3:R3) -> 1746.31 | T3: 7295.32 | U3: =S3/T3 -> 0.23937401 | V3: =A3 -> 45062
A4: 45063 | B4: 1544.58 | F4: 381.51 | J4: 226.65 | M4: 18.5 | N4: 168 | Q4: 109.97 | S4: =SUM(B4:R4) -> 2449.21 | T4: 11110.01 | U4: =S4/T4 -> 0.22045075 | V4: =A4 -> 45063
A5: 45064 | B5: 1721.81 | C5: 363.4 | E5: 180 | H5: 123 | M5: 18.5 | S5: =SUM(B5:R5) -> 2406.71 | T5: 26922.01 | U5: =S5/T5 -> 0.089395628 | V5: =A5 -> 45064
A6: 45065 | B6: 1408.87 | C6: 933.57 | G6: 569.9 | J6: 1624.13 | K6: 120 | P6: 117 | Q6: 109.97 | S6: =SUM(B6:R6) -> 4883.44 | T6: 21020 | U6: =S6/T6 -> 0.2323235 | V6: =A6 -> 45065
A7: 45066 | B7: 2141.54 | C7: 1091.32 | N7: 270 | R7: 67.71 | S7: =SUM(B7:R7) -> 3570.57 | T7: 29430.71 | U7: =S7/T7 -> 0.12132123 | V7: =A7 -> 45066
A8: 45067 | B8: N/A | C8: N/A | D8: N/A | E8: N/A | G8: N/A | H8: N/A | I8: N/A | J8: N/A | K8: N/A | L8: N/A | N8: N/A | O8: N/A | P8: N/A | Q8: N/A | R8: N/A | S8: 0 | T8: 17579.54 | U8: =S8/T8 -> 0 | V8: =A8 -> 45067
B9: fortune invoice | C9: 683163
A11: Budget | B11: 13000
A12: Total Weekly Spend | B12: =SUM(B2:R8) -> 19188.54
A13: Remaing Spend | B13: =SUM(B11-B12) -> -6188.54
A15: Weekly Food Revenue | B15: =SUM(T2:T8) -> 119492.67 | C15: =B15*0.1175 -> 14040.389 | D15: =B15-C15 -> 105452.28
A16: Weekly Cost % | B16: =B12/B15 -> 0.16058341
A19: End of week status
A20: list items over $100
A21: Items carrying over | B21: Amount | C21: Items discarded | D21: Amount
A22: Hamachi Collars
A23: Bellota Ham BNLS

Sheet Roister (522-528)
B1: CW | C1: Fortune | D1: Closed Loop | E1: A1 Firewood | F1: Wabash/Allen | G1: Superior | H1: Aya | I1: Rocker Bros | J1: D'artagnan | K1: Four Star | L1: Other | M1: D'amatos | N1: Cornille | O1: Truffles | P1: Rare Tea Cellar | Q1: Steve's | R1: Turano | S1: Daily Spend | T1: Daily Revenue | U1: Daily Cost %
A2: 45068 | B2: 2850.03 | C2: 627.54 | F2: 304.75 | K2: 240 | M2: 18.5 | Q2: 109.97 | S2: =SUM(B2:R2) -> 4150.79 | T2: 9972.5 | U2: =S2/T2 -> 0.41622361 | V2: =A2 -> 45068
A3: 45069 | B3: 1292.84 | C3: 744.76 | D3: 132 | F3: 460.92 | G3: 759.8 | H3: 42 | N3: 468 | R3: 179.96 | S3: =SUM(B3:R3) -> 4080.28 | T3: 6433.6 | U3: =S3/T3 -> 0.63421413 | V3: =A3 -> 45069
A4: 45070 | B4: 1701.01 | C4: 286.6 | J4: 1011.59 | M4: 18.5 | Q4: 109.97 | S4: =SUM(B4:R4) -> 3127.67 | T4: 7004 | U4: =S4/T4 -> 0.44655483 | V4: =A4 -> 45070
A5: 45071 | B5: 1456.08 | C5: 586.72 | E5: 180 | F5: 551.53 | G5: 95 | H5: 123 | L5: 180 | M5: 18.5 | S5: =SUM(B5:R5) -> 3190.83 | T5: 6770 | U5: =S5/T5 -> 0.47131905 | V5: =A5 -> 45071
A6: 45072 | B6: 1210.35 | C6: 518.56 | D6: 221 | F6: 209.5 | M6: 18.5 | Q6: 109.97 | S6: =SUM(B6:R6) -> 2287.88 | T6: 12624.05 | U6: =S6/T6 -> 0.18123186 | V6: =A6 -> 45072
A7: 45073 | B7: 1661.93 | C7: 133.05 | R7: 61.26 | S7: =SUM(B7:R7) -> 1856.24 | T7: 19342.4 | U7: =S7/T7 -> 0.095967408 | V7: =A7 -> 45073
A8: 45074 | B8: N/A | C8: N/A | D8: N/A | E8: N/A | G8: N/A | H8: N/A | I8: N/A | J8: N/A | K8: N/A | L8: N/A | N8: N/A | O8: N/A | P8: N/A | Q8: N/A | R8: N/A | S8: 0 | T8: 15176.5 | U8: =S8/T8 -> 0 | V8: =A8 -> 45074
A11: Budget | B11: 13000
A12: Total Weekly Spend | B12: =SUM(B2:R8) -> 18693.69
A13: Remaing Spend | B13: =SUM(B11-B12) -> -5693.69
A15: Weekly Food Revenue | B15: =SUM(T2:T8) -> 77323.05
A16: Weekly Cost % | B16: =B12/B15 -> 0.2417609
A19: End of week status
A20: list items over $100
A21: Items carrying over | B21: Amount | C21: Items discarded | D21: Amount
A22: Hamachi Collars
A23: Bellota Ham BNLS | C23: next week: 518.56
A24: Short ribs | B24: 1089.93 | C24: week 1: 544.97 | D24: week 2: 544.97

Sheet Roister (529-64)
B1: CW | C1: Fortune | D1: Closed Loop | E1: A1 Firewood | F1: Wabash/Allen | G1: Superior | H1: Aya | I1: Rocker Bros | J1: D'artagnan | K1: Four Star | L1: Regalis | M1: D'amatos | N1: Cornille | O1: Truffles | P1: Rare Tea Cellar | Q1: Steve's | R1: Turano | S1: Daily Spend | T1: Daily Revenue | U1: Daily Cost %
A2: 45075 | B2: 544.97 | J2: 1002 | K2: 168 | S2: =SUM(B2:R2) -> 1714.97 | T2: 3041.2 | U2: =S2/T2 -> 0.56391227 | V2: =A2 -> 45075
A3: 45076 | B3: 1057.49 | C3: 1221.64 | F3: 334.06 | G3: 757.06 | H3: 42 | J3: 199.36 | N3: 226.25 | R3: 179.96 | S3: =SUM(B3:R3) -> 4017.82 | T3: 4959.46 | U3: =S3/T3 -> 0.81013255 | V3: =A3 -> 45076
A4: 45077 | B4: 1745.99 | C4: 427.76 | M4: 18.5 | Q4: 109.97 | S4: =SUM(B4:R4) -> 2302.22 | T4: 6953 | U4: =S4/T4 -> 0.33111175 | V4: =A4 -> 45077
A5: 45078 | B5: 959.41 | C5: 328 | E5: 180 | F5: 577.48 | H5: 123 | M5: 18.5 | N5: 38 | P5: 76.5 | S5: =SUM(B5:R5) -> 2300.89 | T5: 8590.01 | U5: =S5/T5 -> 0.2678565 | V5: =A5 -> 45078
A6: 45079 | B6: 1208.46 | C6: 780.3 | D6: 244 | K6: 168 | M6: 18.5 | N6: 166 | P6: 180 | Q6: 109.97 | S6: =SUM(B6:R6) -> 2875.23 | T6: 15942 | U6: =S6/T6 -> 0.18035566 | V6: =A6 -> 45079
A7: 45080 | B7: 1163.84 | C7: 256.06 | F7: 183.34 | G7: 380 | N7: 135 | R7: 48.36 | S7: =SUM(B7:R7) -> 2166.6 | T7: 20130 | U7: =S7/T7 -> 0.1076304 | V7: =A7 -> 45080
A8: 45081 | B8: N/A | C8: N/A | D8: N/A | E8: N/A | G8: N/A | H8: N/A | I8: N/A | J8: N/A | K8: N/A | L8: N/A | N8: N/A | O8: N/A | P8: N/A | Q8: N/A | R8: N/A | S8: 0 | T8: 11502.05 | U8: =S8/T8 -> 0 | V8: =A8 -> 45081
A11: Budget | B11: 13000
A12: Total Weekly Spend | B12: =SUM(B2:R8) -> 15377.73
A13: Remaing Spend | B13: =SUM(B11-B12) -> -2377.73
A15: Weekly Food Revenue | B15: =SUM(T2:T8) -> 71117.72
A16: Weekly Cost % | B16: =B12/B15 -> 0.21622923
A19: End of week status
A20: list items over $100
A21: Items carrying over | B21: Amount | C21: Items discarded | D21: Amount
A22: Hamachi Collars
A23: Bellota Ham BNLS
A24: Short ribs | B24: 544.97 | D24: week 2: 544.97

Sheet Roister (65-611)
B1: CW | C1: Fortune | D1: Closed Loop | E1: A1 Firewood | F1: Wabash/Allen | G1: Superior | H1: Aya | I1: Rocker Bros | J1: D'artagnan | K1: Four Star | L1: Regalis | M1: D'amatos | N1: Cornille | O1: Truffles | P1: Rare Tea Cellar | Q1: Steve's | R1: Turano | S1: Beca Imp | T1: Daily Spend | U1: Daily Revenue | V1: Daily Cost % | X1: Beca Imp
A2: 45082 | B2: 2307.68 | C2: 1395.86 | F2: 232.09 | J2: 205.07 | K2: 168 | Q2: 109.97 | S2: 44 | T2: =SUM(B2:S2) -> 4462.67 | U2: =8094.7-2394 -> 5700.7 | V2: =T2/U2 -> 0.78282842 | W2: =A2 -> 45082 | X2: 44
A3: 45083 | B3: 1038.72 | C3: 663.49 | D3: 205 | H3: 42 | N3: 399 | R3: 179 | T3: =SUM(B3:S3) -> 2527.21 | U3: =21058.5-8925-5250 -> 6883.5 | V3: =T3/U3 -> 0.36714026 | W3: =A3 -> 45083
A4: 45084 | B4: 2078.61 | C4: 945.97 | F4: 316 | G4: 473.08 | M4: 18.5 | Q4: 109.97 | T4: =SUM(B4:S4) -> 3942.13 | U4: =17841-1144 -> 16697 | V4: =T4/U4 -> 0.2360981 | W4: =A4 -> 45084
A5: 45085 | B5: 1824.66 | E5: 280 | F5: 415.78 | H5: 123 | M5: 18.5 | P5: 134 | T5: =SUM(B5:S5) -> 2795.94 | U5: =12556.2-2870 -> 9686.2 | V5: =T5/U5 -> 0.2886519 | W5: =A5 -> 45085
A6: 45086 | B6: 2568.33 | C6: 585 | F6: 109.12 | G6: 758.8 | M6: 18.5 | Q6: 109.97 | T6: =SUM(B6:S6) -> 4149.72 | U6: =15287.6-2916.5 -> 12371.1 | V6: =T6/U6 -> 0.33543662 | W6: =A6 -> 45086
A7: 45087 | B7: 1697.56 | C7: 206.4 | R7: 43.32 | T7: =SUM(B7:S7) -> 1947.28 | U7: =23987.1-4382 -> 19605.1 | V7: =T7/U7 -> 0.099325176 | W7: =A7 -> 45087
A8: 45088 | B8: N/A | C8: N/A | D8: N/A | E8: N/A | G8: N/A | H8: N/A | I8: N/A | J8: N/A | K8: N/A | L8: N/A | N8: N/A | O8: N/A | P8: N/A | Q8: N/A | R8: N/A | S8: N/A | T8: 0 | U8: =11650.6-1335.6 -> 10315 | V8: =T8/U8 -> 0 | W8: =A8 -> 45088
B9: =SUM(B2:B8) -> 11515.56 | C9: =SUM(C2:C8) -> 3796.72
A11: Budget | B11: 13000
A12: Total Weekly Spend | B12: =SUM(B2:R8) -> 19780.95
A13: Remaing Spend | B13: =SUM(B11-B12) -> -6780.95
A15: Weekly Food Revenue | B15: =SUM(U2:U8) -> 81258.6
A16: Weekly Cost % | B16: =B12/B15 -> 0.24343208
A19: End of week status
A20: list items over $100
A21: Items carrying over | B21: Amount | C21: Items discarded | D21: Amount
A22: Hamachi Collars
A23: Bellota Ham BNLS
A24: Short ribs | B24: week 6/9 $638.08 | D24: 1277.61
A25: Duck Legs | B25: 560.53 | D25: 560.53
A26: Salmon Glory Bay | B26: 185.13 | D26: 185.13

Sheet Roister (612-618)
B1: CW | C1: Fortune | D1: Closed Loop | E1: A1 Firewood | F1: Wabash/Allen | G1: Superior | H1: Aya | I1: Rocker Bros | J1: D'artagnan | K1: Four Star | L1: Regalis | M1: D'amatos | N1: Cornille | O1: Truffles | P1: Rare Tea Cellar | Q1: Steve's | R1: Turano | S1: Daily Spend | T1: Daily Revenue | U1: Daily Cost %
A2: 45089 | B2: 2839.56 | C2: 445 | F2: 281.09 | K2: 168 | L2: 144 | S2: =SUM(B2:R2) -> 3877.65 | T2: 12152.01 | U2: =S2/T2 -> 0.31909536 | V2: =A2 -> 45089
A3: 45090 | B3: 1003.47 | C3: 2226.63 | F3: 185.13 | H3: 42 | R3: 179.76 | S3: =SUM(B3:R3) -> 3636.99 | T3: 8141.5 | U3: =S3/T3 -> 0.44672235 | V3: =A3 -> 45090
A4: 45091 | B4: 1598.87 | C4: 445 | E4: 280 | F4: 137.91 | G4: 285 | M4: 18.5 | S4: =SUM(B4:R4) -> 2765.28 | T4: 9053.07 | U4: =S4/T4 -> 0.30545218 | V4: =A4 -> 45091
A5: 45092 | B5: 2746.44 | C5: 750.36 | F5: 71.69 | H5: 123 | M5: 18.5 | R5: 1462.5 | S5: =SUM(B5:R5) -> 5172.49 | T5: 6837.8 | U5: =S5/T5 -> 0.75645529 | V5: =A5 -> 45092
A6: 45093 | B6: 1373.52 | C6: 1504.2 | F6: 529.51 | G6: 285 | M6: 18.5 | S6: =SUM(B6:R6) -> 3710.73 | T6: 19975.41 | U6: =S6/T6 -> 0.1857649 | V6: =A6 -> 45093
A7: 45094 | B7: 2021.04 | C7: 144.09 | S7: =SUM(B7:R7) -> 2165.13 | T7: 36252.54 | U7: =S7/T7 -> 0.059723539 | V7: =A7 -> 45094
A8: 45095 | B8: N/A | C8: N/A | D8: N/A | E8: N/A | G8: N/A | H8: N/A | I8: N/A | J8: N/A | K8: N/A | L8: N/A | N8: N/A | O8: N/A | P8: N/A | Q8: N/A | R8: N/A | S8: 0 | T8: 26781.01 | U8: =S8/T8 -> 0 | V8: =A8 -> 45095
A11: Budget | B11: 13000
A12: Total Weekly Spend | B12: =SUM(B2:R8) -> 21328.27
A13: Remaing Spend | B13: =SUM(B11-B12) -> -8328.27
A15: Weekly Food Revenue | B15: =SUM(T2:T8) -> 119193.34
A16: Weekly Cost % | B16: =B12/B15 -> 0.17893844
A19: End of week status
A20: list items over $100
A21: Items carrying over | B21: Amount | C21: Items discarded | D21: Amount
A22: Hamachi Collars
A23: Bellota Ham BNLS | B23: 995.75 | D23: 995.75
A24: Short ribs | B24: week 6/9 $638.08 | D24: 638.08
A25: Duck Legs
A26: Salmon Glory Bay

Sheet Roister (619-625)
B1: CW | C1: Fortune | D1: Closed Loop | E1: A1 Firewood | F1: Wabash/Allen | G1: Superior | H1: Aya | I1: Rocker Bros | J1: D'artagnan | K1: Four Star | L1: Regalis | M1: D'amatos | N1: Cornille | O1: Truffles | P1: Rare Tea Cellar | Q1: Steve's | R1: Turano | S1: Daily Spend | T1: Daily Revenue | U1: Daily Cost %
A2: 45096 | B2: 1956 | C2: 857.18 | F2: 670.23 | K2: 168 | P2: 57.05 | S2: =SUM(B2:R2) -> 3708.46 | T2: 14733.6 | U2: =S2/T2 -> 0.25170087 | V2: =A2 -> 45096
A3: 45097 | B3: 1517.44 | F3: 105.42 | G3: 852.06 | H3: 42 | R3: 179.96 | S3: =SUM(B3:R3) -> 2696.88 | T3: 6258.6 | U3: =S3/T3 -> 0.43090787 | V3: =A3 -> 45097
A4: 45098 | B4: 1139.81 | C4: 1244.07 | M4: 18.5 | S4: =SUM(B4:R4) -> 2402.38 | T4: 9381.91 | U4: =S4/T4 -> 0.25606513 | V4: =A4 -> 45098
A5: 45099 | B5: 1213.54 | C5: 394.21 | E5: 280 | F5: 211.2 | H5: 123 | M5: 18.5 | S5: =SUM(B5:R5) -> 2240.45 | T5: 8142.01 | U5: =S5/T5 -> 0.27517161 | V5: =A5 -> 45099
A6: 45100 | B6: 1621.05 | C6: 1131.8 | F6: 72.93 | G6: 190 | M6: 18.5 | S6: =SUM(B6:R6) -> 3034.28 | T6: 10087 | U6: =S6/T6 -> 0.30081094 | V6: =A6 -> 45100
A7: 45101 | B7: 2067.79 | C7: 211.4 | M7: 86.25 | S7: =SUM(B7:R7) -> 2365.44 | T7: 15108 | U7: =S7/T7 -> 0.15656871 | V7: =A7 -> 45101
A8: 45102 | B8: N/A | C8: N/A | D8: N/A | E8: N/A | G8: N/A | H8: N/A | I8: N/A | J8: N/A | K8: N/A | L8: N/A | N8: N/A | O8: N/A | P8: N/A | Q8: N/A | R8: N/A | S8: 0 | T8: 11847.04 | U8: =S8/T8 -> 0 | V8: =A8 -> 45102
A11: Budget | B11: 13000
A12: Total Weekly Spend | B12: =SUM(B2:R8) -> 16447.89
A13: Remaing Spend | B13: =SUM(B11-B12) -> -3447.89
A15: Weekly Food Revenue | B15: =SUM(T2:T8) -> 75558.16
A16: Weekly Cost % | B16: =B12/B15 -> 0.21768516
A19: End of week status
A20: list items over $100
A21: Items carrying over | B21: Amount | C21: Items discarded | D21: Amount
A22: Hamachi Collars
A23: Bellota Ham BNLS
A24: Short ribs
A25: Duck Legs
A26: Salmon Glory Bay

Sheet Roister (626-72)
B1: CW | C1: Fortune | D1: Closed Loop | E1: A1 Firewood | F1: Wabash/Allen | G1: Superior | H1: Aya | I1: Rocker Bros | J1: D'artagnan | K1: Four Star | L1: Regalis | M1: D'amatos | N1: Cornille | O1: Truffles | P1: Rare Tea Cellar | Q1: Steve's | R1: Turano | S1: Daily Spend | T1: Daily Revenue | U1: Daily Cost %
A2: 45082 | S2: =SUM(B2:R2) -> 0 | U2: =S2/T2 -> #DIV/0! | V2: =A2 -> 45082
A3: 45083 | S3: =SUM(B3:R3) -> 0 | U3: =S3/T3 -> #DIV/0! | V3: =A3 -> 45083
A4: 45084 | S4: =SUM(B4:R4) -> 0 | U4: =S4/T4 -> #DIV/0! | V4: =A4 -> 45084
A5: 45085 | S5: =SUM(B5:R5) -> 0 | U5: =S5/T5 -> #DIV/0! | V5: =A5 -> 45085
A6: 45086 | S6: =SUM(B6:R6) -> 0 | U6: =S6/T6 -> #DIV/0! | V6: =A6 -> 45086
A7: 45087 | S7: =SUM(B7:R7) -> 0 | U7: =S7/T7 -> #DIV/0! | V7: =A7 -> 45087
A8: 45088 | B8: N/A | C8: N/A | D8: N/A | E8: N/A | G8: N/A | H8: N/A | I8: N/A | J8: N/A | K8: N/A | L8: N/A | N8: N/A | O8: N/A | P8: N/A | Q8: N/A | R8: N/A | S8: 0 | U8: =S8/T8 -> #DIV/0! | V8: =A8 -> 45088
A11: Budget | B11: 13000
A12: Total Weekly Spend | B12: =SUM(B2:R8) -> 0
A13: Remaing Spend | B13: =SUM(B11-B12) -> 13000
A15: Weekly Food Revenue | B15: =SUM(T2:T8) -> 0
A16: Weekly Cost % | B16: =B12/B15 -> #DIV/0!
A19: End of week status
A20: list items over $100
A21: Items carrying over | B21: Amount | C21: Items discarded | D21: Amount
A22: Hamachi Collars
A23: Bellota Ham BNLS
A24: Short ribs
A25: Duck Legs
A26: Salmon Glory Bay

Sheet Roister (73-79)
B1: CW | C1: Fortune | D1: Closed Loop | E1: A1 Firewood | F1: Wabash/Allen | G1: Superior | H1: Aya | I1: Rocker Bros | J1: D'artagnan | K1: Four Star | L1: Regalis | M1: D'amatos | N1: Cornille | O1: Truffles | P1: Rare Tea Cellar | Q1: Steve's | R1: Murphy's | S1: Turano | T1: Regiis Ova | U1: Daily Spend | V1: Daily Revenue | W1: Daily Cost %
A2: 45110 | B2: 826.04 | C2: 486.76 | K2: 168 | U2: =SUM(B2:S2) -> 1480.8 | V2: 10100 | W2: =U2/V2 -> 0.14661386 | X2: =A2 -> 45110
A3: 45111 | B3: 86.44 | H3: 42 | U3: =SUM(B3:S3) -> 128.44 | V3: 0 | W3: =U3/V3 -> #DIV/0! | X3: =A3 -> 45111
A4: 45112 | B4: 730.56 | C4: 226.06 | G4: 637.8 | M4: 18.5 | T4: 1155.58 | U4: =SUM(B4:T4) -> 2768.5 | V4: 4923 | W4: =U4/V4 -> 0.56236035 | X4: =A4 -> 45112
A5: 45113 | B5: 1191.35 | C5: 387.72 | E5: 280 | F5: 460.29 | H5: 123 | M5: 18.5 | P5: 39 | R5: 196 | S5: 92.7 | U5: =SUM(B5:S5) -> 2788.56 | V5: 6819.5 | W5: =U5/V5 -> 0.40890974 | X5: =A5 -> 45113
A6: 45114 | B6: 927.59 | C6: 395.68 | G6: 508.3 | M6: 18.5 | U6: =SUM(B6:S6) -> 1850.07 | V6: 10997 | W6: =U6/V6 -> 0.16823406 | X6: =A6 -> 45114
A7: 45115 | B7: 920.97 | C7: 306.8 | F7: 264.5 | S7: 148.36 | U7: =SUM(B7:S7) -> 1640.63 | V7: 14702.2 | W7: =U7/V7 -> 0.11159078 | X7: =A7 -> 45115
A8: 45116 | B8: N/A | C8: N/A | D8: N/A | E8: N/A | F8: N/A | G8: N/A | H8: N/A | I8: N/A | J8: N/A | K8: N/A | L8: N/A | M8: N/A | N8: N/A | O8: N/A | P8: N/A | Q8: N/A | R8: N/A | S8: N/A | T8: N/A | U8: 0 | V8: 8483.7 | W8: =U8/V8 -> 0 | X8: =A8 -> 45116
A11: Budget | B11: 13000
A12: Total Weekly Spend | B12: =SUM(B2:S8) -> 9501.42
A13: Remaing Spend | B13: =SUM(B11-B12) -> 3498.58
A15: Weekly Food Revenue | B15: =SUM(V2:V8) -> 56025.4
A16: Weekly Cost % | B16: =B12/B15 -> 0.16959129
A19: End of week status
A20: list items over $100
A21: Items carrying over | B21: Amount | C21: Items discarded | D21: Amount
A22: Hamachi Collars
A23: Bellota Ham BNLS
A24: Short ribs
A25: Duck Legs
A26: Salmon Glory Bay
A27: Caviar | B27: 1 tin (500 grams) | D27: 690

Sheet Roister (710-716
B1: CW | C1: Fortune | D1: Closed Loop | E1: A1 Firewood | F1: Wabash/Allen | G1: Superior | H1: Aya | I1: Rocker Bros | J1: D'artagnan | K1: Four Star | L1: Regalis | M1: D'amatos | N1: Cornille | O1: Truffles | P1: Honey | Q1: Murphy | R1: Rare Tea Cellar | S1: Steve's | T1: Turano | U1: Daily Spend | V1: Daily Revenue | W1: Daily Cost %
A2: 45117 | B2: 1630.87 | C2: 477.8 | F2: 467.05 | K2: 168 | R2: 64 | U2: =SUM(B2:T2) -> 2807.72 | V2: 5789 | W2: =U2/V2 -> 0.4850095 | X2: =A2 -> 45117
A3: 45118 | B3: 633.4 | G3: 577.3 | H3: 42 | L3: 144 | T3: 179.96 | U3: =SUM(B3:T3) -> 1576.66 | V3: 6835.8 | W3: =U3/V3 -> 0.23064747 | X3: =A3 -> 45118
A4: 45119 | B4: 696.95 | C4: 1334.81 | M4: 18.5 | U4: =SUM(B4:T4) -> 2050.26 | V4: 9423.4 | W4: =U4/V4 -> 0.21757115 | X4: =A4 -> 45119
A5: 45120 | B5: 1429.21 | C5: 383.22 | G5: 909.8 | H5: 123 | M5: 18.5 | P5: 615 | Q5: 224 | U5: =SUM(B5:T5) -> 3702.73 | V5: 9875.6 | W5: =U5/V5 -> 0.37493722 | X5: =A5 -> 45120
A6: 45121 | B6: 2253.89 | C6: 691.4 | E6: 280 | F6: 740.86 | M6: 18.5 | U6: =SUM(B6:T6) -> 3984.65 | V6: 12427.2 | W6: =U6/V6 -> 0.3206394 | X6: =A6 -> 45121
A7: 45122 | B7: 1408.38 | C7: 459.98 | T7: 48.36 | U7: =SUM(B7:T7) -> 1916.72 | V7: 16616.5 | W7: =U7/V7 -> 0.1153504 | X7: =A7 -> 45122
A8: 45123 | B8: N/A | C8: N/A | D8: N/A | E8: N/A | G8: N/A | H8: N/A | I8: N/A | J8: N/A | K8: N/A | L8: N/A | N8: N/A | O8: N/A | Q8: 96 | R8: N/A | S8: N/A | T8: N/A | U8: 0 | V8: 9529 | W8: =U8/V8 -> 0 | X8: =A8 -> 45123
A11: Budget | B11: 13000
A12: Total Weekly Spend | B12: =SUM(B2:T8) -> 16134.74
A13: Remaing Spend | B13: =SUM(B11-B12) -> -3134.74
A15: Weekly Food Revenue | B15: =SUM(V2:V8) -> 70496.5
A16: Weekly Cost % | B16: =B12/B15 -> 0.22887292
A19: End of week status
A20: list items over $100
A21: Items carrying over | B21: Amount | C21: Items discarded | D21: Amount
A22: Hamachi Collars
A23: Bellota Ham BNLS | B23: whole leg | D23: 920.19
A24: Short ribs
A25: Duck Legs
A26: Salmon Glory Bay

Sheet Roister (717-723)
B1: CW | C1: Fortune | D1: Closed Loop | E1: A1 Firewood | F1: Wabash/Allen | G1: Superior | H1: Aya | I1: Rocker Bros | J1: D'artagnan | K1: Four Star | L1: Regalis | M1: Murphy | N1: D'amatos | O1: Honey | P1: Cornille | Q1: Truffles | R1: Rare Tea Cellar | S1: Steve's | T1: Beca | U1: Turano | V1: Daily Spend | W1: Daily Revenue | X1: Daily Cost %
A2: 45124 | B2: 1695.44 | C2: 931.6 | J2: 991.91 | K2: 168 | O2: 252 | P2: 307 | S2: 109.97 | V2: =SUM(B2:U2) -> 4455.92 | W2: 7928.4 | X2: =V2/W2 -> 0.56202008 | Y2: =A2 -> 45124
A3: 45125 | B3: 1269.8 | C3: 211.81 | E3: 280 | F3: 261.49 | H3: 42 | M3: 60 | P3: 775 | U3: 179.96 | V3: =SUM(B3:U3) -> 3080.06 | W3: 7929.5 | X3: =V3/W3 -> 0.38843054 | Y3: =A3 -> 45125
A4: 45126 | B4: 783.93 | C4: 726.17 | F4: 1105.5 | G4: 388.5 | N4: 18.5 | S4: 109.97 | T4: 245 | V4: =SUM(B4:U4) -> 3377.57 | W4: 9671.1 | X4: =V4/W4 -> 0.34924362 | Y4: =A4 -> 45126
A5: 45127 | B5: 1354.25 | C5: 1025.09 | H5: 123 | N5: 18.5 | P5: 152 | V5: =SUM(B5:U5) -> 2672.84 | W5: 11002.6 | X5: =V5/W5 -> 0.24292804 | Y5: =A5 -> 45127
A6: 45128 | B6: 1210.47 | C6: 539.4 | F6: 448.39 | G6: 1200.6 | N6: 18.5 | S6: 109.97 | V6: =SUM(B6:U6) -> 3527.33 | W6: 14129.9 | X6: =V6/W6 -> 0.24963588 | Y6: =A6 -> 45128
A7: 45129 | B7: 1235.3 | C7: 216.94 | P7: 1155 | U7: 79.8 | V7: =SUM(B7:U7) -> 2687.04 | W7: 16643.5 | X7: =V7/W7 -> 0.16144681 | Y7: =A7 -> 45129
A8: 45130 | B8: N/A | C8: N/A | D8: N/A | E8: N/A | G8: N/A | H8: N/A | I8: N/A | J8: N/A | K8: N/A | L8: N/A | P8: N/A | Q8: N/A | R8: N/A | S8: N/A | U8: N/A | V8: 0 | X8: =V8/W8 -> #DIV/0! | Y8: =A8 -> 45130
C9: 920.19 | D9: Fermin Bellota Ham BNLs 1lb | E9: Move to SC for wine dinner | P9: =SUM(P2:P8) -> 2389
A11: Budget | B11: 13000
A12: Total Weekly Spend | B12: =SUM(B2:U8)+C9 -> 20720.95
A13: Remaing Spend | B13: =SUM(B11-B12) -> -7720.95
A15: Weekly Food Revenue | B15: =SUM(W2:W8) -> 67305
A16: Weekly Cost % | B16: =B12/B15 -> 0.30786643
A19: End of week status
A20: list items over $100
A21: Items carrying over | B21: Amount | C21: notes | D21: Expected use date
A22: Hamachi Collars
A23: Bellota Ham BNLS
A24: Short ribs
A25: Duck Legs
A26: Salmon Glory Bay
A27: Ribeye CHOICE | B27: 512.83 | C27: Aging 60 days

Sheet Roister (724-730)
B1: CW | C1: Fortune | D1: Closed Loop | E1: A1 Firewood | F1: Wabash/Allen | G1: Superior | H1: Aya | I1: Rocker Bros | J1: D'artagnan | K1: Four Star | L1: Regalis | M1: Murphy | N1: D'amatos | O1: Honey | P1: Cornille | Q1: Murphy | R1: Truffles | S1: Rare Tea Cellar | T1: Steve's | U1: Beca | V1: Turano | W1: Daily Spend | X1: Daily Revenue | Y1: Daily Cost %
A2: 45131 | C2: 1409.98 | K2: 168 | L2: 216 | T2: 109.97 | W2: =SUM(B2:V2) -> 1903.95 | X2: 7897 | Y2: =W2/X2 -> 0.24109789 | Z2: =A2 -> 45131
A3: 45132 | B3: 670.74 | C3: 281.18 | V3: 179.96 | W3: =SUM(B3:V3) -> 1131.88 | X3: 6146.8 | Y3: =W3/X3 -> 0.18414134 | Z3: =A3 -> 45132
A4: 45133 | B4: 86.44 | C4: 517.8 | G4: 748.8 | H4: 42 | N4: 18.5 | T4: 109.97 | W4: =SUM(B4:V4) -> 1523.51 | X4: 9076.5 | Y4: =W4/X4 -> 0.16785215 | Z4: =A4 -> 45133
A5: 45134 | B5: 1648.85 | C5: 1348.06 | E5: 280 | F5: 561.33 | G5: 908.1 | H5: 123 | M5: 249 | N5: 18.5 | W5: =SUM(B5:V5) -> 5136.84 | X5: 10504 | Y5: =W5/X5 -> 0.48903656 | Z5: =A5 -> 45134
A6: 45135 | B6: 1018.25 | C6: 841.85 | N6: 18.5 | S6: 44.5 | T6: 109.97 | W6: =SUM(B6:V6) -> 2033.07 | X6: 11974.5 | Y6: =W6/X6 -> 0.16978329 | Z6: =A6 -> 45135
A7: 45136 | B7: 1969.89 | C7: 1433.2 | V7: 89.67 | W7: =SUM(B7:V7) -> 3492.76 | X7: 15731.6 | Y7: =W7/X7 -> 0.22202192 | Z7: =A7 -> 45136
A8: 45137 | B8: N/A | C8: N/A | D8: N/A | E8: N/A | G8: N/A | H8: N/A | I8: N/A | J8: N/A | K8: N/A | L8: N/A | P8: N/A | R8: N/A | S8: N/A | T8: N/A | V8: N/A | W8: 0 | X8: 9796.2 | Y8: =W8/X8 -> 0 | Z8: =A8 -> 45137
A11: Budget | B11: 13000
A12: Total Weekly Spend | B12: =SUM(B2:V8)+C9 -> 15222.01
A13: Remaing Spend | B13: =SUM(B11-B12) -> -2222.01
A15: Weekly Food Revenue | B15: =SUM(X2:X8) -> 71126.6
A16: Weekly Cost % | B16: =B12/B15 -> 0.2140129
A19: End of week status
A20: list items over $100
A21: Items carrying over | B21: Amount | C21: notes | D21: Expected use date
A22: Hamachi Collars
A23: Bellota Ham BNLS
A24: Short ribs
A25: Duck Legs
A26: Salmon Glory Bay
A27: Ribeye CHOICE | B27: 512.83 | C27: Aging 60 days

Sheet Roister (731-86)
B1: CW | C1: Fortune | D1: Closed Loop | E1: A1 Firewood | F1: Wabash/Allen | G1: Superior | H1: Aya | I1: Rocker Bros | J1: D'artagnan | K1: Four Star | L1: Regalis | N1: D'amatos | O1: Honey | P1: Cornille | Q1: Murphy | R1: Truffles | S1: Rare Tea Cellar | T1: Steve's | U1: Beca | V1: Turano | W1: Daily Spend | X1: Daily Revenue | Y1: Daily Cost %
A2: 45138 | B2: 1867.46 | C2: 1137.83 | F2: 420.98 | K2: 168 | T2: 109.97 | W2: =SUM(B2:V2) -> 3704.24 | Y2: =W2/X2 -> #DIV/0! | Z2: =A2 -> 45138
A3: 45139 | B3: 937.98 | C3: 1169.95 | F3: 343.35 | G3: 554.5 | H3: 42 | V3: 179.96 | W3: =SUM(B3:V3) -> 3227.74 | Y3: =W3/X3 -> #DIV/0! | Z3: =A3 -> 45139
A4: 45140 | B4: 1266.33 | C4: 1063.23 | F4: 359.15 | N4: 18.5 | Q4: 213 | T4: 109.97 | W4: =SUM(B4:V4) -> 3030.18 | Y4: =W4/X4 -> #DIV/0! | Z4: =A4 -> 45140
A5: 45141 | B5: 1046.92 | C5: 194.6 | E5: 280 | N5: 18.5 | W5: =SUM(B5:V5) -> 1540.02 | Y5: =W5/X5 -> #DIV/0! | Z5: =A5 -> 45141
A6: 45142 | B6: 902.68 | C6: 583.13 | F6: 178.71 | G6: 400.5 | H6: 123 | N6: 18.5 | T6: 109.97 | W6: =SUM(B6:V6) -> 2316.49 | Y6: =W6/X6 -> #DIV/0! | Z6: =A6 -> 45142
A7: 45143 | B7: 1743.6 | C7: 766.18 | F7: 666.32 | L7: 1083 | W7: =SUM(B7:V7) -> 4259.1 | Y7: =W7/X7 -> #DIV/0! | Z7: =A7 -> 45143
A8: 45144 | B8: N/A | C8: N/A | D8: N/A | E8: N/A | G8: N/A | H8: N/A | I8: N/A | J8: N/A | K8: N/A | L8: N/A | P8: N/A | R8: N/A | S8: N/A | T8: N/A | V8: N/A | W8: 0 | Y8: =W8/X8 -> #DIV/0! | Z8: =A8 -> 45144
A11: Budget | B11: 13000
A12: Total Weekly Spend | B12: =SUM(B2:V8)+C9 -> 18077.77
A13: Remaing Spend | B13: =SUM(B11-B12) -> -5077.77
A15: Weekly Food Revenue | B15: =SUM(X2:X8) -> 0
A16: Weekly Cost % | B16: =B12/B15 -> #DIV/0!
A19: End of week status
A20: list items over $100
A21: Items carrying over | B21: Amount | C21: notes | D21: Expected use date
A22: Hamachi Collars
A23: Bellota Ham BNLS
A24: Short ribs
A25: Duck Legs
A26: Salmon Glory Bay
A27: Ribeye CHOICE | B27: 512.83 | C27: Aging 60 days
A28: Caviar | B28: 1083 | C28: Carrying for week of 8/7

Sheet  Roister (-86)
B1: CW | C1: Fortune | D1: Closed Loop | E1: A1 Firewood | F1: Wabash/Allen | G1: Superior | H1: Aya | I1: Rocker Bros | J1: D'artagnan | K1: Four Star | L1: Regalis | N1: D'amatos | O1: Honey | P1: Cornille | Q1: Murphy | R1: Truffles | S1: Rare Tea Cellar | T1: Steve's | U1: Beca | V1: Turano | W1: Daily Spend | X1: Daily Revenue | Y1: Daily Cost %
A2: 45138 | B2: 1867.46 | C2: 1137.83 | F2: 420.98 | K2: 168 | T2: 109.97 | W2: =SUM(B2:V2) -> 3704.24 | Y2: =W2/X2 -> #DIV/0! | Z2: =A2 -> 45138
A3: 45139 | B3: 937.98 | C3: 1169.95 | F3: 343.35 | G3: 554.5 | H3: 42 | V3: 179.96 | W3: =SUM(B3:V3) -> 3227.74 | Y3: =W3/X3 -> #DIV/0! | Z3: =A3 -> 45139
A4: 45140 | B4: 1266.33 | C4: 1063.23 | F4: 359.15 | N4: 18.5 | Q4: 213 | T4: 109.97 | W4: =SUM(B4:V4) -> 3030.18 | Y4: =W4/X4 -> #DIV/0! | Z4: =A4 -> 45140
A5: 45141 | B5: 1046.92 | C5: 194.6 | E5: 280 | N5: 18.5 | W5: =SUM(B5:V5) -> 1540.02 | Y5: =W5/X5 -> #DIV/0! | Z5: =A5 -> 45141
A6: 45142 | B6: 902.68 | C6: 583.13 | F6: 178.71 | G6: 400.5 | H6: 123 | N6: 18.5 | T6: 109.97 | W6: =SUM(B6:V6) -> 2316.49 | Y6: =W6/X6 -> #DIV/0! | Z6: =A6 -> 45142
A7: 45143 | W7: =SUM(B7:V7) -> 0 | Y7: =W7/X7 -> #DIV/0! | Z7: =A7 -> 45143
A8: 45144 | B8: N/A | C8: N/A | D8: N/A | E8: N/A | G8: N/A | H8: N/A | I8: N/A | J8: N/A | K8: N/A | L8: N/A | P8: N/A | R8: N/A | S8: N/A | T8: N/A | V8: N/A | W8: 0 | Y8: =W8/X8 -> #DIV/0! | Z8: =A8 -> 45144
A11: Budget | B11: 13000
A12: Total Weekly Spend | B12: =SUM(B2:V8)+C9 -> 13818.67
A13: Remaing Spend | B13: =SUM(B11-B12) -> -818.67
A15: Weekly Food Revenue | B15: =SUM(X2:X8) -> 0
A16: Weekly Cost % | B16: =B12/B15 -> #DIV/0!
A19: End of week status
A20: list items over $100
A21: Items carrying over | B21: Amount | C21: notes | D21: Expected use date
A22: Hamachi Collars
A23: Bellota Ham BNLS
A24: Short ribs
A25: Duck Legs
A26: Salmon Glory Bay
A27: Ribeye CHOICE | B27: 512.83 | C27: Aging 60 days

Sheet  Roister (87-813)
B1: CW | C1: Fortune | D1: Closed Loop | E1: A1 Firewood | F1: Wabash/Allen | G1: Superior | H1: Aya | I1: Rocker Bros | J1: D'artagnan | K1: Four Star | L1: Regalis | N1: D'amatos | O1: Honey | P1: Cornille | Q1: Murphy | R1: Truffles | S1: Rare Tea Cellar | T1: Steve's | U1: Beca | V1: Turano | W1: Daily Spend | X1: Daily Revenue | Y1: Daily Cost %
A2: 45145 | B2: 1873.65 | C2: 447.8 | K2: 168 | T2: 109.97 | W2: =SUM(B2:V2) -> 2599.42 | Y2: =W2/X2 -> #DIV/0! | Z2: =A2 -> 45145
A3: 45146 | B3: 86.44 | F3: 170.3 | G3: 688.5 | H3: 42 | V3: 179.96 | W3: =SUM(B3:V3) -> 1167.2 | Y3: =W3/X3 -> #DIV/0! | Z3: =A3 -> 45146
A4: 45147 | B4: 1840.11 | C4: 919.09 | N4: 18.5 | Q4: 243 | T4: 109.97 | W4: =SUM(B4:V4) -> 3130.67 | Y4: =W4/X4 -> #DIV/0! | Z4: =A4 -> 45147
A5: 45148 | B5: 1689.85 | C5: 1420.19 | E5: 280 | N5: 18.5 | W5: =SUM(B5:V5) -> 3408.54 | Y5: =W5/X5 -> #DIV/0! | Z5: =A5 -> 45148
A6: 45149 | B6: 2263.55 | C6: 566.28 | F6: 858.96 | G6: 365.7 | H6: 123 | N6: 18.5 | S6: 19.5 | T6: 109.97 | W6: =SUM(B6:V6) -> 4325.46 | Y6: =W6/X6 -> #DIV/0! | Z6: =A6 -> 45149
A7: 45150 | B7: 1104.62 | C7: 1090.75 | W7: =SUM(B7:V7) -> 2195.37 | Y7: =W7/X7 -> #DIV/0! | Z7: =A7 -> 45150
A8: 45151 | B8: N/A | C8: N/A | D8: N/A | E8: N/A | G8: N/A | H8: N/A | I8: N/A | J8: N/A | K8: N/A | L8: N/A | P8: N/A | R8: N/A | S8: N/A | T8: N/A | V8: N/A | W8: 0 | Y8: =W8/X8 -> #DIV/0! | Z8: =A8 -> 45151
A11: Budget | B11: 13000
A12: Total Weekly Spend | B12: =SUM(B2:V8)+C9 -> 16826.66
A13: Remaing Spend | B13: =SUM(B11-B12) -> -3826.66
A15: Weekly Food Revenue | B15: =SUM(X2:X8) -> 0
A16: Weekly Cost % | B16: =B12/B15 -> #DIV/0!
A19: End of week status
A20: list items over $100
A21: Items carrying over | B21: Amount | C21: notes | D21: Expected use date
A22: Hamachi Collars
A23: Bellota Ham BNLS
A24: Short ribs | B24: 2243.86 | D24: 8/14-8/20
A25: Duck Legs
A26: Salmon Glory Bay
A27: Ribeye CHOICE | B27: 512.83 | C27: Aging 60 days

Sheet Roister (814-820)
B1: CW | C1: Fortune | D1: Closed Loop | E1: A1 Firewood | F1: Wabash/Allen | G1: Superior | H1: Aya | I1: Rocker Bros | J1: D'artagnan | K1: Four Star | L1: Regalis | M1: D'amatos | N1: Honey | O1: Cornille | P1: Murphy | Q1: Truffles | R1: Rare Tea Cellar | S1: Steve's | T1: Beca | U1: Turano | V1: Daily Spend | W1: Daily Revenue | X1: Daily Cost %
A2: 45152 | B2: 1709.87 | C2: 453.8 | F2: 727.48 | K2: 168 | S2: 109.97 | V2: =SUM(B2:U2) -> 3169.12 | W2: 9253.9 | X2: =V2/W2 -> 0.34246318 | Y2: =A2 -> 45152
A3: 45153 | B3: 727.46 | C3: 1210.46 | F3: 463.84 | G3: 619.5 | H3: 42 | O3: 753 | V3: =SUM(B3:U3) -> 3816.26 | W3: 6563.5 | X3: =V3/W3 -> 0.58143673 | Y3: =A3 -> 45153
A4: 45154 | B4: 1136.12 | C4: 453.8 | M4: 18.5 | S4: 109.97 | V4: =SUM(B4:U4) -> 1718.39 | W4: 8880.5 | X4: =V4/W4 -> 0.19350149 | Y4: =A4 -> 45154
A5: 45155 | B5: 1742.36 | C5: 480.46 | E5: 280 | F5: 526.84 | G5: 718.5 | H5: 123 | M5: 18.5 | V5: =SUM(B5:U5) -> 3889.66 | W5: 7415 | X5: =V5/W5 -> 0.52456642 | Y5: =A5 -> 45155
A6: 45156 | B6: 2274.27 | C6: 526.69 | D6: 450 | F6: 1461.65 | M6: 18.5 | P6: 137 | S6: 109.97 | V6: =SUM(B6:U6) -> 4978.08 | W6: 14252.5 | X6: =V6/W6 -> 0.34927767 | Y6: =A6 -> 45156
A7: 45157 | B7: 896.24 | C7: 263 | P7: 50 | U7: 66.9 | V7: =SUM(B7:U7) -> 1276.14 | W7: 15355.3 | X7: =V7/W7 -> 0.083107461 | Y7: =A7 -> 45157
A8: 45158 | B8: N/A | C8: N/A | D8: N/A | E8: N/A | G8: N/A | H8: N/A | I8: N/A | J8: N/A | K8: N/A | L8: N/A | O8: N/A | Q8: N/A | R8: N/A | S8: N/A | U8: N/A | V8: 0 | X8: =V8/W8 -> #DIV/0! | Y8: =A8 -> 45158
A11: Budget | B11: 13000
A12: Total Weekly Spend | B12: =SUM(B2:U8)+C9 -> 18847.65
A13: Remaing Spend | B13: =SUM(B11-B12) -> -5847.65
A15: Weekly Food Revenue | B15: =SUM(W2:W8) -> 61720.7
A16: Weekly Cost % | B16: =B12/B15 -> 0.30537
A19: End of week status
A20: list items over $100
A21: Items carrying over | B21: Amount | C21: notes | D21: Expected use date
A22: Hamachi Collars
A23: Bellota Ham BNLS
A24: Short ribs
A25: Duck Legs
A26: Salmon Glory Bay
A27: Ribeye CHOICE

Sheet Roister (821-827)
B1: CW | C1: Fortune | D1: Closed Loop | E1: A1 Firewood | F1: Wabash/Allen | G1: Superior | H1: Aya | I1: Rocker Bros | J1: D'artagnan | K1: Four Star | L1: Regalis | M1: D'amatos | N1: Honey | O1: Cornille | P1: Murphy | Q1: Truffles | R1: Rare Tea Cellar | S1: Steve's | T1: Beca | U1: Turano | V1: Daily Spend | W1: Daily Revenue | X1: Daily Cost %
A2: 45159 | B2: 2439.17 | C2: 1358.79 | F2: 699.42 | K2: 168 | L2: 72 | S2: 109.97 | T2: 304.5 | V2: =SUM(B2:U2) -> 5151.85 | W2: 5460 | X2: =V2/W2 -> 0.94356227 | Y2: =A2 -> 45159
A3: 45160 | B3: 1043.13 | C3: 784.34 | G3: 507.6 | H3: 42 | L3: 108 | U3: 179.96 | V3: =SUM(B3:U3) -> 2665.03 | W3: 27577.25 | X3: =V3/W3 -> 0.096638715 | Y3: =A3 -> 45160
A4: 45161 | B4: 1752.22 | C4: 192.38 | F4: 307.15 | M4: 18.5 | S4: 109.97 | V4: =SUM(B4:U4) -> 2380.22 | W4: 7337 | X4: =V4/W4 -> 0.32441325 | Y4: =A4 -> 45161
A5: 45162 | B5: 948.52 | C5: 453.8 | E5: 280 | L5: 950 | M5: 18.5 | R5: 25 | V5: =SUM(B5:U5) -> 2675.82 | W5: 5501 | X5: =V5/W5 -> 0.48642429 | Y5: =A5 -> 45162
A6: 45163 | B6: 1105.78 | C6: 179.8 | G6: 1007 | H6: 123 | M6: 18.5 | R6: 77 | S6: 109.97 | V6: =SUM(B6:U6) -> 2621.05 | W6: 13262 | X6: =V6/W6 -> 0.1976361 | Y6: =A6 -> 45163
A7: 45164 | B7: 912.79 | C7: 263 | U7: 86.25 | V7: =SUM(B7:U7) -> 1262.04 | W7: 18215.5 | X7: =V7/W7 -> 0.069283852 | Y7: =A7 -> 45164
A8: 45165 | B8: N/A | C8: N/A | D8: N/A | E8: N/A | G8: N/A | H8: N/A | I8: N/A | J8: N/A | K8: N/A | L8: N/A | O8: N/A | Q8: N/A | R8: N/A | S8: N/A | U8: N/A | V8: 0 | W8: 6643.2 | X8: =V8/W8 -> 0 | Y8: =A8 -> 45165
A11: Budget | B11: 13000
A12: Total Weekly Spend | B12: =SUM(B2:U8)+C9 -> 16756.01
A13: Remaing Spend | B13: =SUM(B11-B12) -> -3756.01
A15: Weekly Food Revenue | B15: =SUM(W2:W8) -> 83995.95
A16: Weekly Cost % | B16: =B12/B15 -> 0.19948593
A19: End of week status
A20: list items over $100
A21: Items carrying over | B21: Amount | C21: notes | D21: Expected use date
A22: Hamachi Collars
A23: Bellota Ham BNLS
A24: Short ribs
A25: Duck Legs
A26: Salmon Glory Bay
A27: Caviar | B27: 1082.05 | C27: from 8/21-9/3 | D27: 2 weeks worth

Sheet Roister (828-93)
B1: CW | C1: Fortune | D1: Closed Loop | E1: A1 Firewood | F1: Wabash/Allen | G1: Superior | H1: Aya | I1: Rocker Bros | J1: D'artagnan | K1: Four Star | L1: Regalis | N1: D'amatos | O1: Honey | P1: Cornille | Q1: Murphy | R1: Truffles | S1: Rare Tea Cellar | T1: Steve's | U1: Beca | V1: Turano | W1: Daily Spend | X1: Daily Revenue | Y1: Daily Cost %
A2: 45166 | B2: 1155.03 | C2: 555.81 | F2: 521.94 | T2: 109.97 | V2: 20.1 | W2: =SUM(B2:V2) -> 2362.85 | X2: 3238 | Y2: =W2/X2 -> 0.72972514 | Z2: =A2 -> 45166
A3: 45167 | B3: 738.43 | F3: 266.42 | H3: 42 | V3: 179.96 | W3: =SUM(B3:V3) -> 1226.81 | X3: 5005.5 | Y3: =W3/X3 -> 0.2450924 | Z3: =A3 -> 45167
A4: 45168 | B4: 503.93 | C4: 1136.39 | N4: 18.5 | T4: 109.97 | W4: =SUM(B4:V4) -> 1768.79 | X4: 6469.7 | Y4: =W4/X4 -> 0.27339598 | Z4: =A4 -> 45168
A5: 45169 | B5: 1436.25 | C5: 402.36 | E5: 180 | N5: 18.5 | W5: =SUM(B5:V5) -> 2037.11 | X5: 7747.2 | Y5: =W5/X5 -> 0.2629479 | Z5: =A5 -> 45169
A6: 45170 | B6: 1891.25 | F6: 575.52 | G6: 718.5 | H6: 123 | N6: 18.5 | Q6: 50 | T6: 109.97 | W6: =SUM(B6:V6) -> 3486.74 | X6: 10548.5 | Y6: =W6/X6 -> 0.33054368 | Z6: =A6 -> 45170
A7: 45171 | B7: 1443.99 | C7: 358.32 | F7: 99.15 | K7: 84 | W7: =SUM(B7:V7) -> 1985.46 | X7: 15950.79 | Y7: =W7/X7 -> 0.12447409 | Z7: =A7 -> 45171
A8: 45172 | B8: N/A | C8: N/A | D8: N/A | E8: N/A | G8: N/A | H8: N/A | I8: N/A | J8: N/A | K8: N/A | L8: N/A | P8: N/A | R8: N/A | S8: N/A | T8: N/A | V8: N/A | W8: 0 | X8: 13814.5 | Y8: =W8/X8 -> 0 | Z8: =A8 -> 45172
A11: Budget | B11: 13000
A12: Total Weekly Spend | B12: =SUM(B2:V8)+C9 -> 12867.76
A13: Remaing Spend | B13: =SUM(B11-B12) -> 132.24
A15: Weekly Food Revenue | B15: =SUM(X2:X8) -> 62774.19
A16: Weekly Cost % | B16: =B12/B15 -> 0.20498488
A19: End of week status
A20: list items over $100
A21: Items carrying over | B21: Amount | C21: notes | D21: Expected use date
A22: Hamachi Collars
A23: Bellota Ham BNLS
A24: Short ribs | B24: 2243.86 | C24: ADD? For this week
A25: Duck Legs
A26: Salmon Glory Bay
A27: Ribeye CHOICE

Sheet Roister (94-910)
B1: CW | C1: Fortune | D1: Closed Loop | E1: A1 Firewood | F1: Wabash/Allen | G1: Superior | H1: Aya | I1: Rocker Bros | J1: D'artagnan | K1: Four Star | L1: Regalis | N1: D'amatos | O1: Honey | P1: Cornille | Q1: Murphy | R1: Truffles | S1: Rare Tea Cellar | T1: Steve's | U1: Beca | V1: Turano | W1: Daily Spend | X1: Daily Revenue | Y1: Daily Cost %
A2: 45173 | K2: 84 | T2: 109.97 | W2: =SUM(B2:V2) -> 193.97 | X2: 4430.8 | Y2: =W2/X2 -> 0.043777647 | Z2: =A2 -> 45173
A3: 45174 | B3: 2813.54 | C3: 926.51 | F3: 638.89 | G3: 198 | H3: 42 | W3: =SUM(B3:V3) -> 4618.94 | X3: 6820 | Y3: =W3/X3 -> 0.67726393 | Z3: =A3 -> 45174
A4: 45175 | B4: 984.72 | C4: 1018.16 | N4: 18.5 | T4: 109.97 | W4: =SUM(B4:V4) -> 2131.35 | X4: 7004.5 | Y4: =W4/X4 -> 0.30428296 | Z4: =A4 -> 45175
A5: 45176 | B5: 1789.79 | C5: 303.83 | E5: 180 | H5: 123 | N5: 18.5 | W5: =SUM(B5:V5) -> 2415.12 | X5: 7105.2 | Y5: =W5/X5 -> 0.3399088 | Z5: =A5 -> 45176
A6: 45177 | B6: 998.84 | C6: 604.38 | F6: 526.99 | G6: 336.75 | N6: 18.5 | T6: 109.97 | W6: =SUM(B6:V6) -> 2595.43 | X6: 11768.5 | Y6: =W6/X6 -> 0.22054043 | Z6: =A6 -> 45177
A7: 45178 | B7: 1078.9 | C7: 472.7 | K7: 84 | L7: 36 | V7: 73.35 | W7: =SUM(B7:V7) -> 1744.95 | X7: 15021.5 | Y7: =W7/X7 -> 0.1161635 | Z7: =A7 -> 45178
A8: 45179 | B8: N/A | C8: N/A | D8: N/A | E8: N/A | G8: N/A | H8: N/A | I8: N/A | J8: N/A | K8: N/A | L8: N/A | P8: N/A | R8: N/A | S8: N/A | T8: N/A | V8: N/A | W8: 0 | X8: 2718 | Y8: =W8/X8 -> 0 | Z8: =A8 -> 45179
A11: Budget | B11: 13000
A12: Total Weekly Spend | B12: =SUM(B2:V8)+C9 -> 13699.76
A13: Remaing Spend | B13: =SUM(B11-B12) -> -699.76
A15: Weekly Food Revenue | B15: =SUM(X2:X8) -> 54868.5
A16: Weekly Cost % | B16: =B12/B15 -> 0.24968352
A19: End of week status
A20: list items over $100
A21: Items carrying over | B21: Amount | C21: notes | D21: Expected use date
A22: Hamachi Collars
A23: Bellota Ham BNLS
A24: Short ribs
A25: Duck Legs
A26: Salmon Glory Bay
A27: Ribeye CHOICE

Sheet Roister (911-917)
B1: CW | C1: Fortune | D1: Closed Loop | E1: A1 Firewood | F1: Wabash/Allen | G1: Superior | H1: Aya | I1: Rocker Bros | J1: D'artagnan | K1: Four Star | L1: Regalis | M1: D'amatos | N1: Honey | O1: Cornille | P1: Murphy | Q1: Truffles | R1: Rare Tea Cellar | S1: Steve's | T1: Beca | U1: Turano | V1: Daily Spend | W1: Daily Revenue | X1: Daily Cost %
A2: 45180 | B2: 1007.94 | C2: 453.8 | F2: 448.6 | K2: 168 | L2: 1102 | N2: 252 | S2: 109.97 | V2: =SUM(B2:U2) -> 3542.31 | W2: 12450 | X2: =V2/W2 -> 0.28452289 | Y2: =A2 -> 45180
A3: 45181 | B3: 1724.77 | G3: 507.6 | H3: 42 | P3: 188 | U3: 179.96 | V3: =SUM(B3:U3) -> 2642.33 | W3: 17143.5 | X3: =V3/W3 -> 0.15413014 | Y3: =A3 -> 45181
A4: 45182 | B4: 573.97 | C4: 185 | F4: 263.77 | M4: 18.5 | S4: 109.97 | V4: =SUM(B4:U4) -> 1151.21 | W4: 6196.6 | X4: =V4/W4 -> 0.18578091 | Y4: =A4 -> 45182
A5: 45183 | B5: 1029.94 | C5: 772.92 | E5: 280 | F5: 171.64 | H5: 123 | M5: 18.5 | V5: =SUM(B5:U5) -> 2396 | W5: 8182.6 | X5: =V5/W5 -> 0.29281646 | Y5: =A5 -> 45183
A6: 45184 | B6: 673.74 | F6: 1187.01 | G6: 350.7 | M6: 18.5 | S6: 109.97 | V6: =SUM(B6:U6) -> 2339.92 | W6: 9886.5 | X6: =V6/W6 -> 0.2366783 | Y6: =A6 -> 45184
A7: 45185 | B7: 651.05 | C7: 142.68 | F7: 185.79 | K7: 84 | U7: 54.78 | V7: =SUM(B7:U7) -> 1118.3 | W7: 13984.6 | X7: =V7/W7 -> 0.079966535 | Y7: =A7 -> 45185
A8: 45186 | B8: N/A | C8: N/A | D8: N/A | E8: N/A | G8: N/A | H8: N/A | I8: N/A | J8: N/A | K8: N/A | L8: N/A | O8: N/A | Q8: N/A | R8: N/A | S8: N/A | U8: N/A | V8: 0 | W8: 8047.2 | X8: =V8/W8 -> 0 | Y8: =A8 -> 45186
A11: Budget | B11: 13000
A12: Total Weekly Spend | B12: =SUM(B2:U8)+C9 -> 13190.07
A13: Remaing Spend | B13: =SUM(B11-B12) -> -190.07
A15: Weekly Food Revenue | B15: =SUM(W2:W8) -> 75891
A16: Weekly Cost % | B16: =B12/B15 -> 0.17380282
A19: End of week status
A20: list items over $100
A21: Items carrying over | B21: Amount | C21: notes | D21: Expected use date
A22: Hamachi Collars
A23: Bellota Ham BNLS
A24: Short ribs
A25: Duck Legs
A26: Salmon Glory Bay
A27: Ribeye CHOICE

Sheet Roister (918-924)
B1: CW | C1: Fortune | D1: Closed Loop | E1: A1 Firewood | F1: Wabash/Allen | G1: Superior | H1: Aya | I1: Rocker Bros | J1: D'artagnan | K1: Four Star | L1: Regalis | M1: D'amatos | N1: Honey | O1: Cornille | P1: Murphy | Q1: Beca | R1: Rare Tea Cellar | S1: Steve's | T1: MushroomM | U1: Turano | V1: Daily Spend | W1: Daily Revenue | X1: Daily Cost %
A2: 45187 | B2: 1133.84 | C2: 348.4 | F2: 911.6 | K2: 168 | P2: 137 | Q2: 245 | R2: 198 | S2: 57.05 | V2: =SUM(B2:U2) -> 3198.89 | W2: 9048.42 | X2: =V2/W2 -> 0.35353023 | Y2: =A2 -> 45187
A3: 45188 | B3: 1662.92 | C3: 285.3 | G3: 865.04 | H3: 42 | T3: 132 | U3: 179.96 | V3: =SUM(B3:U3) -> 3167.22 | W3: 8908.8 | X3: =V3/W3 -> 0.35551589 | Y3: =A3 -> 45188
A4: 45189 | B4: 406.03 | C4: 68.29 | M4: 18.5 | S4: 57.05 | V4: =SUM(B4:U4) -> 549.87 | W4: 20539.05 | X4: =V4/W4 -> 0.02677193 | Y4: =A4 -> 45189
A5: 45190 | B5: 858.86 | C5: 453.8 | D5: 197 | E5: 280 | H5: 123 | M5: 18.5 | V5: =SUM(B5:U5) -> 1931.16 | W5: 7633 | X5: =V5/W5 -> 0.25300144 | Y5: =A5 -> 45190
A6: 45191 | B6: 1712.12 | C6: 1179.58 | F6: 595.83 | L6: 104.72 | M6: 18.5 | S6: 57.05 | V6: =SUM(B6:U6) -> 3667.8 | W6: 16895 | X6: =V6/W6 -> 0.21709381 | Y6: =A6 -> 45191
A7: 45192 | B7: 1390.56 | C7: 635.5 | P7: 168 | V7: =SUM(B7:U7) -> 2194.06 | W7: 15413.5 | X7: =V7/W7 -> 0.14234664 | Y7: =A7 -> 45192
A8: 45193 | B8: N/A | C8: N/A | D8: N/A | E8: N/A | G8: N/A | H8: N/A | I8: N/A | J8: N/A | K8: N/A | L8: N/A | O8: N/A | Q8: N/A | R8: N/A | S8: N/A | U8: N/A | V8: 0 | X8: =V8/W8 -> #DIV/0! | Y8: =A8 -> 45193
A11: Budget | B11: 13000
A12: Total Weekly Spend | B12: =SUM(B2:U8)+C9 -> 14709
A13: Remaing Spend | B13: =SUM(B11-B12) -> -1709
A15: Weekly Food Revenue | B15: =SUM(W2:W8) -> 78437.77
A16: Weekly Cost % | B16: =B12/B15 -> 0.18752445
A19: End of week status
A20: list items over $100
A21: Items carrying over | B21: Amount | C21: notes | D21: Expected use date
A22: Hamachi Collars
A23: Bellota Ham BNLS
A24: Short ribs
A25: Duck Legs
A26: Salmon Glory Bay
A27: Ribeye CHOICE

Sheet Roister (925-101)
B1: CW | C1: Fortune | D1: Closed Loop | E1: A1 Firewood | F1: Wabash/Allen | G1: Superior | H1: Aya | I1: Rocker Bros | J1: D'artagnan | K1: Four Star | L1: Regalis | M1: D'amatos | N1: Honey | O1: Cornille | P1: Murphy | Q1: Truffles | R1: Rare Tea Cellar | S1: Steve's | T1: Beca | U1: Turano | V1: Daily Spend | W1: Daily Revenue | X1: Daily Cost %
A2: 45194 | B2: 1300.52 | C2: 1736.75 | K2: 168 | S2: 57.05 | V2: =SUM(B2:U2) -> 3262.32 | W2: 4108.5 | X2: =V2/W2 -> 0.79404162 | Y2: =A2 -> 45194
A3: 45195 | B3: 1080.25 | C3: 249.2 | F3: 403.72 | H3: 42 | V3: =SUM(B3:U3) -> 1775.17 | W3: 7696.4 | X3: =V3/W3 -> 0.23064939 | Y3: =A3 -> 45195
A4: 45196 | B4: 982.93 | C4: 529.6 | G4: 396 | K4: 168 | L4: 1017 | M4: 18.5 | N4: 252 | S4: 57.05 | V4: =SUM(B4:U4) -> 3421.08 | W4: 6500.4 | X4: =V4/W4 -> 0.52628761 | Y4: =A4 -> 45196
A5: 45197 | B5: 992.68 | C5: 807.16 | E5: 180 | G5: 198 | H5: 123 | M5: 18.5 | R5: 86.4 | U5: 24.34 | V5: =SUM(B5:U5) -> 2430.08 | W5: 27718.3 | X5: =V5/W5 -> 0.0876706 | Y5: =A5 -> 45197
A6: 45198 | B6: 1446.72 | C6: 137.74 | F6: 415.7 | M6: 18.5 | S6: 57.05 | V6: =SUM(B6:U6) -> 2075.71 | W6: 11966.89 | X6: =V6/W6 -> 0.17345442 | Y6: =A6 -> 45198
A7: 45199 | B7: 1794.79 | C7: 293.41 | V7: =SUM(B7:U7) -> 2088.2 | W7: 17788.3 | X7: =V7/W7 -> 0.11739177 | Y7: =A7 -> 45199
A8: 45170 | B8: N/A | C8: N/A | D8: N/A | E8: N/A | G8: N/A | H8: N/A | I8: N/A | J8: N/A | K8: N/A | L8: N/A | O8: N/A | Q8: N/A | R8: N/A | S8: N/A | U8: N/A | V8: 0 | W8: 9640.6 | X8: =V8/W8 -> 0 | Y8: =A8 -> 45170
A11: Budget | B11: 13000
A12: Total Weekly Spend | B12: =SUM(B2:U8)+C9 -> 15052.56
A13: Remaing Spend | B13: =SUM(B11-B12) -> -2052.56
A15: Weekly Food Revenue | B15: =SUM(W2:W8) -> 85419.39
A16: Weekly Cost % | B16: =B12/B15 -> 0.17621947
A19: End of week status
A20: list items over $100
A21: Items carrying over | B21: Amount | C21: notes | D21: Expected use date
A22: Hamachi Collars
A23: Bellota Ham BNLS | B23: 1108.18 | C23: from 10/01 | D23: until 10/15-10/18
A24: Short ribs
A25: Duck Legs
A26: Salmon Glory Bay
A27: Ribeye CHOICE

Sheet Roister (102-108)
B1: CW | C1: Fortune | D1: Closed Loop | E1: A1 Firewood | F1: Wabash/Allen | G1: Superior | H1: Aya | I1: Rocker Bros | J1: D'artagnan | K1: Four Star | L1: Regalis | M1: D'amatos | N1: Honey | O1: Cornille | P1: Murphy | Q1: Truffles | R1: Rare Tea Cellar | S1: Steve's | T1: Beca | U1: Turano | V1: Daily Spend | W1: Daily Revenue | X1: Daily Cost %
A2: 45201 | B2: 1397.34 | C2: 569.8 | F2: 758.52 | K2: 168 | S2: 57.05 | V2: =SUM(B2:U2) -> 2950.71 | W2: 4822.01 | X2: =V2/W2 -> 0.61192532 | Y2: =A2 -> 45201
A3: 45202 | B3: 1177.81 | C3: 407.09 | F3: 637.9 | H3: 42 | K3: 168 | R3: 219.75 | V3: =SUM(B3:U3) -> 2652.55 | W3: 7630 | X3: =V3/W3 -> 0.34764744 | Y3: =A3 -> 45202
A4: 45203 | B4: 1804.7 | C4: 460.8 | G4: 399 | M4: 18.5 | S4: 57.05 | V4: =SUM(B4:U4) -> 2740.05 | W4: 14313.5 | X4: =V4/W4 -> 0.19143117 | Y4: =A4 -> 45203
A5: 45204 | B5: 1024.89 | C5: 282.76 | E5: 180 | H5: 123 | M5: 18.5 | V5: =SUM(B5:U5) -> 1629.15 | W5: 8693.41 | X5: =V5/W5 -> 0.18740057 | Y5: =A5 -> 45204
A6: 45205 | B6: 2536.18 | C6: 532.49 | F6: 551.55 | G6: 680.02 | M6: 18.5 | S6: 57.05 | V6: =SUM(B6:U6) -> 4375.79 | W6: 10999 | X6: =V6/W6 -> 0.39783526 | Y6: =A6 -> 45205
A7: 45206 | B7: 1920.43 | C7: 64.6 | Q7: 468 | V7: =SUM(B7:U7) -> 2453.03 | W7: 11610 | X7: =V7/W7 -> 0.21128596 | Y7: =A7 -> 45206
A8: 45207 | B8: N/A | C8: N/A | D8: N/A | E8: N/A | G8: N/A | H8: N/A | I8: N/A | J8: N/A | K8: N/A | L8: N/A | O8: N/A | Q8: N/A | R8: N/A | S8: N/A | U8: N/A | V8: 0 | W8: 9723.5 | X8: =V8/W8 -> 0 | Y8: =A8 -> 45207
A11: Budget | B11: 13000
A12: Total Weekly Spend | B12: =SUM(B2:U8)+C9 -> 16801.28
A13: Remaing Spend | B13: =SUM(B11-B12) -> -3801.28
A15: Weekly Food Revenue | B15: =SUM(W2:W8) -> 67791.42
A16: Weekly Cost % | B16: =B12/B15 -> 0.24783785
A19: End of week status
A20: list items over $100
A21: Items carrying over | B21: Amount | C21: notes | D21: Expected use date
A22: Hamachi Collars
A23: Bellota Ham BNLS
A24: Short ribs | B24: 637.8 | D24: by the end of week 10/9
A25: Duck Legs
A26: Salmon Glory Bay
A27: Ribeye CHOICE

Sheet Roister (109-1015)
B1: CW | C1: Fortune | D1: Closed Loop | E1: A1 Firewood | F1: Wabash/Allen | G1: Superior | H1: Aya | I1: Rocker Bros | J1: D'artagnan | K1: Four Star | L1: Regalis | M1: D'amatos | N1: Honey | O1: Cornille | P1: Murphy | Q1: Truffles | R1: Rare Tea Cellar | S1: Steve's | T1: Beca | U1: Turano | V1: Daily Spend | W1: Daily Revenue | X1: Daily Cost %
A2: 45208 | B2: 1091.36 | C2: 1721.18 | F2: 181.31 | K2: 168 | L2: 1121.29 | S2: 57.05 | V2: =SUM(B2:U2) -> 4340.19 | X2: =V2/W2 -> #DIV/0! | Y2: =A2 -> 45208
A3: 45209 | B3: 673.95 | H3: 42 | V3: =SUM(B3:U3) -> 715.95 | X3: =V3/W3 -> #DIV/0! | Y3: =A3 -> 45209
A4: 45210 | B4: 2388.45 | G4: 549.02 | M4: 18.5 | S4: 57.05 | V4: =SUM(B4:U4) -> 3013.02 | X4: =V4/W4 -> #DIV/0! | Y4: =A4 -> 45210
A5: 45211 | B5: 1119.21 | C5: 605.5 | E5: 180 | H5: 123 | M5: 18.5 | V5: =SUM(B5:U5) -> 2046.21 | X5: =V5/W5 -> #DIV/0! | Y5: =A5 -> 45211
A6: 45212 | B6: 1552.88 | C6: 517.17 | F6: 574.95 | G6: 396 | M6: 18.5 | S6: 57.05 | V6: =SUM(B6:U6) -> 3116.55 | X6: =V6/W6 -> #DIV/0! | Y6: =A6 -> 45212
A7: 45213 | B7: 1617.9 | C7: 332.4 | F7: 221.91 | K7: 84 | V7: =SUM(B7:U7) -> 2256.21 | X7: =V7/W7 -> #DIV/0! | Y7: =A7 -> 45213
A8: 45214 | B8: N/A | C8: N/A | D8: N/A | E8: N/A | G8: N/A | H8: N/A | I8: N/A | J8: N/A | K8: N/A | L8: N/A | O8: N/A | Q8: N/A | R8: N/A | S8: N/A | U8: N/A | V8: 0 | X8: =V8/W8 -> #DIV/0! | Y8: =A8 -> 45214
A11: Budget | B11: 13000
A12: Total Weekly Spend | B12: =SUM(B2:U8)+C9 -> 15488.13
A13: Remaing Spend | B13: =SUM(B11-B12) -> -2488.13
A15: Weekly Food Revenue | B15: =SUM(W2:W8) -> 0
A16: Weekly Cost % | B16: =B12/B15 -> #DIV/0!
A19: End of week status
A20: list items over $100
A21: Items carrying over | B21: Amount | C21: notes | D21: Expected use date
A22: Hamachi Collars
A23: Bellota Ham BNLS
A24: Short ribs | B24: 1637.85 | D24: 10/23-10/30
A25: Duck Legs
A26: Salmon Glory Bay
A27: Ribeye CHOICE
A28: White Truffle | B28: 838.86 | D28: 10/16-10/23

Sheet Roister (1016-1022)
B1: CW | C1: Fortune | D1: Closed Loop | E1: A1 Firewood | F1: Wabash/Allen | G1: Superior | H1: Aya | I1: Rocker Bros | J1: D'artagnan | K1: Four Star | L1: Regalis | M1: D'amatos | N1: Honey | O1: Cornille | P1: Murphy | Q1: Truffles | R1: Rare Tea Cellar | S1: Steve's | T1: Beca | U1: Turano | V1: Daily Spend | W1: Daily Revenue | X1: Daily Cost %
A2: 45215 | B2: 2202.33 | C2: 856.74 | E2: 180 | F2: 593 | K2: 84 | S2: 57.05 | V2: =SUM(B2:U2) -> 3973.12 | W2: 15767.5 | X2: =V2/W2 -> 0.25198161 | Y2: =A2 -> 45215
A3: 45216 | H3: 42 | L3: 60 | V3: =SUM(B3:U3) -> 102 | W3: 22823.5 | X3: =V3/W3 -> 0.0044690779 | Y3: =A3 -> 45216
A4: 45217 | B4: 2357.58 | C4: 619.68 | G4: 715.02 | M4: 18.5 | S4: 57.05 | V4: =SUM(B4:U4) -> 3767.83 | W4: 7525 | X4: =V4/W4 -> 0.50070831 | Y4: =A4 -> 45217
A5: 45218 | B5: 1531,8 | C5: 561.3 | F5: 200.2 | H5: 123 | M5: 18.5 | V5: =SUM(B5:U5) -> 903 | W5: 10704.86 | X5: =V5/W5 -> 0.084354209 | Y5: =A5 -> 45218
A6: 45219 | B6: 1292.55 | C6: 440.71 | F6: 199.49 | G6: 1050.06 | M6: 18.5 | S6: 57.05 | V6: =SUM(B6:U6) -> 3058.36 | W6: 19723.63 | X6: =V6/W6 -> 0.15506071 | Y6: =A6 -> 45219
A7: 45220 | B7: 2301.65 | C7: 590.24 | F7: 249.4 | K7: 84 | L7: 60 | O7: 642.8 | V7: =SUM(B7:U7) -> 3928.09 | W7: 15032.9 | X7: =V7/W7 -> 0.26129955 | Y7: =A7 -> 45220
A8: 45221 | B8: N/A | C8: N/A | D8: N/A | E8: N/A | G8: N/A | H8: N/A | I8: N/A | J8: N/A | K8: N/A | L8: N/A | O8: N/A | Q8: N/A | R8: N/A | S8: N/A | U8: N/A | V8: 0 | W8: 9056.6 | X8: =V8/W8 -> 0 | Y8: =A8 -> 45221
A10: Spend per COGS | B10: 9766.76 | C10: 4714.68 | D10: 159 | E10: 180 | F10: 1305.79 | G10: 1765.08 | H10: 165 | K10: 84 | L10: 539.43 | O10: 642.8 | S10: 171.15
A12: Difference | B12: =B10-sum(B2:B7) -> 1612.65 | C12: =C10-sum(C2:C7) -> 1646.01 | D12: =D10-sum(D2:D7) -> 159 | E12: =E10-sum(E2:E7) -> 0 | F12: =F10-sum(F2:F7) -> 63.7 | G12: =G10-sum(G2:G7) -> 0 | H12: =H10-sum(H2:H7) -> 0 | I12: =I10-sum(I2:I7) -> 0 | ... U12: =U10-sum(U2:U7) -> 0
A14: Budget | B14: 13000
A15: Total Weekly Spend | B15: =SUM(B2:U8)+C9 -> 15732.4
A16: Remaing Spend | B16: =SUM(B14-B15) -> -2732.4
A18: Weekly Food Revenue | B18: =SUM(W2:W8) -> 100633.99
A19: Weekly Cost % | B19: =B15/B18 -> 0.15633287
A22: End of week status
A23: list items over $100
A24: Items carrying over | B24: Amount | C24: notes | D24: Expected use date
A25: Hamachi Collars
A26: Bellota Ham BNLS
A27: Short ribs | B27: 1637.85 | D27: 10/23-10/30
A28: Duck Legs
A29: Salmon Glory Bay
A30: Ribeye CHOICE
A31: White Truffle | B31: 838.86 | D31: 10/16-10/23

Sheet Roister (1023-1029)
B1: CW | C1: Fortune | D1: Closed Loop | E1: A1 Firewood | F1: Wabash/Allen | G1: Superior | H1: Aya | I1: Rocker Bros | J1: D'artagnan | K1: Four Star | L1: Regalis | M1: D'amatos | N1: Honey | O1: Cornille | P1: Murphy | Q1: Truffles | R1: Rare Tea Cellar | S1: Steve's | T1: Beca | U1: Turano | V1: Daily Spend | W1: Daily Revenue | X1: Daily Cost %
A2: 45222 | B2: =1174-486.56 -> 687.44 | C2: 466 | E2: 180 | F2: 433 | K2: 168 | R2: 215 | S2: 57.05 | V2: =SUM(B2:U2) -> 2206.49 | W2: 3674 | X2: =V2/W2 -> 0.60056886 | Y2: =A2 -> 45222
A3: 45223 | B3: =821+71-14.04-23.34-35.96 -> 818.66 | C3: 149 | F3: 170 | H3: 42 | V3: =SUM(B3:U3) -> 1179.66 | W3: 6732 | X3: =V3/W3 -> 0.17523173 | Y3: =A3 -> 45223
A4: 45224 | B4: =1368-63.44-140.04-15.36-13.14-57.3-36.61-19.61 -> 1022.5 | C4: 461 | F4: 899 | G4: 999 | M4: 18.5 | Q4: 838.86 | S4: 57.05 | V4: =SUM(B4:U4) -> 4295.91 | W4: =300+6577 -> 6877 | X4: =V4/W4 -> 0.62467791 | Y4: =A4 -> 45224
A5: 45225 | B5: =1767-473.16-130-11.66+194 -> 1346.18 | C5: 225 | E5: 180 | M5: 18.5 | V5: =SUM(B5:U5) -> 1769.68 | W5: =589+6601 -> 7190 | X5: =V5/W5 -> 0.24613074 | Y5: =A5 -> 45225
A6: 45226 | B6: =1135-32-8.29+54 -> 1148.71 | F6: =614 -> 614 | G6: =487-190 -> 297 | H6: 123 | M6: 18.5 | S6: 57.05 | V6: =SUM(B6:U6) -> 2258.26 | W6: =1015.5+9657 -> 10672.5 | X6: =V6/W6 -> 0.21159616 | Y6: =A6 -> 45226
A7: 45227 | B7: =2590-121.64-73.22-59.96-5.55-14.84-36.28-20.02-12.14-95.97-33.42-61.37 -> 2055.59 | C7: 1332 | D7: 187 | F7: 350.82 | K7: 84 | V7: =SUM(B7:U7) -> 4009.41 | W7: =2564+9575 -> 12139 | X7: =V7/W7 -> 0.33029162 | Y7: =A7 -> 45227
A8: 45228 | B8: N/A | C8: N/A | D8: N/A | E8: N/A | F8: N/A | G8: N/A | H8: N/A | I8: N/A | J8: N/A | K8: N/A | L8: N/A | O8: N/A | Q8: N/A | R8: N/A | S8: N/A | U8: N/A | V8: 0 | W8: 5476.2 | X8: =V8/W8 -> 0 | Y8: =A8 -> 45228
A10: Spend per COGS | B10: 7414.21 | C10: 2632.84 | D10: 187 | E10: 360 | F10: 2466.86 | G10: 1196.6 | H10: 165 | I10: 0 | J10: 0 | K10: 252 | L10: 0 | M10: 55 | N10: 0 | O10: 218.5 | P10: 0 | Q10: 838.86 | R10: 215 | S10: 114.1
A12: Difference | B12: =B10-sum(B2:B7) -> 335.13 | C12: =C10-sum(C2:C7) -> -0.16 | D12: =D10-sum(D2:D7) -> 0 | E12: =E10-sum(E2:E7) -> 0 | F12: =F10-sum(F2:F7) -> 0.04 | G12: =G10-sum(G2:G7) -> -99.4 | H12: =H10-sum(H2:H7) -> 0 | I12: =I10-sum(I2:I7) -> 0 | ... U12: =U10-sum(U2:U7) -> 0
A14: Budget | B14: 13000
A15: Total Weekly Spend | B15: =SUM(B2:U8)+C9 -> 15719.41
A16: Remaing Spend | B16: =SUM(B14-B15) -> -2719.41 | J16: 45222
J17: 62511028 | K17: 975.98
A18: Weekly Food Revenue | B18: =SUM(W2:W8) -> 52760.7 | G18: 486.56 | J18: 62511030 | K18: 214.985
A19: Weekly Cost % | B19: =B15/B18 -> 0.29793786 | G19: =+71-14.04-23.34-35.96 -> -2.34 | K19: =sum(K17:K18) -> 1190.965
G20: =-63.44-140.04-15.36-13.14-57.3-36.61-19.61 -> -345.5
G21: =-473.16-130-11.66+194 -> -420.82 | J21: 45223
A22: End of week status | G22: =-473.16-130-11.66+194 -> -420.82 | J22: 62520327 | K22: 821.13
A23: list items over $100 | G23: =-32-8.29+54 -> 13.71 | J23: 62520329 | K23: 1.61
A24: Items carrying over | B24: Amount | C24: notes | D24: Expected use date | G24: =-121.64-73.22-59.96-5.55-14.84-36.28-20.02-12.14-95.97-33.42-61.37 -> -534.41 | K24: =sum(K22:K23) -> 822.74
A25: Hamachi Collars
A26: Bellota Ham BNLS | J26: 45224
A27: Short ribs | B27: 1637.85 | D27: week of Nov 6-Nov 12 | J27: 62529112 | K27: 1032.18
A28: Duck Legs
A29: Salmon Glory Bay | J29: 45225
A30: Ribeye CHOICE | J30: 62538505 | K30: 1183.01
A31: White Truffle | J31: 62538508 | K31: 193.8
A32: Canola oil | B32: 486.56 | D32: week of oct 30-nov 05 | K32: =sum(K30:K31) -> 1376.81
J34: 45226
J35: 62549473 | K35: 1096.79 | L35: $547 of canola oil here
J36: 62549665 | K36: 53.15
K37: =sum(K35:K36) -> 1149.94
J39: 45227
J40: 62555418 | K40: 2242.93
J41: 62555424 | K41: 85.24
K42: =sum(K40:K41) -> 2328.17

Sheet Roister (1030-1105)
B1: CW | C1: Fortune | D1: Closed Loop | E1: A1 Firewood | F1: Wabash/Allen | G1: Superior | H1: Aya | I1: Rocker Bros | J1: D'artagnan | K1: Four Star | L1: Regalis | M1: D'amatos | N1: Honey | O1: Cornille | P1: Murphy | Q1: Truffles | R1: Rare Tea Cellar | S1: Steve's | T1: Beca | U1: Turano | V1: Daily Spend | W1: Daily Revenue | X1: Daily Cost %
A2: 45229 | B2: =(1080.8-63.44-32-29.42)+(471.79-68.14-111.54-26.43-24.08-17.43-49.29-36.33-75.72) -> 1018.77 | C2: =460.8+417.52+22.5-119.6 -> 781.22 | E2: 180 | J2: 1637 | K2: =468-300 -> 168 | S2: 57.05 | V2: =SUM(B2:U2) -> 3842.04 | W2: 2728.1 | X2: =V2/W2 -> 1.4083208 | Y2: =A2 -> 45229
A3: 45230 | B3: =630.15-1.76-16.61+64.95 -> 676.73 | C3: 270.47 | L3: =690-15 -> 675 | V3: =SUM(B3:U3) -> 1622.2 | W3: 2871 | X3: =V3/W3 -> 0.56502961 | Y3: =A3 -> 45230
A4: 45231 | B4: =1466.67-364.92-89.16-63.44 -> 949.15 | C4: =404.51-139.05+460.8-119.6 -> 606.66 | F4: 254.27 | G4: =998.6-567.6 -> 431 | H4: 42 | M4: 18.5 | S4: 57.05 | V4: =SUM(B4:U4) -> 2358.63 | W4: =997+8685 -> 9682 | X4: =V4/W4 -> 0.24360979 | Y4: =A4 -> 45231
A5: 45232 | B5: 486.56 | E5: 180 | M5: 18.5 | V5: =SUM(B5:U5) -> 685.06 | W5: =832+8364 -> 9196 | X5: =V5/W5 -> 0.074495433 | Y5: =A5 -> 45232
A6: 45233 | B6: =1840.68-188-12.91-11.37-58.45-39.8-40.16-39.36-46.24-24.35-23.36-25.47-18.87-33.79-28-41.49-25.98-31.3 -> 1151.78 | C6: 25 | H6: 123 | M6: 18.5 | O6: 530 | S6: 57.05 | V6: =SUM(B6:U6) -> 1905.33 | W6: 11957.5 | X6: =V6/W6 -> 0.15934184 | Y6: =A6 -> 45233
A7: 45234 | B7: =1032.65-115.22 -> 917.43 | C7: 1332 | F7: =350.23-128.37 -> 221.86 | V7: =SUM(B7:U7) -> 2471.29 | W7: 14058.6 | X7: =V7/W7 -> 0.17578493 | Y7: =A7 -> 45234
A8: 45235 | B8: N/A | C8: N/A | D8: N/A | E8: N/A | F8: N/A | G8: N/A | H8: N/A | I8: N/A | J8: N/A | K8: N/A | L8: N/A | O8: N/A | Q8: N/A | R8: N/A | S8: N/A | U8: N/A | V8: 0 | W8: 9263 | X8: =V8/W8 -> 0 | Y8: =A8 -> 45235
A10: Amounts subtracted from invoices
A11: Family | B11: =36.3+63.44+29.42+28+16.61+1.76+33.79 -> 209.32 | C11: =119.6+119.6 -> 239.2
A12: SCSC | B12: =75.72+95+364.92+12.91+115.22 -> 663.77 | C12: =139.05+11.37+58.45+39.8+40.16+39.36+46.24+24.35+25.47+18.87+41.49 -> 484.61 | F12: 128.37 | K12: 300 | L12: 15
A13: Mijenta Event | B13: =29.42+23.03+60+39.86+71.11+35.15+122.74+67.6+37.28+31.25+36.37+243.28 -> 797.09 | C13: 309.6
A14: Bar | B14: 296.91
A15: Return | B15: 89.16 | C15: =23.36+188+31.3+25.98 -> 268.64
A18: Budget | B18: 13000
A19: Total Weekly Spend | B19: =SUM(B2:U8) -> 12884.55
A20: Remaing Spend | B20: =SUM(B18-B19) -> 115.45
A22: Weekly Food Revenue | B22: =SUM(W2:W8) -> 59756.2
A23: Weekly Cost % | B23: =B19/B22 -> 0.21561863
A26: End of week status
A27: list items over $100
A28: Items carrying over | B28: Amount | C28: notes | D28: Expected use date
A29: Hamachi Collars | B29: 567.6 | D29: week of nov 6-nov 12
A30: Bellota Ham BNLS
A31: Short ribs
A32: Duck
A33: Salmon Glory Bay
A34: Ribeye CHOICE
A35: White Truffle | B35: 834.23 | D35: week of nov 6-nov 13
A36: Caviar

Sheet Roister (1106-1112)
B1: CW | C1: Fortune | D1: Closed Loop | E1: A1 Firewood | F1: Wabash/Allen | G1: Superior | H1: Aya | I1: Rocker Bros | J1: D'artagnan | K1: Four Star | L1: Regalis | M1: D'amatos | N1: Honey | O1: Cornille | P1: Murphy | Q1: Truffles | R1: Rare Tea Cellar | S1: Steve's | T1: Beca | U1: Turano | V1: Daily Spend | W1: Daily Revenue | X1: Daily Cost %
A2: 45236 | B2: =1473.84-11.24-33.83-29.29 -> 1399.48 | C2: =52.89+239.2+221.6+408.7-119.6 -> 802.79 | E2: 180 | F2: =315.84 -> 315.84 | G2: 567.6 | K2: 168 | Q2: 417.12 | S2: 57.05 | V2: =SUM(B2:U2) -> 3907.88 | W2: 4466 | X2: =V2/W2 -> 0.87502911 | Y2: =A2 -> 45236
A3: 45237 | B3: =2151.82-105.88-35.68-18.54-122.74-15.68-22.26-24.1-85.91-31.46-78.43-46.32-11.73-20.15-66.44-35.98-78.48-16.34-12.07 -> 1323.63 | C3: =777.35-150.72 -> 626.63 | F3: 181.31 | L3: =690-345 -> 345 | V3: =SUM(B3:U3) -> 2476.57 | W3: 6468 | X3: =V3/W3 -> 0.38289579 | Y3: =A3 -> 45237
A4: 45238 | B4: =1423-34-44-31.75-63 -> 1250.25 | C4: =465.8-119.6 -> 346.2 | G4: 297 | H4: 42 | M4: 18.5 | S4: 57.05 | V4: =SUM(B4:U4) -> 2011 | W4: 6210 | X4: =V4/W4 -> 0.32383253 | Y4: =A4 -> 45238
A5: 45239 | B5: =1816.31-364.92-70.28-60.24-67.66-42.11-11.24-11.68-22.55-42.48-46.24-58.51-39.8 -> 978.6 | C5: 336.52 | F5: 180 | M5: 18.5 | R5: =280.5-58 -> 222.5 | V5: =SUM(B5:U5) -> 1736.12 | W5: 8089.1 | X5: =V5/W5 -> 0.21462462 | Y5: =A5 -> 45239
A6: 45240 | B6: =1082.13-29.29-17.2-33.71-14.02-36.28-22.4-31.44 -> 897.79 | C6: =328.11-62.01 -> 266.1 | F6: =460.67-92.59 -> 368.08 | H6: 123 | M6: 18.5 | S6: 57.05 | V6: =SUM(B6:U6) -> 1730.52 | W6: 13111.5 | X6: =V6/W6 -> 0.1319849 | Y6: =A6 -> 45240
A7: 45241 | B7: =1252-50 -> 1202 | C7: =1014-360+1332 -> 1986 | F7: 173 | V7: =SUM(B7:U7) -> 3361 | W7: 15436.5 | X7: =V7/W7 -> 0.2177307 | Y7: =A7 -> 45241
A8: 45242 | B8: N/A | C8: N/A | D8: N/A | E8: N/A | F8: N/A | G8: N/A | H8: N/A | I8: N/A | J8: N/A | K8: N/A | L8: N/A | O8: N/A | Q8: N/A | R8: N/A | S8: N/A | U8: N/A | V8: 0 | W8: 7130 | X8: =V8/W8 -> 0 | Y8: =A8 -> 45242
A10: Spend per COGS | B10: 7226.51 | C10: 4924.26 | E10: 360 | F10: 800.89 | G10: 864.6 | H10: 165 | K10: 168 | L10: 345 | O10: 191 | Q10: 417.12 | R10: 222.5 | S10: 114.1
A12: Difference | B12: =B10-sum(B2:B7) -> 174.76 | C12: =C10-sum(C2:C7) -> 560.02 | D12: =D10-sum(D2:D7) -> 0 | E12: =E10-sum(E2:E7) -> 180 | F12: =F10-sum(F2:F7) -> -417.34 | G12: =G10-sum(G2:G7) -> 0 | H12: =H10-sum(H2:H7) -> 0 | I12: =I10-sum(I2:I7) -> 0 | ... U12: =U10-sum(U2:U7) -> 0
A13: Amounts subtracted from invoices
A14: Family | B14: =11.24+33.83+78.43+46.32+11.73+20.15+66.44+35.98+34+44+33.83+42.11+11.24+17.2+14.02+36.28+22.4+50 -> 609.2 | C14: =119.6+119.6 -> 239.2
A15: SCSC | B15: =18.54+122.74+15.68+22.26+24.1+85.91+31.46+364.91+70.28+60.24+33.83+11.68+22.55+42.48+46.24+58.51+39.8+29.29+78.48+16.34+12.07+31.75+63+29.29+33.71+31.45 -> 1396.59 | C15: =150.72+62.01+68.53+71.21+139.4+80.6 -> 572.47 | F15: 92.59 | K15: =144+156 -> 300
A16: Mijenta Event
A17: Bar
A18: Return | B18: =105.88+35.68 -> 141.56 | R18: 58
A21: Budget | B21: 13000
A22: Total Weekly Spend | B22: =SUM(B2:U8) -> 15223.09
A23: Remaing Spend | B23: =SUM(B21-B22) -> -2223.09
A25: Weekly Food Revenue | B25: =SUM(W2:W8) -> 60911.1
A26: Weekly Cost % | B26: =B22/B25 -> 0.24992308
A29: End of week status
A30: list items over $100
A31: Items carrying over | B31: Amount | C31: notes | D31: Expected use date
A32: Short ribs | B32: 1204.53 | D32: week of nov 13-nov 19
A33: White Truffle | B33: 417.12 | D33: week of nov 13-nov 19
A34: Caviar | B34: 345 | D34: week of nov 13-nov 19

Sheet Roister (1113-1119)
B1: CW | C1: Get Fresh | D1: Fortune | E1: Closed Loop | F1: A1 Firewood | G1: Allen Brother | H1: Wabash/Allen | I1: Superior | J1: Sysco | K1: Aya | L1: Rocker Bros | M1: D'artagnan | N1: Four Star | O1: Regalis | P1: D'amatos | Q1: Honey | R1: Cornille | S1: Murphy | T1: Truffles | U1: Rare Tea Cellar | V1: Steve's | W1: Breakthru | X1: Vintage Wines | Y1: Daily Spend | Z1: Daily Revenue | AA1: Daily Cost %
A2: 45243 | B2: =1926.55-14.18-29.8-8.55-13.06-33.12 -> 1827.84 | D2: =448.63-80.6+460.8-119.6 -> 709.23 | F2: 180 | G2: =602.27*2 -> 1204.54 | H2: 487.73 | N2: 168 | T2: 417.12 | V2: 57.05 | Y2: =SUM(B2:X2) -> 5051.51 | Z2: 4923.62 | AA2: =Y2/Z2 -> 1.0259748 | AB2: =A2 -> 45243
A3: 45244 | B3: =1229.8-312.48-40.99 -> 876.33 | D3: =809.17-590.97-161.2 -> 57 | J3: 185.24 | O3: =345+387 -> 732 | Y3: =SUM(B3:X3) -> 1850.57 | Z3: 11971 | AA3: =Y3/Z3 -> 0.15458775 | AB3: =A3 -> 45244
A4: 45245 | B4: =1381.62-31.75-75.3-110-8.23-36.25-60.6-92.64-81.83-53.15-228-83.15 -> 520.72 | D4: =226.6+213.6-110.8+33.6 -> 363 | I4: =1220.6-190-567.6 -> 463 | K4: 42 | P4: 18.5 | V4: 57.05 | Y4: =SUM(B4:X4) -> 1464.27 | Z4: =1041.01+7233 -> 8274.01 | AA4: =Y4/Z4 -> 0.17697223 | AB4: =A4 -> 45245
A5: 45246 | B5: =2023.66-58.57-39.8-67.76-8.6-31.75-33.54-16.89-245.6-14.91-46.18-40.73-38.34-7.23-51.25-30.1-24.7 -> 1267.71 | D5: 284.1 | F5: 180 | P5: 18.5 | Y5: =SUM(B5:X5) -> 1750.31 | Z5: 7877 | AA5: =Y5/Z5 -> 0.22220515 | AB5: =A5 -> 45246
A6: 45247 | B6: =1421.86-14.09-35.79-12.91-15.98-44.67-59.96-33.76-33.88-121.64 -> 1049.18 | C6: 98.2 | D6: =283.8-139.4 -> 144.4 | H6: =379.76-119.68-133.04 -> 127.04 | K6: 123 | P6: 18.5 | V6: 57.05 | Y6: =SUM(B6:X6) -> 1617.37 | Z6: =641+8276 -> 8917 | AA6: =Y6/Z6 -> 0.18138051 | AB6: =A6 -> 45247
A7: 45248 | B7: =918.88-102.37-55.75-38.95-70.39-82.53 -> 568.89 | C7: =293.55-133.8 -> 159.75 | D7: =213.9-80.6+1207.4 -> 1340.7 | H7: 311.58 | Q7: 252 | Y7: =SUM(B7:X7) -> 2632.92 | Z7: 14091 | AA7: =Y7/Z7 -> 0.18685118 | AB7: =A7 -> 45248
A8: 45249 | B8: N/A | C8: N/A | D8: N/A | E8: N/A | F8: N/A | H8: N/A | I8: N/A | K8: N/A | L8: N/A | M8: N/A | N8: N/A | O8: N/A | R8: N/A | T8: N/A | U8: N/A | V8: N/A | X8: N/A | Y8: 0 | Z8: 6357.81 | AA8: =Y8/Z8 -> 0 | AB8: =A8 -> 45249
A10: Spend per COGS | B10: 6695.51 | C10: 257.95 | D10: 2893.43 | F10: 360 | G10: 1204.53 | H10: 931.04 | I10: 463 | J10: 438.33 | K10: 165 | L10: 345 | N10: 168 | O10: 732 | P10: 55.5 | R10: 490 | S10: 114.1 | T10: 417.12 | V10: 171.15 | W10: 171.03 | X10: 131.74
A12: Difference | B12: =B10-sum(B2:B7) -> 584.84 | C12: =C10-sum(C2:C7) -> 0 | D12: =D10-sum(D2:D7) -> -5 | E12: =E10-sum(E2:E7) -> 0 | F12: =F10-sum(F2:F7) -> 0 | G12: =G10-sum(G2:G7) -> -0.01 | H12: =H10-sum(H2:H7) -> 4.69 | I12: =I10-sum(I2:I7) -> 0 | ... X12: =X10-sum(X2:X7) -> 131.74
A13: Amounts subtracted from invoices
A14: Family | B14: =14.18+29.8+8.55+13.06+60.6+92.64+33.88+14.91+46.18+40.73+38.34+7.23+14.09+33.12+40.99+51.25+30.1+24.7+197.07+42.37 -> 833.79 | D14: =119.6+110.8 -> 230.4
A15: SCSC | B15: =31.75+75.3+110+8.23+36.25+228+39.8+33.88+8.6+31.75+58.57+33.54+16.89+35.79+12.91+15.98+44.67+59.96+33.76+33.88+83.15+121.64+40.6 -> 1194.9 | C15: 133.8 | D15: =80.6+161.2+139.04+80.6 -> 461.44 | H15: =119.68+133.04 -> 252.72 | I15: 190 | N15: 156
A16: Mijenta Event
A17: Thanksgiving | B17: =81.83+53.15+70.39 -> 205.37
A18: Return | B18: =312.48+245.6 -> 558.08 | N18: 144
A21: Budget | B21: 13000
A22: Total Weekly Spend | B22: =SUM(B2:X8) -> 14366.95
A23: Remaing Spend | B23: =SUM(B21-B22) -> -1366.95
A25: Weekly Food Revenue | B25: =SUM(Z2:Z8) -> 62411.44
A26: Weekly Cost % | B26: =B22/B25 -> 0.23019738
A29: End of week status
A30: list items over $100
A31: Items carrying over | B31: Amount | D31: notes | E31: Expected use date
A32: Caviar | B32: 387 | E32: week of nov 20-nov 26
A33: Jamon Iberico | B33: 590.17 | E33: week of nov 13-dec 3
A34: Hamachi collar | B34: 567.6 | E34: week of nov 13-dec 3

Sheet  Roister (1120-1126)
B1: CW | C1: Get Fresh | D1: Fortune | E1: Closed Loop | F1: A1 Firewood | G1: Allen Brother | H1: Wabash/Allen | I1: Superior | J1: Sysco | K1: Aya | L1: Rocker Bros | M1: D'artagnan | N1: Four Star | O1: Regalis | P1: D'amatos | Q1: Honey | R1: Cornille | S1: Murphy | T1: Truffles | U1: Rare Tea Cellar | V1: Steve's | W1: Breakthru | X1: Vintage Wines | Y1: Daily Spend | Z1: Daily Revenue | AA1: Daily Cost %
A2: 45250 | B2: =1007.19-31.75 -> 975.44 | D2: =465.8-119.6 -> 346.2 | F2: 180 | N2: 168 | V2: 57.05 | Y2: =SUM(B2:X2) -> 1726.69 | Z2: 4189.4 | AA2: =Y2/Z2 -> 0.41215687 | AB2: =A2 -> 45250
A3: 45251 | K3: 42 | Y3: =SUM(B3:X3) -> 42 | AA3: =Y3/Z3 -> #DIV/0! | AB3: =A3 -> 45251
A4: 45252 | D4: 465.8 | V4: 57.05 | Y4: =SUM(B4:X4) -> 522.85 | AA4: =Y4/Z4 -> #DIV/0! | AB4: =A4 -> 45252
A5: 45253 | P5: 18.5 | Y5: =SUM(B5:X5) -> 18.5 | AA5: =Y5/Z5 -> #DIV/0! | AB5: =A5 -> 45253
A6: 45254 | F6: 180 | K6: 61.5 | V6: 57.05 | Y6: =SUM(B6:X6) -> 298.55 | AA6: =Y6/Z6 -> #DIV/0! | AB6: =A6 -> 45254
A7: 45255 | B7: =2228.43-16.81-27.65-32.92-39.58-8.51-152-46.24 -> 1904.72 | D7: 817.92 | H7: 283.26 | Y7: =SUM(B7:X7) -> 3005.9 | Z7: 8311.5 | AA7: =Y7/Z7 -> 0.36165554 | AB7: =A7 -> 45255
A8: 45256 | B8: N/A | C8: N/A | D8: N/A | E8: N/A | F8: N/A | G8: N/A | H8: N/A | I8: N/A | K8: N/A | L8: N/A | M8: N/A | N8: N/A | O8: N/A | R8: N/A | T8: N/A | U8: N/A | V8: N/A | X8: N/A | Y8: 0 | Z8: =1896+4473.81 -> 6369.81 | AA8: =Y8/Z8 -> 0 | AB8: =A8 -> 45256
A10: Amounts subtracted from invoices
A11: Family | D11: 119.6
A12: SCSC | B12: =16.81+27.65+32.92+39.58+152+31.75 -> 300.71 | N12: =156 -> 156
A13: Mijenta Event
A14: Thanksgiving
A15: Return
A18: Budget | B18: 13000
A19: Total Weekly Spend | B19: =SUM(B2:X8) -> 5614.49
A20: Remaing Spend | B20: =SUM(B18-B19) -> 7385.51
A22: Weekly Food Revenue | B22: =SUM(Z2:Z8) -> 18870.71
A23: Weekly Cost % | B23: =B19/B22 -> 0.29752405
A26: End of week status
A27: list items over $100
A28: Items carrying over | B28: Amount | D28: notes | E28: Expected use date
A29: Caviar | B29: 387 | E29: week of nov 20-nov 26
A30: Jamon Iberico | B30: 590.17 | E30: week of nov 13-dec 3
A31: Hamachi collar | B31: 567.6 | E31: week of nov 13-dec 3
A32: Short Ribs | B32: 1341.83 | E32: week of nov 27-dec 10
B34: =B31/2 -> 283.8

Sheet Roister (1127-1203)
B1: CW | C1: Get Fresh | D1: Fortune | E1: Closed Loop | F1: A1 Firewood | G1: Allen Brother | H1: Wabash/Allen | I1: Superior | J1: Sysco | K1: Aya | L1: Rocker Bros | M1: D'artagnan | N1: Four Star | O1: Regalis | P1: D'amatos | Q1: Honey | R1: Cornille | S1: Murphy | T1: Truffles | U1: Rare Tea Cellar | V1: Steve's | W1: Breakthru | X1: Vintage Wines | Y1: Daily Spend | Z1: Daily Revenue | AA1: Daily Cost %
A2: 45257 | B2: =2305.31-151.46-24.79-47.03-486.56-26.31-26.61-111.63-19.65-37.28-67.1-28.96-25-45.75 -> 1207.18 | D2: =239.2+521.28-100.1 -> 660.38 | F2: 180 | H2: 459.43 | N2: 168 | U2: 208.5 | V2: 57.05 | Y2: =SUM(B2:X2) -> 2940.54 | Z2: 3255 | AA2: =Y2/Z2 -> 0.90339171 | AB2: =A2 -> 45257
A3: 45258 | B3: =471.96-29.29-55.75-28.18 -> 358.74 | C3: =394.35-29 -> 365.35 | D3: 191.95 | O3: 60 | Y3: =SUM(B3:X3) -> 976.04 | Z3: 7093 | AA3: =Y3/Z3 -> 0.13760609 | AB3: =A3 -> 45258
A4: 45259 | B4: =1229.86-29.42-52.44-19.18-34.2-27.19-39.24-39.24-48.02-37.66 -> 903.27 | D4: =424.6-82.2 -> 342.4 | I4: =364-99 -> 265 | K4: 42 | V4: 57.05 | Y4: =SUM(B4:X4) -> 1609.72 | Z4: =506+4345.8 -> 4851.8 | AA4: =Y4/Z4 -> 0.3317779 | AB4: =A4 -> 45259
A5: 45260 | B5: =2199.51-20.7-12.91-10.84-79.48-49.95-50.18-83.16-33.55-38-38-41.43-46.32-26.61 -> 1668.38 | D5: 238.79 | H5: 126.86 | Y5: =SUM(B5:X5) -> 2034.03 | Z5: 4829 | AA5: =Y5/Z5 -> 0.42121143 | AB5: =A5 -> 45260
A6: 45261 | B6: =998.13-45-58.57-29-2.99-7.01-35.05-33.55-47.03 -> 739.93 | D6: =227.46-105.2 -> 122.26 | F6: 180 | I6: =770.8-190-283.8 -> 297 | K6: 123 | P6: 18.5 | V6: 57.05 | Y6: =SUM(B6:X6) -> 1537.74 | Z6: =1175.2+9535 -> 10710.2 | AA6: =Y6/Z6 -> 0.14357715 | AB6: =A6 -> 45261
A7: 45262 | B7: =1001.3-47.12-32.68-121.64-13.06 -> 786.8 | C7: =625.8-39.45-20.1-29-12.2-15.9-133.8-28.5-43 -> 303.85 | D7: =409.5+1256.58 -> 1666.08 | Y7: =SUM(B7:X7) -> 2756.73 | Z7: =2152.5+8481.5 -> 10634 | AA7: =Y7/Z7 -> 0.25923735 | AB7: =A7 -> 45262
A8: 45263 | C8: N/A | D8: N/A | E8: N/A | F8: N/A | G8: N/A | H8: N/A | I8: N/A | J8: N/A | K8: N/A | L8: N/A | M8: N/A | N8: N/A | O8: N/A | P8: N/A | Q8: N/A | R8: N/A | S8: N/A | T8: N/A | U8: N/A | V8: N/A | W8: N/A | X8: N/A | Y8: 0 | Z8: =2551.2+2747.5 -> 5298.7 | AA8: =Y8/Z8 -> 0 | AB8: =A8 -> 45263
A10: Spend per cogs | B10: 6475.51 | C10: 669.2 | D10: 3408.85 | G10: 670.92 | H10: 616.31 | I10: 562 | K10: 165 | N10: 168 | O10: 60 | R10: 280 | U10: 208.5 | V10: 171.15
A11: Difference | B11: =sum(B2:B8)-B10 -> -811.21 | C11: =sum(C2:C8)-C10 -> 0 | D11: =sum(D2:D8)-D10 -> -186.99 | G11: =sum(G2:G8)-G10 -> -670.92 | H11: =sum(H2:H8)-H10 -> -30.02 | I11: =sum(I2:I8)-I10 -> 0 | K11: =sum(K2:K8)-K10 -> 0 | N11: =sum(N2:N8)-N10 -> 0 | O11: =sum(O2:O8)-O10 -> 0 | R11: =sum(R2:R8)-R10 -> -280 | U11: =sum(U2:U8)-U10 -> 0 | V11: =sum(V2:V8)-V10 -> 0
A12: Amounts subtracted from invoices
A13: Family | B13: =111.63+37.66+39.74+7.01+35.05+24.79+28.18+29.42+27.19+48.02+46.32+47.03+47.12+32.68+121.64+13.06 -> 696.54 | C13: =29+39.45+20.1+29+28.5+43 -> 189.05 | D13: =82.2+105.2 -> 187.4
A14: SCSC | B14: =+486.56+52.44+19.18+34.2+39.24+12.91+10.84+39.74+49.95+58.57+29.29+29+33.55 -> 895.47 | C14: =12.2+15.9+133.8 -> 161.9 | D14: =+100.1+191.95 -> 292.05 | I14: =99+190 -> 289 | N14: 156
A15: Mijenta Event
A16: Negroni dinner | B16: =26.31+26.61+19.65+37.28+55.75+39.24+50.18+83.16+33.55+38+38+47.03+67.1+67.1+28.96+25+45.75+41.43+26.61 -> 796.71
A17: Return | B17: =151.46+20.7+45+2.99 -> 220.15
A20: Budget | B20: 13000
A21: Total Weekly Spend | B21: =SUM(B2:X8) -> 11854.8
A22: Remaing Spend | B22: =SUM(B20-B21) -> 1145.2
A24: Weekly Food Revenue | B24: =SUM(Z2:Z8) -> 46671.7
A25: Weekly Cost % | B25: =B21/B24 -> 0.25400403
A28: End of week status
A29: list items over $100
A30: Items carrying over | B30: Amount | D30: notes | E30: Expected use date
A31: Jamon Iberico | B31: 590.17 | E31: week of dec 04-dec 10
A32: Hamachi collar | B32: 851.4 | E32: week of dec 04-dec 10
A33: Short Ribs | B33: 1341.83 | E33: week of nov 27-dec 10
A34: Caviar | B34: 387 | E34: week of nov 27-dec 10

Sheet Roister (1204-1210)
B1: CW | C1: Get Fresh | D1: Fortune | E1: Closed Loop | F1: A1 Firewood | G1: Allen Brother | H1: Wabash/Allen | I1: Superior | J1: Sysco | K1: Aya | L1: Rocker Bros | M1: D'artagnan | N1: Four Star | O1: Regalis | P1: D'amatos | Q1: Honey | R1: Cornille | S1: Murphy | T1: Truffles | U1: Rare Tea Cellar | V1: Steve's | W1: Breakthru | X1: Vintage Wines | Y1: Daily Spend | Z1: Daily Revenue | AA1: Daily Cost %
A2: 45264 | B2: =1116.8-6.95-55.36-59.96-20.44-42.96-40.3-241.43-50.18 -> 599.22 | C2: =432.3-23.5-21.25 -> 387.55 | D2: =52.99+460.8-239.2+244.52-62.5 -> 456.61 | F2: 180 | H2: 247.91 | I2: 851.4 | N2: 168 | O2: 387 | V2: 57.05 | Y2: =SUM(B2:X2) -> 3334.74 | Z2: 3223 | AA2: =Y2/Z2 -> 1.0346696 | AB2: =A2 -> 45264
A3: 45265 | C3: =354-25.5-10.25--23.5-25.5-37.5-42.55 -> 236.2 | Y3: =SUM(B3:X3) -> 236.2 | Z3: 6412 | AA3: =Y3/Z3 -> 0.03683718 | AB3: =A3 -> 45265
A4: 45266 | B4: =992.6-8.15-49.42-33.04-46.24-33.55-12.17-33.62-32.44-117.48-140.52-55.75-62.89 -> 367.33 | C4: =659.98-24-27-82.98-254.1 -> 271.9 | D4: =370.9-123.3+215.4-138+332.4-166.2 -> 491.2 | F4: 360 | H4: 169.8 | I4: =503.5-99 -> 404.5 | K4: 42 | P4: 18.5 | V4: 57.05 | Y4: =SUM(B4:X4) -> 2182.28 | Z4: =302.5+4658.4 -> 4960.9 | AA4: =Y4/Z4 -> 0.43989599 | AB4: =A4 -> 45266
A5: 45267 | B5: =729.15-25.58-55-33.94-27.41-45.92-10.8-6.23-87.85 -> 436.42 | P5: 18.5 | Y5: =SUM(B5:X5) -> 454.92 | Z5: 6162.2 | AA5: =Y5/Z5 -> 0.073824284 | AB5: =A5 -> 45267
A6: 45268 | B6: =896.76-14.2-8.15-11-33.62-15.14-61.92-33.71-33.79-50.18-14.44-6.8 -> 613.81 | C6: =788.37-23.88-27-84.7 -> 652.79 | D6: 249.49 | F6: 180 | I6: =720.3-283.8 -> 436.5 | K6: 123 | P6: 18.5 | V6: 57.05 | Y6: =SUM(B6:X6) -> 2331.14 | Z6: =962+9137 -> 10099 | AA6: =Y6/Z6 -> 0.23082879 | AB6: =A6 -> 45268
A7: 45269 | B7: =230.33-23.09-36.28-14.13-96.6-17.16-27.65-12.17+892.38-40.16-100.76-6.72-40.91-17.22-47.03 -> 642.83 | C7: 234 | D7: =128.3+29.6+94.8 -> 252.7 | H7: 186.61 | Y7: =SUM(B7:X7) -> 1316.14 | Z7: 13791 | AA7: =Y7/Z7 -> 0.095434704 | AB7: =A7 -> 45269
A8: 45270 | B8: 590 | C8: N/A | D8: 1310.49 | E8: N/A | F8: N/A | G8: 670.92 | H8: N/A | I8: N/A | J8: N/A | K8: N/A | L8: N/A | M8: N/A | N8: N/A | O8: N/A | P8: N/A | Q8: N/A | R8: N/A | S8: N/A | T8: N/A | U8: N/A | V8: N/A | W8: N/A | X8: N/A | Y8: =SUM(B8:X8) -> 2571.41 | Z8: =2787.1+2684 -> 5471.1 | AA8: =Y8/Z8 -> 0.46999872 | AB8: =A8 -> 45270
A10: Amounts subtracted from invoices
A11: Family | B11: =6.95+42.96+40.3+27.41+45.92+10.8+6.23+32.44+14.2+61.92+50.18+6.8+23.09+36.28+14.13+96.6+17.16+27.65+12.17+100.76+40.91 -> 714.86 | C11: =25.5+10.25+25.5+37.5+42.55+24+27+23.5+27 -> 242.8 | D11: =239.2+166.2 -> 405.4
A12: SCSC | B12: =8.15+49.42+33.04+46.24+33.55+12.17+33.62+25.58+55+33.94+8.15+11+33.62+15.14+33.71+55.75+62.89+87.85+33.79+50.18+14.44+40.16+6.72+17.22+47.03 -> 848.36 | C12: =82.98+254.1+23.88+84.7 -> 445.66 | D12: =62.5+123.3 -> 185.8 | I12: 99 | N12: =156+144 -> 300
A13: Mijenta Event
A14: Truffle dinner | B14: =59.96 -> 59.96 | C14: =23.5+21.25 -> 44.75
A15: Return | B15: =55.36+20.44 -> 75.8 | D15: 138
A18: Budget | B18: 13000
A19: Total Weekly Spend | B19: =SUM(B2:X8) -> 12426.83
A20: Remaing Spend | B20: =SUM(B18-B19) -> 573.17
A22: Weekly Food Revenue | B22: =SUM(Z2:Z8) -> 50119.2
A23: Weekly Cost % | B23: =B19/B22 -> 0.2479455
A26: End of week status
A27: list items over $100
A28: Items carrying over | B28: Amount | D28: notes | E28: Expected use date
A29: Short Ribs | B29: 670.92 | E29: week of nov 27-dec 10
A30: Aji panca-amarillo | B30: =117.48+140.52 -> 258 | E30: week of dec 11-dec 24
A31: Parmesan | B31: 241.43 | E31: week of dec 11-dec 24
A32: Short Ribs | B32: 1402.33 | E32: week of dec 11-dec 24
A33: Hamachi collar | B33: 283.8 | E33: week of dec 11-dec 24
A34: Caviar | B34: =185+285 -> 470 | E34: week of dec 11-dec 24

Sheet Roister (1211-1217)
B1: CW | C1: Get Fresh | D1: Fortune | E1: Closed Loop | F1: A1 Firewood | G1: Allen Brother | H1: Wabash/Allen | I1: Superior | J1: Sysco | K1: Aya | L1: Rocker Bros | M1: D'artagnan | N1: Four Star | O1: Regalis | P1: D'amatos | Q1: Honey | R1: Cornille | S1: Murphy | T1: Truffles | U1: Rare Tea Cellar | V1: Steve's | W1: Breakthru | X1: Vintage Wines | Y1: Daily Spend | Z1: Daily Revenue | AA1: Daily Cost %
A2: 45271 | B2: =1408.32-47.03-78.76-95.74-40.43 -> 1146.36 | D2: =227.88-170.88+460.8-221.6 -> 296.2 | F2: 180 | H2: 418.86 | I2: 283.8 | N2: 168 | O2: 470 | V2: 57.05 | Y2: =SUM(B2:X2) -> 3020.27 | Z2: 3099.6 | AA2: =Y2/Z2 -> 0.97440638 | AB2: =A2 -> 45271
A3: 45272 | B3: =616.42-46.32-33.55-13.52+200.22-27.41-26.12 -> 669.72 | D3: 457.99 | Y3: =SUM(B3:X3) -> 1127.71 | Z3: 4908 | AA3: =Y3/Z3 -> 0.22976976 | AB3: =A3 -> 45272
A4: 45273 | B4: =1374.3-40.16-33.95-36.78-34.32-54.76-52.51-59.4-79.9-52.01-46.24-27.65-30.01-59.88 -> 766.73 | C4: =707.83-82.98-381.15 -> 243.7 | D4: =543.59-120.6-60.38-362.61+460.8 -> 460.8 | I4: =1013.31-198-190-283.8 -> 341.51 | K4: 42 | P4: 18.5 | V4: 57.05 | Y4: =SUM(B4:X4) -> 1930.29 | Z4: 7959.6 | AA4: =Y4/Z4 -> 0.24251093 | AB4: =A4 -> 45273
A5: 45274 | B5: =2886.76-77.5-11.75-55-27.6-12.91-87-44-29.75-27.41-80.86-1098.03-7.85-32.98-14.02 -> 1280.1 | F5: 180 | H5: =265.75-101.46 -> 164.29 | P5: 18.5 | U5: 184.85 | Y5: =SUM(B5:X5) -> 1827.74 | Z5: =2786+8045 -> 10831 | AA5: =Y5/Z5 -> 0.16875081 | AB5: =A5 -> 45274
A6: 45275 | B6: =6.17+2106.19-100.83-155.52-87.85-57.5-96.04-29-64-80.86-162.29-65.32-51.47 -> 1161.68 | D6: =290.83+94.8 -> 385.63 | I6: 297 | K6: 123 | P6: 18.5 | V6: 57.05 | Y6: =SUM(B6:X6) -> 2042.86 | Z6: =1251+15321.5 -> 16572.5 | AA6: =Y6/Z6 -> 0.12326806 | AB6: =A6 -> 45275
A7: 45276 | B7: =1000.57-59.96-55-100.34-14.2-12.78-13.06 -> 745.23 | C7: =629.69-41.2-38.6-22.05 -> 527.84 | D7: =731.25-120.6-62.45 -> 548.2 | H7: 169.36 | N7: 84 | Y7: =SUM(B7:X7) -> 2074.63 | Z7: =2623.5+11683 -> 14306.5 | AA7: =Y7/Z7 -> 0.14501311 | AB7: =A7 -> 45276
A8: 45277 | B8: =241.43+258 -> 499.43 | C8: N/A | D8: 1332 | E8: N/A | F8: N/A | G8: 670.92 | H8: N/A | I8: N/A | J8: N/A | K8: N/A | L8: N/A | M8: N/A | N8: N/A | O8: N/A | P8: N/A | Q8: N/A | R8: N/A | S8: N/A | T8: N/A | U8: N/A | V8: N/A | W8: N/A | X8: N/A | Y8: =SUM(B8:X8) -> 2502.35 | Z8: 6831 | AA8: =Y8/Z8 -> 0.36632265 | AB8: =A8 -> 45277
A10: Amounts subtracted from invoices
A11: Family | B11: =47.03+78.76+95.74+40.43+26.12+13.52+33.95+27.65+59.88+27.41+7.85+32.98+14.02+27.41+29+40.43++155.52+96.04+59.96+55+100.34+14.2+12.78+13.06 -> 1109.08 | C11: =41.2+38.6 -> 79.8 | D11: =221.6+120.6 -> 342.2
A12: SCSC | B12: =46.32+33.55+40.16+36.78+34.32+54.76+52.51+59.4+52.01+46.24+77.5+11.75+55+27.6+12.91+87+44+29.75+80.86+87.85+57.5+64+40.43+162.29+65.32 -> 1359.81 | C12: =381.15+82.98+22.05 -> 486.18 | D12: =60.38+120.6+62.45 -> 243.43 | H12: 101.46 | I12: =198+190 -> 388 | N12: =144+156 -> 300
A13: Mijenta Event
A14: Bar | B14: 30.01
A15: Return | B15: =79.9+100.83+51.47 -> 232.2
A18: Budget | B18: 13000
A19: Total Weekly Spend | B19: =SUM(B2:X8) -> 14525.85
A20: Remaing Spend | B20: =SUM(B18-B19) -> -1525.85
A22: Weekly Food Revenue | B22: =SUM(Z2:Z8) -> 64508.2
A23: Weekly Cost % | B23: =B19/B22 -> 0.22517835
A26: End of week status
A27: list items over $100
A28: Items carrying over | B28: Amount | D28: notes | E28: Expected use date
A29: Short Ribs | B29: 1402.33 | E29: week of dec 11-dec 24
A30: Foie Grass | B30: 170.88 | E30: week of dec 11-dec 24
A31: Pork Belly | B31: 362.61 | E31: week of dec 11-dec 24
A32: Hamachi collar | B32: =283.8+283.8 -> 567.6 | E32: week of dec 11-dec 24
A33: Jamon Iberico de Bellota | B33: 1098.03 | E33: week of dec 11-ene 07
A34: Caviar | B34: 317 | E34: week of dec 11-dec 24

Sheet Roister (1218-1224)
B1: CW | C1: Get Fresh | D1: Fortune | E1: Closed Loop | F1: A1 Firewood | G1: Allen Brother | H1: Wabash/Allen | I1: Superior | J1: Sysco | K1: Aya | L1: Rocker Bros | M1: D'artagnan | N1: Four Star | O1: Regalis | P1: D'amatos | Q1: Honey | R1: Cornille | S1: Murphy | T1: Truffles | U1: Rare Tea Cellar | V1: Steve's | W1: Breakthru | X1: Vintage Wines | Y1: Daily Spend | Z1: Daily Revenue | AA1: Daily Cost %
A2: 45278 | B2: =1717.48-266-31.74-28.75+459.52-255.34+226.91 -> 1822.08 | D2: =460.8+772.7 -> 1233.5 | F2: 180 | H2: =294.93 -> 294.93 | N2: 168 | O2: 123 | V2: 57.05 | Y2: =SUM(B2:X2) -> 3878.56 | Z2: 5033 | AA2: =Y2/Z2 -> 0.77062587 | AB2: =A2 -> 45278
A3: 45279 | B3: =1491.18-193.2-8.52-15.5 -> 1273.96 | D3: =374.27 -> 374.27 | H3: 170.25 | I3: 567.6 | O3: 520 | R3: 115 | Y3: =SUM(B3:X3) -> 3021.08 | Z3: 13425 | AA3: =Y3/Z3 -> 0.22503389 | AB3: =A3 -> 45279
A4: 45280 | B4: =700.17-34.25-12.88-28.26-79.6 -> 545.18 | D4: =493.33-66.13 -> 427.2 | I4: =570.5-99 -> 471.5 | K4: 42 | P4: 18.5 | V4: 57.05 | Y4: =SUM(B4:X4) -> 1561.43 | Z4: =1678+13875 -> 15553 | AA4: =Y4/Z4 -> 0.10039414 | AB4: =A4 -> 45280
A5: 45281 | B5: =309.64-29.82-30.12+157.43-56.4-109.43+1076.42-12.91-32-46.24-27.87-27.87-109.43-14.2-36.3 -> 1010.9 | F5: 180 | P5: 18.5 | Y5: =SUM(B5:X5) -> 1209.4 | Z5: =1232+7074 -> 8306 | AA5: =Y5/Z5 -> 0.14560559 | AB5: =A5 -> 45281
A6: 45282 | B6: =1278.54-43.5-82.86-52.71-36.67 -> 1062.8 | D6: =581.06-44.08-304 -> 232.98 | K6: 123 | P6: 18.5 | V6: 57.05 | Y6: =SUM(B6:X6) -> 1494.33 | Z6: =1115+10067.43 -> 11182.43 | AA6: =Y6/Z6 -> 0.13363196 | AB6: =A6 -> 45282
A7: 45283 | B7: =1075.46-7.37-11-21.95-221.62-14.14-72.56 -> 726.82 | D7: =533.49 -> 533.49 | I7: 567.6 | Y7: =SUM(B7:X7) -> 1827.91 | Z7: =2723.5+9110.5 -> 11834 | AA7: =Y7/Z7 -> 0.15446257 | AB7: =A7 -> 45283
A8: 45284 | B8: 1402.33 | C8: N/A | D8: 860 | E8: N/A | F8: N/A | G8: N/A | H8: N/A | I8: N/A | J8: N/A | K8: N/A | L8: N/A | M8: N/A | N8: N/A | O8: 317 | P8: N/A | Q8: N/A | R8: N/A | S8: N/A | T8: N/A | U8: N/A | V8: N/A | W8: N/A | X8: N/A | Y8: =SUM(B8:X8) -> 2579.33 | Z8: 0 | AA8: =Y8/Z8 -> #DIV/0! | AB8: =A8 -> 45284
A10: Amounts subtracted from invoices
A11: Family | B11: =255.34+193.2+8.52+15.5+34.25+12.88+29.82+30.12+56.4+27.87+36.3+36.67+72.56 -> 809.43
A12: SCSC | B12: =266+31.74+28.75+28.26+79.6+12.91+32+46.24+27.87+109.43+14.2+43.5+52.71+7.37+11+21.95+221.62+14.14 -> 1049.29 | D12: 44.08 | I12: 99 | N12: =144+156 -> 300
A13: Mijenta Event
A14: Bar
A15: Return | B15: =109.43+82.86 -> 192.29 | D15: 304
A18: Budget | B18: 13000
A19: Total Weekly Spend | B19: =SUM(B2:X8) -> 15572.04
A20: Remaing Spend | B20: =SUM(B18-B19) -> -2572.04
A22: Weekly Food Revenue | B22: =SUM(Z2:Z8) -> 65333.43
A23: Weekly Cost % | B23: =B19/B22 -> 0.2383472
A26: End of week status
A27: list items over $100
A28: Items carrying over | B28: Amount | D28: notes | E28: Expected use date
A29: Jamon Iberico de Bellota | B29: 1098.03 | E29: week of dec 11-ene 07

Sheet Roister (1225-1231)
B1: CW | C1: Get Fresh | D1: Fortune | E1: Closed Loop | F1: A1 Firewood | G1: Allen Brother | H1: Wabash/Allen | I1: Superior | J1: Sysco | K1: Aya | L1: Rocker Bros | M1: D'artagnan | N1: Four Star | O1: Regalis | P1: D'amatos | Q1: Honey | R1: Cornille | S1: Murphy | T1: Truffles | U1: Rare Tea Cellar | V1: Steve's | W1: Breakthru | X1: Vintage Wines | Y1: Daily Spend | Z1: Daily Revenue | AA1: Daily Cost %
A2: 45285 | G2: 1407.69 | Y2: =SUM(B2:X2) -> 1407.69 | Z2: 0 | AA2: =Y2/Z2 -> #DIV/0! | AB2: =A2 -> 45285
A3: 45286 | B3: =972-228-155.52-19.62-35.97-23.61-32-7.84-70.56 -> 398.88 | C3: =390-15.6-37-38.5 -> 298.9 | D3: =229.1+29 -> 258.1 | F3: 180 | N3: 168 | O3: 305 | Y3: =SUM(B3:X3) -> 1608.88 | Z3: 5145.4 | AA3: =Y3/Z3 -> 0.31268317 | AB3: =A3 -> 45286
A4: 45287 | B4: =1110.14-42.06-28.28-27.65-34.4-26.13-8 -> 943.62 | C4: 531.8 | D4: =313.14-123.3 -> 189.84 | H4: 169.36 | I4: =580.8-198 -> 382.8 | K4: 42 | O4: 33.5 | P4: 18.5 | Q4: 252 | U4: 151 | V4: 57.05 | Y4: =SUM(B4:X4) -> 2771.47 | Z4: =906+6762 -> 7668 | AA4: =Y4/Z4 -> 0.36143323 | AB4: =A4 -> 45287
A5: 45288 | B5: =2782.83-30.77-93.39-25.82-28.26-44-47.61-87-54-38.34-34.8-98.1-110-83-40.16-65.98 -> 1901.6 | D5: =1306.94-120.6-348.64-60.95-29.5-79.75 -> 667.5 | F5: 180 | H5: 345.31 | P5: 18.5 | Y5: =SUM(B5:X5) -> 3112.91 | Z5: =561+7086.8 -> 7647.8 | AA5: =Y5/Z5 -> 0.4070334 | AB5: =A5 -> 45288
A6: 45289 | B6: =1602.68-79.6-62.07-34.97-47.61-155.52-100.36-145-23.12-64.93 -> 889.5 | C6: 413.15 | D6: =852.49-105.2-292+251.6 -> 706.89 | I6: 495 | K6: 123 | P6: 18.5 | V6: 57.05 | Y6: =SUM(B6:X6) -> 2703.09 | Z6: =1463+5982 -> 7445 | AA6: =Y6/Z6 -> 0.36307455 | AB6: =A6 -> 45289
A7: 45290 | B7: =1093.97-18.61-39.43-23.11-37.77-26.16-155.52 -> 793.37 | C7: =514.4-19.85-21.2-25.9-130 -> 317.45 | F7: 180 | I7: 958 | N7: 420 | O7: 397.5 | R7: 70 | Y7: =SUM(B7:X7) -> 3136.32 | Z7: =3349.15+10380 -> 13729.15 | AA7: =Y7/Z7 -> 0.2284424 | AB7: =A7 -> 45290
A8: 45291 | B8: 1098.03 | C8: N/A | D8: 860 | E8: N/A | F8: N/A | G8: N/A | H8: N/A | I8: N/A | J8: N/A | K8: N/A | L8: N/A | M8: N/A | N8: N/A | P8: N/A | Q8: N/A | R8: N/A | S8: N/A | T8: N/A | U8: N/A | V8: N/A | W8: N/A | X8: N/A | Y8: =SUM(B8:X8) -> 1958.03 | Z8: =4916+24150 -> 29066 | AA8: =Y8/Z8 -> 0.067364963 | AB8: =A8 -> 45291
A10: Amounts subtracted from invoices
A11: Family | B11: =35.97+42.06+27.65+34.4+26.13+30.77+12.91+65.98+7.84+70.56 -> 354.27 | C11: =15.6+37+38.5+19.85+21.2+25.9+130 -> 288.05 | D11: 105.2
A12: SCSC | B12: =228+155.52+19.62+23.61+32+28.28+12.91+28.26+47.61+83+40.16+47.61+145+23.12+18.61+39.43+23.11+37.77+26.16+155.52 -> 1215.3 | D12: =123.3+120.6+86+60.95 -> 390.85 | H12: 198 | I12: =198+190 -> 388 | N12: 300
A13: Macallan | B13: =44+54+38.34+34.8+98.1+110+79.6+62.07+34.97+155.52+100.36+64.93 -> 876.69 | D13: =263+29.5+292 -> 584.5 | G13: 1483.31
A14: Bar
A15: Return | B15: =8+93.39+87 -> 188.39 | D15: 79.75
A18: Budget | B18: 13000
A19: Total Weekly Spend | B19: =SUM(B2:X8) -> 16698.39
A20: Remaing Spend | B20: =SUM(B18-B19) -> -3698.39
A22: Weekly Food Revenue | B22: =SUM(Z2:Z8) -> 70701.35
A23: Weekly Cost % | B23: =B19/B22 -> 0.23618205
A26: End of week status
A27: list items over $100
A28: Items carrying over | B28: Amount | D28: notes | E28: Expected use date

Sheet Roister (11-17)
B1: CW | C1: Get Fresh | D1: Fortune | E1: Closed Loop | F1: A1 Firewood | G1: Allen Brother | H1: Wabash/Allen | I1: Superior | J1: Sysco | K1: Aya | L1: Rocker Bros | M1: D'artagnan | N1: Four Star | O1: Regalis | P1: D'amatos | Q1: Honey | R1: Cornille | S1: Murphy | T1: Truffles | U1: Rare Tea Cellar | V1: Steve's | W1: Breakthru | X1: Vintage Wines | Y1: Daily Spend | Z1: Daily Revenue | AA1: Daily Cost %
A2: 45292 | Y2: =SUM(B2:X2) -> 0 | Z2: 0 | AA2: =Y2/Z2 -> #DIV/0! | AB2: =A2 -> 45292
A3: 45293 | B3: =2212.87-77.76-24.6-32-59.89-44-21.6 -> 1953.02 | C3: =279.3-211.75 -> 67.55 | D3: =449.6-239.2+669.5-248.5 -> 631.4 | F3: 180 | G3: =150.37+332.05 -> 482.42 | N3: 168 | Y3: =SUM(B3:X3) -> 3482.39 | Z3: 1505.5 | AA3: =Y3/Z3 -> 2.3131119 | AB3: =A3 -> 45293
A4: 45294 | B4: =13.64+935.48-28.28-162.29-45.06-34.1-33.71-25.82-180.87-46.21-37.77-24.6 -> 330.41 | C4: 202.3 | D4: =292.37-120.6-57.4-69.2 -> 45.17 | K4: 42 | P4: 18.5 | R4: 250 | V4: 57.05 | Y4: =SUM(B4:X4) -> 945.43 | Z4: =143+2918.6 -> 3061.6 | AA4: =Y4/Z4 -> 0.30880259 | AB4: =A4 -> 45294
A5: 45295 | B5: =1617.83-98.43-59.59-22-59.96-12.19-349-27.6-24.91-26.19-14.91-33.06-12.88-32.98-8.6-30.1-37.77-34.14 -> 733.52 | C5: =452.25-27-169.4 -> 255.85 | D5: =333.75-33.4-90.57-58.48 -> 151.3 | F5: 180 | I5: =1005.94-190 -> 815.94 | O5: 30 | P5: 18.5 | Y5: =SUM(B5:X5) -> 2185.11 | Z5: 3602 | AA5: =Y5/Z5 -> 0.60663798 | AB5: =A5 -> 45295
A6: 45296 | B6: =330.09-11.47-22.4-12.26-48.48-5.71-7.84+378.1-218 -> 382.03 | K6: 123 | P6: 18.5 | V6: 57.05 | Y6: =SUM(B6:X6) -> 580.58 | Z6: =821+6430.8 -> 7251.8 | AA6: =Y6/Z6 -> 0.080060123 | AB6: =A6 -> 45296
A7: 45297 | B7: =432.5 -> 432.5 | C7: =281.5-101.2 -> 180.3 | D7: 175.38 | F7: 588 | Y7: =SUM(B7:X7) -> 1376.18 | Z7: 12307 | AA7: =Y7/Z7 -> 0.11182091 | AB7: =A7 -> 45297
